Workbook

Sheet Index
B2: MATERIAL PRICE LIST & RATE DATABASE
B3: Saeed Al Siraj Glass & Aluminium Works L.L.C. | Estimation Department | Aluminium, Glass, MS & SS Works
B5: Rate validity / last reviewed: | D5: =Settings!C21 -> 09-Oct-2026 | F5: =HYPERLINK("#Search!C5",">> SEARCH MATERIAL <<") -> >> SEARCH MATERIAL <<
B6: VAT: | D6: =VAT -> 0.05
B7: Default O&P: | D7: =OHP -> 0.2 | F7: =HYPERLINK("#Settings!C6","Edit base rates / VAT / O&P") -> Edit base rates / VAT / O&P
B8: Total items: | D8: =COUNTA('ALL ITEMS'!D3:D764)-COUNTBLANK('ALL ITEMS'!D3:D764) -> 537 | F8: =HYPERLINK("#'ALL ITEMS'!A1","View master list (all items)") -> View master list (all items)
B10: No. | C10: Category | D10: Code | E10: Scope / Contents | F10: Items | G10: Open | H10: Sheet | K10: All Categories
B11: 1 | C11: Aluminium Profiles & Systems | D11: AL | E11: Extrusions by kg, standard sections, window/door/curtain wall/pergola profiles | F11: =COUNTA('01 Aluminium'!C5:C72) -> 53 | G11: =HYPERLINK("#'01 Aluminium'!A1","Open >") -> Open > | H11: 01 Aluminium | K11: Aluminium Profiles & Systems
B12: 2 | C12: Glass - Float, Tempered, Laminated & DGU | D12: GL | E12: Clear, tinted, reflective, tempered, laminated, insulated, low-E, low-iron, fire-rated | F12: =COUNTA('02 Glass'!C5:C73) -> 54 | G12: =HYPERLINK("#'02 Glass'!A1","Open >") -> Open > | H12: 02 Glass | K12: Glass - Float, Tempered, Laminated & DGU
B13: 3 | C13: Glass Processing & Fabrication Charges | D13: GP | E13: Edge work, holes, cut-outs, bevelling, sand-blasting, film, cutting & handling | F13: =COUNTA('03 Glass Processing'!C5:C42) -> 23 | G13: =HYPERLINK("#'03 Glass Processing'!A1","Open >") -> Open > | H13: 03 Glass Processing | K13: Glass Processing & Fabrication Charges
B14: 4 | C14: Mirrors | D14: MR | E14: Silver, coloured, safety-backed, bevelled, LED & framed mirrors | F14: =COUNTA('04 Mirrors'!C5:C36) -> 17 | G14: =HYPERLINK("#'04 Mirrors'!A1","Open >") -> Open > | H14: 04 Mirrors | K14: Mirrors
B15: 5 | C15: Hardware - Doors & Windows | D15: HW | E15: Floor springs, closers, locks, handles, hinges, rollers, friction stays, multipoint locks | F15: =COUNTA('05 Door & Window HW'!C5:C57) -> 38 | G15: =HYPERLINK("#'05 Door & Window HW'!A1","Open >") -> Open > | H15: 05 Door & Window HW | K15: Hardware - Doors & Windows
B16: 6 | C16: Glass Fittings - Partition, Shower & Spider | D16: GF | E16: Patch fittings, shower hinges, clamps, spider / routel, sliding glass systems | F16: =COUNTA('06 Glass Fittings HW'!C5:C49) -> 30 | G16: =HYPERLINK("#'06 Glass Fittings HW'!A1","Open >") -> Open > | H16: 06 Glass Fittings HW | K16: Glass Fittings - Partition, Shower & Spider
B17: 7 | C17: Balustrade & Handrail Components | D17: BH | E17: SS posts, glass clamps, spigots, standoffs, handrail brackets & end caps | F17: =COUNTA('07 Balustrade HW'!C5:C42) -> 23 | G17: =HYPERLINK("#'07 Balustrade HW'!A1","Open >") -> Open > | H17: 07 Balustrade HW | K17: Balustrade & Handrail Components
B18: 8 | C18: Sealants, Gaskets, Fixings & Consumables | D18: SF | E18: Silicones, foams, EPDM, tapes, anchors, screws, brackets, shims, tools & consumables | F18: =COUNTA('08 Sealants & Fixings'!C5:C65) -> 46 | G18: =HYPERLINK("#'08 Sealants & Fixings'!A1","Open >") -> Open > | H18: 08 Sealants & Fixings | K18: Sealants, Gaskets, Fixings & Consumables
B19: 9 | C19: Cladding, ACP & Facade Panels | D19: CL | E19: ACP, solid aluminium, perforated, louvered and HPL panels | F19: =COUNTA('09 Cladding & ACP'!C5:C36) -> 17 | G19: =HYPERLINK("#'09 Cladding & ACP'!A1","Open >") -> Open > | H19: 09 Cladding & ACP | K19: Cladding, ACP & Facade Panels
B20: 10 | C20: Mild Steel (MS) - Sections, Plates & Sheets | D20: MS | E20: SHS, RHS, angles, channels, beams, flats, rounds, pipes, plates, GI sheets, grating | F20: =COUNTA('10 Mild Steel'!C5:C82) -> 63 | G20: =HYPERLINK("#'10 Mild Steel'!A1","Open >") -> Open > | H20: 10 Mild Steel | K20: Mild Steel (MS) - Sections, Plates & Sheets
B21: 11 | C21: Stainless Steel (SS) - Tubes, Sheets & Drains | D21: SS | E21: SS 304 / 316 round, square & rectangular tubes, sheets, flats, rods, linear drains | F21: =COUNTA('11 Stainless Steel'!C5:C61) -> 42 | G21: =HYPERLINK("#'11 Stainless Steel'!A1","Open >") -> Open > | H21: 11 Stainless Steel | K21: Stainless Steel (SS) - Tubes, Sheets & Drains
B22: 12 | C22: Automatic Doors, Operators & Shutters | D22: AD | E22: Sliding / swing operators, sensors, access control, rolling shutters | F22: =COUNTA('12 Auto Doors & Shutters'!C5:C37) -> 18 | G22: =HYPERLINK("#'12 Auto Doors & Shutters'!A1","Open >") -> Open > | H22: 12 Auto Doors & Shutters | K22: Automatic Doors, Operators & Shutters
B23: 13 | C23: Coating, Finishing & Treatment Services | D23: CF | E23: Powder coating, anodizing, PVDF, galvanizing, painting, polishing (job-work rates) | F23: =COUNTA('13 Coating & Finishing'!C5:C36) -> 17 | G23: =HYPERLINK("#'13 Coating & Finishing'!A1","Open >") -> Open > | H23: 13 Coating & Finishing | K23: Coating, Finishing & Treatment Services
B24: 14 | C24: Labour, Equipment, Transport & Misc. Costs | D24: LB | E24: Manpower day rates, access equipment, cranes, transport, scaffolding, testing | F24: =COUNTA('14 Labour & Equipment'!C5:C59) -> 40 | G24: =HYPERLINK("#'14 Labour & Equipment'!A1","Open >") -> Open > | H24: 14 Labour & Equipment | K24: Labour, Equipment, Transport & Misc. Costs
B25: 15 | C25: Finished Systems - Budget Supply & Install Rates | D25: SI | E25: All-in budget rates for quick estimates (material + fabrication + installation) | F25: =COUNTA('15 System Rates S&I'!C5:C75) -> 56 | G25: =HYPERLINK("#'15 System Rates S&I'!A1","Open >") -> Open > | H25: 15 System Rates S&I | K25: Finished Systems - Budget Supply & Install Rates
C26: TOTAL | F26: =SUM(F11:F25) -> 537
B28: HOW TO USE
B29: 1. FIND: Go to 'Search' - type any keyword (size, brand, item) - results with rates appear instantly.
B30: 2. BROWSE: Click 'Open' above to go to a category sheet. Use the filter arrows on the header row.
B31: 3. UPDATE RATE: Type the new Basic Rate (blue) in the category sheet, set Rate Status, Supplier, Quote Ref & Date, then log it in 'Rate Log'.
B32: 4. ADD ITEM: Use the yellow spare rows at the bottom of each category sheet - the code, net, selling & VAT rates fill in automatically.
B33: 5. MARKET CHANGE: Change aluminium / steel / SS rate per kg, VAT or O&P in 'Settings' - all linked rates (green) update automatically.
B34: 6. NET COST RATE = Basic Rate x (1 + Wastage %). SELLING = Net Cost x (1 + O&P). SELLING incl. VAT = Selling x (1 + VAT).
B36: LEGEND
C37: Blue text | D37: Input / editable value
C38: Black text | D38: Formula - do not overwrite
C39: Green text | D39: Linked to Settings / another sheet
C40: Indicative | D40: Budget market rate - confirm before final quote
C41: Quoted | D41: Rate taken from a supplier quotation
C42: Verified | D42: Rate confirmed by recent purchase / LPO
C43: Obsolete | D43: Item no longer used (shown struck-through)
B45: UNITS
B46: m2 = square metre | lm = linear metre | kg = kilogram | nos = numbers | set / pair / pkt / box / roll | ltr = litre | day / hr / month / trip | ls = lump sum | % = percentage
B48: DISCLAIMER: Rates are indicative UAE market budget rates (Oct-2026) for estimation reference. Always confirm with current supplier quotations, project specification and quantities before submitting a final quotation.

Sheet Search
B2: QUICK MATERIAL SEARCH
B3: Type one or more words in any order (e.g. aluminium sheet, 12 tempered, floor spring, 316 tube, DGU low e) - every word must match the start of a word. Pick a category if needed. Results update instantly.
Q4: =TRIM(SUBSTITUTE(SUBSTITUTE(SUBSTITUTE(SUBSTITUTE(SUBSTITUTE(SUBSTITUTE(SUBSTITUTE(SUBSTITUTE(SUBSTITUTE(LOWER($C$5),"*","x"),"?"," "),"~"," "),"("," "),")"," "),"/"," "),"-"," "),","," "),";"," "))&" " -> aluminium sheet
A5: Search keyword: | C5: aluminium sheet | G5: Tip: clear the keyword to list a whole category. | P5: =IF(AND(LEN(R5)>3,RIGHT(R5,1)="s",RIGHT(R5,2)<>"ss"),LEFT(R5,LEN(R5)-1),R5) -> aluminium | Q5: =IFERROR(MID(Q4,FIND(" ",Q4)+1,999),"") -> sheet | R5: =IFERROR(LEFT(Q4,FIND(" ",Q4)-1),"") -> aluminium
A6: Category: | C6: All Categories | G6: Max 300 results shown - refine keyword if needed. | P6: =IF(AND(LEN(R6)>3,RIGHT(R6,1)="s",RIGHT(R6,2)<>"ss"),LEFT(R6,LEN(R6)-1),R6) -> sheet | Q6: =IFERROR(MID(Q5,FIND(" ",Q5)+1,999),"") | R6: =IFERROR(LEFT(Q5,FIND(" ",Q5)-1),"") -> sheet
A7: Items found: | C7: =COUNT('ALL ITEMS'!M3:M764) -> 8 | D7: =IF(C7=0,"No match - check spelling or try fewer words (e.g. 40x40 tube)","") | G7: =HYPERLINK("#Index!A1","<< Back to Index") -> << Back to Index | P7: =IF(AND(LEN(R7)>3,RIGHT(R7,1)="s",RIGHT(R7,2)<>"ss"),LEFT(R7,LEN(R7)-1),R7) | Q7: =IFERROR(MID(Q6,FIND(" ",Q6)+1,999),"") | R7: =IFERROR(LEFT(Q6,FIND(" ",Q6)-1),"")
A8: Words matched: | C8: =IF(P5="","(none - showing all)",P5&IF(P6="",""," + "&P6)&IF(P7="",""," + "&P7)&IF(P8="",""," + "&P8)&IF(P9="",""," + "&P9)&IF(P10="",""," + "&P10)) -> aluminium + sheet | P8: =IF(AND(LEN(R8)>3,RIGHT(R8,1)="s",RIGHT(R8,2)<>"ss"),LEFT(R8,LEN(R8)-1),R8) | Q8: =IFERROR(MID(Q7,FIND(" ",Q7)+1,999),"") | R8: =IFERROR(LEFT(Q7,FIND(" ",Q7)-1),"")
A9: # | B9: Item Code | C9: Category | D9: Item Description | E9: Specification / Size | F9: Finish / Colour | G9: Brand / Origin | H9: Unit | I9: Net Cost (AED) | J9: Selling (AED) | K9: Selling incl. VAT | L9: Rate Status | P9: =IF(AND(LEN(R9)>3,RIGHT(R9,1)="s",RIGHT(R9,2)<>"ss"),LEFT(R9,LEN(R9)-1),R9) | Q9: =IFERROR(MID(Q8,FIND(" ",Q8)+1,999),"") | R9: =IFERROR(LEFT(Q8,FIND(" ",Q8)-1),"")
A10: =IF($N10="","",ROWS($N$10:N10)) -> 1 | B10: =IF($N10="","",INDEX('ALL ITEMS'!$B:$B,$N10)) -> AL-051 | C10: =IF($N10="","",INDEX('ALL ITEMS'!$A:$A,$N10)) -> Aluminium Profiles & Systems | D10: =IF($N10="","",INDEX('ALL ITEMS'!$D:$D,$N10)) -> Aluminium flat sheet | E10: =IF($N10="","",INDEX('ALL ITEMS'!$E:$E,$N10)) -> 2.0 mm, 1250 x 2500 | F10: =IF($N10="","",INDEX('ALL ITEMS'!$F:$F,$N10)) -> Mill finish | G10: =IF($N10="","",INDEX('ALL ITEMS'!$G:$G,$N10)) -> Local / Imported | H10: =IF($N10="","",INDEX('ALL ITEMS'!$H:$H,$N10)) -> m2 | I10: =IF($N10="","",INDEX('ALL ITEMS'!$I:$I,$N10)) -> 50.4 | J10: =IF($N10="","",INDEX('ALL ITEMS'!$J:$J,$N10)) -> 60.48 | K10: =IF($N10="","",INDEX('ALL ITEMS'!$K:$K,$N10)) -> 63.5 | L10: =IF($N10="","",INDEX('ALL ITEMS'!$L:$L,$N10)) -> Indicative | N10: =IF(ROWS($N$10:N10)>$C$7,"",SMALL('ALL ITEMS'!$M$3:$M$764,ROWS($N$10:N10))) -> 53 | P10: =IF(AND(LEN(R10)>3,RIGHT(R10,1)="s",RIGHT(R10,2)<>"ss"),LEFT(R10,LEN(R10)-1),R10) | Q10: =IFERROR(MID(Q9,FIND(" ",Q9)+1,999),"") | R10: =IFERROR(LEFT(Q9,FIND(" ",Q9)-1),"")
A11: =IF($N11="","",ROWS($N$10:N11)) -> 2 | B11: =IF($N11="","",INDEX('ALL ITEMS'!$B:$B,$N11)) -> AL-052 | C11: =IF($N11="","",INDEX('ALL ITEMS'!$A:$A,$N11)) -> Aluminium Profiles & Systems | D11: =IF($N11="","",INDEX('ALL ITEMS'!$D:$D,$N11)) -> Aluminium flat sheet | E11: =IF($N11="","",INDEX('ALL ITEMS'!$E:$E,$N11)) -> 3.0 mm, 1250 x 2500 | F11: =IF($N11="","",INDEX('ALL ITEMS'!$F:$F,$N11)) -> Mill finish | G11: =IF($N11="","",INDEX('ALL ITEMS'!$G:$G,$N11)) -> Local / Imported | H11: =IF($N11="","",INDEX('ALL ITEMS'!$H:$H,$N11)) -> m2 | I11: =IF($N11="","",INDEX('ALL ITEMS'!$I:$I,$N11)) -> 73.5 | J11: =IF($N11="","",INDEX('ALL ITEMS'!$J:$J,$N11)) -> 88.2 | K11: =IF($N11="","",INDEX('ALL ITEMS'!$K:$K,$N11)) -> 92.61 | L11: =IF($N11="","",INDEX('ALL ITEMS'!$L:$L,$N11)) -> Indicative | N11: =IF(ROWS($N$10:N11)>$C$7,"",SMALL('ALL ITEMS'!$M$3:$M$764,ROWS($N$10:N11))) -> 54
A12: =IF($N12="","",ROWS($N$10:N12)) -> 3 | B12: =IF($N12="","",INDEX('ALL ITEMS'!$B:$B,$N12)) -> AL-053 | C12: =IF($N12="","",INDEX('ALL ITEMS'!$A:$A,$N12)) -> Aluminium Profiles & Systems | D12: =IF($N12="","",INDEX('ALL ITEMS'!$D:$D,$N12)) -> Aluminium chequered plate | E12: =IF($N12="","",INDEX('ALL ITEMS'!$E:$E,$N12)) -> 3.0 mm tread | F12: =IF($N12="","",INDEX('ALL ITEMS'!$F:$F,$N12)) -> Mill finish | G12: =IF($N12="","",INDEX('ALL ITEMS'!$G:$G,$N12)) -> Local / Imported | H12: =IF($N12="","",INDEX('ALL ITEMS'!$H:$H,$N12)) -> m2 | I12: =IF($N12="","",INDEX('ALL ITEMS'!$I:$I,$N12)) -> 89.25 | J12: =IF($N12="","",INDEX('ALL ITEMS'!$J:$J,$N12)) -> 107.1 | K12: =IF($N12="","",INDEX('ALL ITEMS'!$K:$K,$N12)) -> 112.46 | L12: =IF($N12="","",INDEX('ALL ITEMS'!$L:$L,$N12)) -> Indicative | N12: =IF(ROWS($N$10:N12)>$C$7,"",SMALL('ALL ITEMS'!$M$3:$M$764,ROWS($N$10:N12))) -> 55
A13: =IF($N13="","",ROWS($N$10:N13)) -> 4 | B13: =IF($N13="","",INDEX('ALL ITEMS'!$B:$B,$N13)) -> CL-001 | C13: =IF($N13="","",INDEX('ALL ITEMS'!$A:$A,$N13)) -> Cladding, ACP & Facade Panels | D13: =IF($N13="","",INDEX('ALL ITEMS'!$D:$D,$N13)) -> Aluminium composite panel (ACP) | E13: =IF($N13="","",INDEX('ALL ITEMS'!$E:$E,$N13)) -> 4 mm, 0.3 mm skin, non-FR | F13: =IF($N13="","",INDEX('ALL ITEMS'!$F:$F,$N13)) -> PVDF | G13: =IF($N13="","",INDEX('ALL ITEMS'!$G:$G,$N13)) -> Alubond / Alucobond / Equiv. | H13: =IF($N13="","",INDEX('ALL ITEMS'!$H:$H,$N13)) -> m2 | I13: =IF($N13="","",INDEX('ALL ITEMS'!$I:$I,$N13)) -> 60.5 | J13: =IF($N13="","",INDEX('ALL ITEMS'!$J:$J,$N13)) -> 72.6 | K13: =IF($N13="","",INDEX('ALL ITEMS'!$K:$K,$N13)) -> 76.23 | L13: =IF($N13="","",INDEX('ALL ITEMS'!$L:$L,$N13)) -> Indicative | N13: =IF(ROWS($N$10:N13)>$C$7,"",SMALL('ALL ITEMS'!$M$3:$M$764,ROWS($N$10:N13))) -> 407
A14: =IF($N14="","",ROWS($N$10:N14)) -> 5 | B14: =IF($N14="","",INDEX('ALL ITEMS'!$B:$B,$N14)) -> CL-002 | C14: =IF($N14="","",INDEX('ALL ITEMS'!$A:$A,$N14)) -> Cladding, ACP & Facade Panels | D14: =IF($N14="","",INDEX('ALL ITEMS'!$D:$D,$N14)) -> Aluminium composite panel - fire rated FR (B1) | E14: =IF($N14="","",INDEX('ALL ITEMS'!$E:$E,$N14)) -> 4 mm, 0.5 mm skin | F14: =IF($N14="","",INDEX('ALL ITEMS'!$F:$F,$N14)) -> PVDF | G14: =IF($N14="","",INDEX('ALL ITEMS'!$G:$G,$N14)) -> Alubond / Alucobond / Equiv. | H14: =IF($N14="","",INDEX('ALL ITEMS'!$H:$H,$N14)) -> m2 | I14: =IF($N14="","",INDEX('ALL ITEMS'!$I:$I,$N14)) -> 82.5 | J14: =IF($N14="","",INDEX('ALL ITEMS'!$J:$J,$N14)) -> 99 | K14: =IF($N14="","",INDEX('ALL ITEMS'!$K:$K,$N14)) -> 103.95 | L14: =IF($N14="","",INDEX('ALL ITEMS'!$L:$L,$N14)) -> Indicative | N14: =IF(ROWS($N$10:N14)>$C$7,"",SMALL('ALL ITEMS'!$M$3:$M$764,ROWS($N$10:N14))) -> 408
A15: =IF($N15="","",ROWS($N$10:N15)) -> 6 | B15: =IF($N15="","",INDEX('ALL ITEMS'!$B:$B,$N15)) -> CL-003 | C15: =IF($N15="","",INDEX('ALL ITEMS'!$A:$A,$N15)) -> Cladding, ACP & Facade Panels | D15: =IF($N15="","",INDEX('ALL ITEMS'!$D:$D,$N15)) -> Aluminium composite panel - A2 non-combustible | E15: =IF($N15="","",INDEX('ALL ITEMS'!$E:$E,$N15)) -> 4 mm, 0.5 mm skin | F15: =IF($N15="","",INDEX('ALL ITEMS'!$F:$F,$N15)) -> PVDF | G15: =IF($N15="","",INDEX('ALL ITEMS'!$G:$G,$N15)) -> Alubond / Alucobond / Equiv. | H15: =IF($N15="","",INDEX('ALL ITEMS'!$H:$H,$N15)) -> m2 | I15: =IF($N15="","",INDEX('ALL ITEMS'!$I:$I,$N15)) -> 121 | J15: =IF($N15="","",INDEX('ALL ITEMS'!$J:$J,$N15)) -> 145.2 | K15: =IF($N15="","",INDEX('ALL ITEMS'!$K:$K,$N15)) -> 152.46 | L15: =IF($N15="","",INDEX('ALL ITEMS'!$L:$L,$N15)) -> Indicative | N15: =IF(ROWS($N$10:N15)>$C$7,"",SMALL('ALL ITEMS'!$M$3:$M$764,ROWS($N$10:N15))) -> 409
A16: =IF($N16="","",ROWS($N$10:N16)) -> 7 | B16: =IF($N16="","",INDEX('ALL ITEMS'!$B:$B,$N16)) -> CL-010 | C16: =IF($N16="","",INDEX('ALL ITEMS'!$A:$A,$N16)) -> Cladding, ACP & Facade Panels | D16: =IF($N16="","",INDEX('ALL ITEMS'!$D:$D,$N16)) -> Aluminium corrugated / profiled sheet | E16: =IF($N16="","",INDEX('ALL ITEMS'!$E:$E,$N16)) -> 0.7 mm | F16: =IF($N16="","",INDEX('ALL ITEMS'!$F:$F,$N16)) -> PC / PVDF | G16: =IF($N16="","",INDEX('ALL ITEMS'!$G:$G,$N16)) -> Local | H16: =IF($N16="","",INDEX('ALL ITEMS'!$H:$H,$N16)) -> m2 | I16: =IF($N16="","",INDEX('ALL ITEMS'!$I:$I,$N16)) -> 71.5 | J16: =IF($N16="","",INDEX('ALL ITEMS'!$J:$J,$N16)) -> 85.8 | K16: =IF($N16="","",INDEX('ALL ITEMS'!$K:$K,$N16)) -> 90.09 | L16: =IF($N16="","",INDEX('ALL ITEMS'!$L:$L,$N16)) -> Indicative | N16: =IF(ROWS($N$10:N16)>$C$7,"",SMALL('ALL ITEMS'!$M$3:$M$764,ROWS($N$10:N16))) -> 416
A17: =IF($N17="","",ROWS($N$10:N17)) -> 8 | B17: =IF($N17="","",INDEX('ALL ITEMS'!$B:$B,$N17)) -> SI-045 | C17: =IF($N17="","",INDEX('ALL ITEMS'!$A:$A,$N17)) -> Finished Systems - Budget Supply & Install Rates | D17: =IF($N17="","",INDEX('ALL ITEMS'!$D:$D,$N17)) -> Polycarbonate canopy on MS / aluminium frame | E17: =IF($N17="","",INDEX('ALL ITEMS'!$E:$E,$N17)) -> 10 mm multiwall | F17: =IF($N17="","",INDEX('ALL ITEMS'!$F:$F,$N17)) -> PC | G17: =IF($N17="","",INDEX('ALL ITEMS'!$G:$G,$N17)) -> Local | H17: =IF($N17="","",INDEX('ALL ITEMS'!$H:$H,$N17)) -> m2 | I17: =IF($N17="","",INDEX('ALL ITEMS'!$I:$I,$N17)) -> 380 | J17: =IF($N17="","",INDEX('ALL ITEMS'!$J:$J,$N17)) -> 456 | K17: =IF($N17="","",INDEX('ALL ITEMS'!$K:$K,$N17)) -> 478.8 | L17: =IF($N17="","",INDEX('ALL ITEMS'!$L:$L,$N17)) -> Indicative | N17: =IF(ROWS($N$10:N17)>$C$7,"",SMALL('ALL ITEMS'!$M$3:$M$764,ROWS($N$10:N17))) -> 738
A18: =IF($N18="","",ROWS($N$10:N18)) | B18: =IF($N18="","",INDEX('ALL ITEMS'!$B:$B,$N18)) | C18: =IF($N18="","",INDEX('ALL ITEMS'!$A:$A,$N18)) | D18: =IF($N18="","",INDEX('ALL ITEMS'!$D:$D,$N18)) | E18: =IF($N18="","",INDEX('ALL ITEMS'!$E:$E,$N18)) | F18: =IF($N18="","",INDEX('ALL ITEMS'!$F:$F,$N18)) | G18: =IF($N18="","",INDEX('ALL ITEMS'!$G:$G,$N18)) | H18: =IF($N18="","",INDEX('ALL ITEMS'!$H:$H,$N18)) | I18: =IF($N18="","",INDEX('ALL ITEMS'!$I:$I,$N18)) | J18: =IF($N18="","",INDEX('ALL ITEMS'!$J:$J,$N18)) | K18: =IF($N18="","",INDEX('ALL ITEMS'!$K:$K,$N18)) | L18: =IF($N18="","",INDEX('ALL ITEMS'!$L:$L,$N18)) | N18: =IF(ROWS($N$10:N18)>$C$7,"",SMALL('ALL ITEMS'!$M$3:$M$764,ROWS($N$10:N18)))
A19: =IF($N19="","",ROWS($N$10:N19)) | B19: =IF($N19="","",INDEX('ALL ITEMS'!$B:$B,$N19)) | C19: =IF($N19="","",INDEX('ALL ITEMS'!$A:$A,$N19)) | D19: =IF($N19="","",INDEX('ALL ITEMS'!$D:$D,$N19)) | E19: =IF($N19="","",INDEX('ALL ITEMS'!$E:$E,$N19)) | F19: =IF($N19="","",INDEX('ALL ITEMS'!$F:$F,$N19)) | G19: =IF($N19="","",INDEX('ALL ITEMS'!$G:$G,$N19)) | H19: =IF($N19="","",INDEX('ALL ITEMS'!$H:$H,$N19)) | I19: =IF($N19="","",INDEX('ALL ITEMS'!$I:$I,$N19)) | J19: =IF($N19="","",INDEX('ALL ITEMS'!$J:$J,$N19)) | K19: =IF($N19="","",INDEX('ALL ITEMS'!$K:$K,$N19)) | L19: =IF($N19="","",INDEX('ALL ITEMS'!$L:$L,$N19)) | N19: =IF(ROWS($N$10:N19)>$C$7,"",SMALL('ALL ITEMS'!$M$3:$M$764,ROWS($N$10:N19)))
A20: =IF($N20="","",ROWS($N$10:N20)) | B20: =IF($N20="","",INDEX('ALL ITEMS'!$B:$B,$N20)) | C20: =IF($N20="","",INDEX('ALL ITEMS'!$A:$A,$N20)) | D20: =IF($N20="","",INDEX('ALL ITEMS'!$D:$D,$N20)) | E20: =IF($N20="","",INDEX('ALL ITEMS'!$E:$E,$N20)) | F20: =IF($N20="","",INDEX('ALL ITEMS'!$F:$F,$N20)) | G20: =IF($N20="","",INDEX('ALL ITEMS'!$G:$G,$N20)) | H20: =IF($N20="","",INDEX('ALL ITEMS'!$H:$H,$N20)) | I20: =IF($N20="","",INDEX('ALL ITEMS'!$I:$I,$N20)) | J20: =IF($N20="","",INDEX('ALL ITEMS'!$J:$J,$N20)) | K20: =IF($N20="","",INDEX('ALL ITEMS'!$K:$K,$N20)) | L20: =IF($N20="","",INDEX('ALL ITEMS'!$L:$L,$N20)) | N20: =IF(ROWS($N$10:N20)>$C$7,"",SMALL('ALL ITEMS'!$M$3:$M$764,ROWS($N$10:N20)))
A21: =IF($N21="","",ROWS($N$10:N21)) | B21: =IF($N21="","",INDEX('ALL ITEMS'!$B:$B,$N21)) | C21: =IF($N21="","",INDEX('ALL ITEMS'!$A:$A,$N21)) | D21: =IF($N21="","",INDEX('ALL ITEMS'!$D:$D,$N21)) | E21: =IF($N21="","",INDEX('ALL ITEMS'!$E:$E,$N21)) | F21: =IF($N21="","",INDEX('ALL ITEMS'!$F:$F,$N21)) | G21: =IF($N21="","",INDEX('ALL ITEMS'!$G:$G,$N21)) | H21: =IF($N21="","",INDEX('ALL ITEMS'!$H:$H,$N21)) | I21: =IF($N21="","",INDEX('ALL ITEMS'!$I:$I,$N21)) | J21: =IF($N21="","",INDEX('ALL ITEMS'!$J:$J,$N21)) | K21: =IF($N21="","",INDEX('ALL ITEMS'!$K:$K,$N21)) | L21: =IF($N21="","",INDEX('ALL ITEMS'!$L:$L,$N21)) | N21: =IF(ROWS($N$10:N21)>$C$7,"",SMALL('ALL ITEMS'!$M$3:$M$764,ROWS($N$10:N21)))
A22: =IF($N22="","",ROWS($N$10:N22)) | B22: =IF($N22="","",INDEX('ALL ITEMS'!$B:$B,$N22)) | C22: =IF($N22="","",INDEX('ALL ITEMS'!$A:$A,$N22)) | D22: =IF($N22="","",INDEX('ALL ITEMS'!$D:$D,$N22)) | E22: =IF($N22="","",INDEX('ALL ITEMS'!$E:$E,$N22)) | F22: =IF($N22="","",INDEX('ALL ITEMS'!$F:$F,$N22)) | G22: =IF($N22="","",INDEX('ALL ITEMS'!$G:$G,$N22)) | H22: =IF($N22="","",INDEX('ALL ITEMS'!$H:$H,$N22)) | I22: =IF($N22="","",INDEX('ALL ITEMS'!$I:$I,$N22)) | J22: =IF($N22="","",INDEX('ALL ITEMS'!$J:$J,$N22)) | K22: =IF($N22="","",INDEX('ALL ITEMS'!$K:$K,$N22)) | L22: =IF($N22="","",INDEX('ALL ITEMS'!$L:$L,$N22)) | N22: =IF(ROWS($N$10:N22)>$C$7,"",SMALL('ALL ITEMS'!$M$3:$M$764,ROWS($N$10:N22)))
... A309: =IF($N309="","",ROWS($N$10:N309)) | B309: =IF($N309="","",INDEX('ALL ITEMS'!$B:$B,$N309)) | C309: =IF($N309="","",INDEX('ALL ITEMS'!$A:$A,$N309)) | D309: =IF($N309="","",INDEX('ALL ITEMS'!$D:$D,$N309)) | E309: =IF($N309="","",INDEX('ALL ITEMS'!$E:$E,$N309)) | F309: =IF($N309="","",INDEX('ALL ITEMS'!$F:$F,$N309)) | G309: =IF($N309="","",INDEX('ALL ITEMS'!$G:$G,$N309)) | H309: =IF($N309="","",INDEX('ALL ITEMS'!$H:$H,$N309)) | I309: =IF($N309="","",INDEX('ALL ITEMS'!$I:$I,$N309)) | J309: =IF($N309="","",INDEX('ALL ITEMS'!$J:$J,$N309)) | K309: =IF($N309="","",INDEX('ALL ITEMS'!$K:$K,$N309)) | L309: =IF($N309="","",INDEX('ALL ITEMS'!$L:$L,$N309)) | N309: =IF(ROWS($N$10:N309)>$C$7,"",SMALL('ALL ITEMS'!$M$3:$M$764,ROWS($N$10:N309)))

Sheet ALL ITEMS
A1: ALL ITEMS - MASTER LIST (auto-linked from category sheets; do not edit here)
A2: Category | B2: Item Code | C2: Sub-Category | D2: Item Description | E2: Specification / Size | F2: Finish / Colour | G2: Brand / Origin | H2: Unit | I2: Net Cost (AED) | J2: Selling (AED) | K2: Selling incl. VAT | L2: Rate Status | M2: Search key
A3: =IF('01 Aluminium'!$C$5="","","Aluminium Profiles & Systems") -> Aluminium Profiles & Systems | B3: =IF('01 Aluminium'!$C$5="","",'01 Aluminium'!A5) -> AL-001 | C3: =IF('01 Aluminium'!$C$5="","",'01 Aluminium'!B5) -> Extrusions (per kg) | D3: =IF('01 Aluminium'!$C$5="","",'01 Aluminium'!C5) -> Aluminium extrusion | E3: =IF('01 Aluminium'!$C$5="","",'01 Aluminium'!D5) -> Alloy 6063-T5/T6 | F3: =IF('01 Aluminium'!$C$5="","",'01 Aluminium'!E5) -> Mill finish | G3: =IF('01 Aluminium'!$C$5="","",'01 Aluminium'!F5) -> Gulf Extrusions / Equiv. | H3: =IF('01 Aluminium'!$C$5="","",'01 Aluminium'!G5) -> kg | I3: =IF('01 Aluminium'!$C$5="","",'01 Aluminium'!J5) -> 16.28 | J3: =IF('01 Aluminium'!$C$5="","",'01 Aluminium'!K5) -> 19.54 | K3: =IF('01 Aluminium'!$C$5="","",'01 Aluminium'!L5) -> 20.52 | L3: =IF('01 Aluminium'!$C$5="","",'01 Aluminium'!M5) -> Indicative | M3: =IF(D3="","",IF(AND(OR(Search!$C$6="All Categories",A3=Search!$C$6),OR(Search!$P$5="",ISNUMBER(SEARCH(" "&Search!$P$5,N3))),OR(Search!$P$6="",ISNUMBER(SEARCH(" "&Search!$P$6,N3))),OR(Search!$P$7="",ISNUMBER(SEARCH(" "&Search!$P$7,N3))),OR(Search!$P$8="",ISNUMBER(SEARCH(" "&Search!$P$8,N3))),OR(Search!$P$9="",ISNUMBER(SEARCH(" "&Search!$P$9,N3))),OR(Search!$P$10="",ISNUMBER(SEARCH(" "&Search!$P$10,N3)))),ROW(),"")) | N3: =IF(D3="",""," "&SUBSTITUTE(SUBSTITUTE(SUBSTITUTE(SUBSTITUTE(SUBSTITUTE(SUBSTITUTE(SUBSTITUTE(B3&" "&C3&" "&D3&" "&E3&" "&F3&" "&G3&" "&H3&" "&'01 Aluminium'!R5,"("," "),")"," "),"/"," "),"-"," "),","," "),";"," "),":"," ")&" ") -> AL 001 Extrusions per kg Aluminium extrusion Alloy 6063 T5 T6 Mill finish Gulf Extrusions Equiv. kg aluminum alu
A4: =IF('01 Aluminium'!$C$6="","","Aluminium Profiles & Systems") -> Aluminium Profiles & Systems | B4: =IF('01 Aluminium'!$C$6="","",'01 Aluminium'!A6) -> AL-002 | C4: =IF('01 Aluminium'!$C$6="","",'01 Aluminium'!B6) -> Extrusions (per kg) | D4: =IF('01 Aluminium'!$C$6="","",'01 Aluminium'!C6) -> Aluminium extrusion | E4: =IF('01 Aluminium'!$C$6="","",'01 Aluminium'!D6) -> Alloy 6063-T5/T6 | F4: =IF('01 Aluminium'!$C$6="","",'01 Aluminium'!E6) -> Powder coated (RAL) | G4: =IF('01 Aluminium'!$C$6="","",'01 Aluminium'!F6) -> Gulf Extrusions / Equiv. | H4: =IF('01 Aluminium'!$C$6="","",'01 Aluminium'!G6) -> kg | I4: =IF('01 Aluminium'!$C$6="","",'01 Aluminium'!J6) -> 19.43 | J4: =IF('01 Aluminium'!$C$6="","",'01 Aluminium'!K6) -> 23.32 | K4: =IF('01 Aluminium'!$C$6="","",'01 Aluminium'!L6) -> 24.49 | L4: =IF('01 Aluminium'!$C$6="","",'01 Aluminium'!M6) -> Indicative | M4: =IF(D4="","",IF(AND(OR(Search!$C$6="All Categories",A4=Search!$C$6),OR(Search!$P$5="",ISNUMBER(SEARCH(" "&Search!$P$5,N4))),OR(Search!$P$6="",ISNUMBER(SEARCH(" "&Search!$P$6,N4))),OR(Search!$P$7="",ISNUMBER(SEARCH(" "&Search!$P$7,N4))),OR(Search!$P$8="",ISNUMBER(SEARCH(" "&Search!$P$8,N4))),OR(Search!$P$9="",ISNUMBER(SEARCH(" "&Search!$P$9,N4))),OR(Search!$P$10="",ISNUMBER(SEARCH(" "&Search!$P$10,N4)))),ROW(),"")) | N4: =IF(D4="",""," "&SUBSTITUTE(SUBSTITUTE(SUBSTITUTE(SUBSTITUTE(SUBSTITUTE(SUBSTITUTE(SUBSTITUTE(B4&" "&C4&" "&D4&" "&E4&" "&F4&" "&G4&" "&H4&" "&'01 Aluminium'!R6,"("," "),")"," "),"/"," "),"-"," "),","," "),";"," "),":"," ")&" ") -> AL 002 Extrusions per kg Aluminium extrusion Alloy 6063 T5 T6 Powder coated RAL Gulf Extrusions Equiv. kg aluminum alu pc
A5: =IF('01 Aluminium'!$C$7="","","Aluminium Profiles & Systems") -> Aluminium Profiles & Systems | B5: =IF('01 Aluminium'!$C$7="","",'01 Aluminium'!A7) -> AL-003 | C5: =IF('01 Aluminium'!$C$7="","",'01 Aluminium'!B7) -> Extrusions (per kg) | D5: =IF('01 Aluminium'!$C$7="","",'01 Aluminium'!C7) -> Aluminium extrusion | E5: =IF('01 Aluminium'!$C$7="","",'01 Aluminium'!D7) -> Alloy 6063-T5/T6 | F5: =IF('01 Aluminium'!$C$7="","",'01 Aluminium'!E7) -> Anodized 15-20 micron | G5: =IF('01 Aluminium'!$C$7="","",'01 Aluminium'!F7) -> Gulf Extrusions / Equiv. | H5: =IF('01 Aluminium'!$C$7="","",'01 Aluminium'!G7) -> kg | I5: =IF('01 Aluminium'!$C$7="","",'01 Aluminium'!J7) -> 21.53 | J5: =IF('01 Aluminium'!$C$7="","",'01 Aluminium'!K7) -> 25.84 | K5: =IF('01 Aluminium'!$C$7="","",'01 Aluminium'!L7) -> 27.13 | L5: =IF('01 Aluminium'!$C$7="","",'01 Aluminium'!M7) -> Indicative | M5: =IF(D5="","",IF(AND(OR(Search!$C$6="All Categories",A5=Search!$C$6),OR(Search!$P$5="",ISNUMBER(SEARCH(" "&Search!$P$5,N5))),OR(Search!$P$6="",ISNUMBER(SEARCH(" "&Search!$P$6,N5))),OR(Search!$P$7="",ISNUMBER(SEARCH(" "&Search!$P$7,N5))),OR(Search!$P$8="",ISNUMBER(SEARCH(" "&Search!$P$8,N5))),OR(Search!$P$9="",ISNUMBER(SEARCH(" "&Search!$P$9,N5))),OR(Search!$P$10="",ISNUMBER(SEARCH(" "&Search!$P$10,N5)))),ROW(),"")) | N5: =IF(D5="",""," "&SUBSTITUTE(SUBSTITUTE(SUBSTITUTE(SUBSTITUTE(SUBSTITUTE(SUBSTITUTE(SUBSTITUTE(B5&" "&C5&" "&D5&" "&E5&" "&F5&" "&G5&" "&H5&" "&'01 Aluminium'!R7,"("," "),")"," "),"/"," "),"-"," "),","," "),";"," "),":"," ")&" ") -> AL 003 Extrusions per kg Aluminium extrusion Alloy 6063 T5 T6 Anodized 15 20 micron Gulf Extrusions Equiv. kg aluminum alu
A6: =IF('01 Aluminium'!$C$8="","","Aluminium Profiles & Systems") -> Aluminium Profiles & Systems | B6: =IF('01 Aluminium'!$C$8="","",'01 Aluminium'!A8) -> AL-004 | C6: =IF('01 Aluminium'!$C$8="","",'01 Aluminium'!B8) -> Extrusions (per kg) | D6: =IF('01 Aluminium'!$C$8="","",'01 Aluminium'!C8) -> Aluminium extrusion | E6: =IF('01 Aluminium'!$C$8="","",'01 Aluminium'!D8) -> Alloy 6063-T5/T6 | F6: =IF('01 Aluminium'!$C$8="","",'01 Aluminium'!E8) -> PVDF 2/3-coat | G6: =IF('01 Aluminium'!$C$8="","",'01 Aluminium'!F8) -> Gulf Extrusions / Equiv. | H6: =IF('01 Aluminium'!$C$8="","",'01 Aluminium'!G8) -> kg | I6: =IF('01 Aluminium'!$C$8="","",'01 Aluminium'!J8) -> 25.2 | J6: =IF('01 Aluminium'!$C$8="","",'01 Aluminium'!K8) -> 30.24 | K6: =IF('01 Aluminium'!$C$8="","",'01 Aluminium'!L8) -> 31.75 | L6: =IF('01 Aluminium'!$C$8="","",'01 Aluminium'!M8) -> Indicative | M6: =IF(D6="","",IF(AND(OR(Search!$C$6="All Categories",A6=Search!$C$6),OR(Search!$P$5="",ISNUMBER(SEARCH(" "&Search!$P$5,N6))),OR(Search!$P$6="",ISNUMBER(SEARCH(" "&Search!$P$6,N6))),OR(Search!$P$7="",ISNUMBER(SEARCH(" "&Search!$P$7,N6))),OR(Search!$P$8="",ISNUMBER(SEARCH(" "&Search!$P$8,N6))),OR(Search!$P$9="",ISNUMBER(SEARCH(" "&Search!$P$9,N6))),OR(Search!$P$10="",ISNUMBER(SEARCH(" "&Search!$P$10,N6)))),ROW(),"")) | N6: =IF(D6="",""," "&SUBSTITUTE(SUBSTITUTE(SUBSTITUTE(SUBSTITUTE(SUBSTITUTE(SUBSTITUTE(SUBSTITUTE(B6&" "&C6&" "&D6&" "&E6&" "&F6&" "&G6&" "&H6&" "&'01 Aluminium'!R8,"("," "),")"," "),"/"," "),"-"," "),","," "),";"," "),":"," ")&" ") -> AL 004 Extrusions per kg Aluminium extrusion Alloy 6063 T5 T6 PVDF 2 3 coat Gulf Extrusions Equiv. kg aluminum alu
A7: =IF('01 Aluminium'!$C$9="","","Aluminium Profiles & Systems") -> Aluminium Profiles & Systems | B7: =IF('01 Aluminium'!$C$9="","",'01 Aluminium'!A9) -> AL-005 | C7: =IF('01 Aluminium'!$C$9="","",'01 Aluminium'!B9) -> Extrusions (per kg) | D7: =IF('01 Aluminium'!$C$9="","",'01 Aluminium'!C9) -> Aluminium extrusion | E7: =IF('01 Aluminium'!$C$9="","",'01 Aluminium'!D9) -> Alloy 6063-T5/T6 | F7: =IF('01 Aluminium'!$C$9="","",'01 Aluminium'!E9) -> Wood-grain finish | G7: =IF('01 Aluminium'!$C$9="","",'01 Aluminium'!F9) -> Gulf Extrusions / Equiv. | H7: =IF('01 Aluminium'!$C$9="","",'01 Aluminium'!G9) -> kg | I7: =IF('01 Aluminium'!$C$9="","",'01 Aluminium'!J9) -> 26.25 | J7: =IF('01 Aluminium'!$C$9="","",'01 Aluminium'!K9) -> 31.5 | K7: =IF('01 Aluminium'!$C$9="","",'01 Aluminium'!L9) -> 33.08 | L7: =IF('01 Aluminium'!$C$9="","",'01 Aluminium'!M9) -> Indicative | M7: =IF(D7="","",IF(AND(OR(Search!$C$6="All Categories",A7=Search!$C$6),OR(Search!$P$5="",ISNUMBER(SEARCH(" "&Search!$P$5,N7))),OR(Search!$P$6="",ISNUMBER(SEARCH(" "&Search!$P$6,N7))),OR(Search!$P$7="",ISNUMBER(SEARCH(" "&Search!$P$7,N7))),OR(Search!$P$8="",ISNUMBER(SEARCH(" "&Search!$P$8,N7))),OR(Search!$P$9="",ISNUMBER(SEARCH(" "&Search!$P$9,N7))),OR(Search!$P$10="",ISNUMBER(SEARCH(" "&Search!$P$10,N7)))),ROW(),"")) | N7: =IF(D7="",""," "&SUBSTITUTE(SUBSTITUTE(SUBSTITUTE(SUBSTITUTE(SUBSTITUTE(SUBSTITUTE(SUBSTITUTE(B7&" "&C7&" "&D7&" "&E7&" "&F7&" "&G7&" "&H7&" "&'01 Aluminium'!R9,"("," "),")"," "),"/"," "),"-"," "),","," "),";"," "),":"," ")&" ") -> AL 005 Extrusions per kg Aluminium extrusion Alloy 6063 T5 T6 Wood grain finish Gulf Extrusions Equiv. kg aluminum alu
A8: =IF('01 Aluminium'!$C$10="","","Aluminium Profiles & Systems") -> Aluminium Profiles & Systems | B8: =IF('01 Aluminium'!$C$10="","",'01 Aluminium'!A10) -> AL-006 | C8: =IF('01 Aluminium'!$C$10="","",'01 Aluminium'!B10) -> Extrusions (per kg) | D8: =IF('01 Aluminium'!$C$10="","",'01 Aluminium'!C10) -> Thermal-break aluminium extrusion | E8: =IF('01 Aluminium'!$C$10="","",'01 Aluminium'!D10) -> With polyamide strips | F8: =IF('01 Aluminium'!$C$10="","",'01 Aluminium'!E10) -> Powder coated | G8: =IF('01 Aluminium'!$C$10="","",'01 Aluminium'!F10) -> Gulf Extrusions / Equiv. | H8: =IF('01 Aluminium'!$C$10="","",'01 Aluminium'!G10) -> kg | I8: =IF('01 Aluminium'!$C$10="","",'01 Aluminium'!J10) -> 25.73 | J8: =IF('01 Aluminium'!$C$10="","",'01 Aluminium'!K10) -> 30.88 | K8: =IF('01 Aluminium'!$C$10="","",'01 Aluminium'!L10) -> 32.42 | L8: =IF('01 Aluminium'!$C$10="","",'01 Aluminium'!M10) -> Indicative | M8: =IF(D8="","",IF(AND(OR(Search!$C$6="All Categories",A8=Search!$C$6),OR(Search!$P$5="",ISNUMBER(SEARCH(" "&Search!$P$5,N8))),OR(Search!$P$6="",ISNUMBER(SEARCH(" "&Search!$P$6,N8))),OR(Search!$P$7="",ISNUMBER(SEARCH(" "&Search!$P$7,N8))),OR(Search!$P$8="",ISNUMBER(SEARCH(" "&Search!$P$8,N8))),OR(Search!$P$9="",ISNUMBER(SEARCH(" "&Search!$P$9,N8))),OR(Search!$P$10="",ISNUMBER(SEARCH(" "&Search!$P$10,N8)))),ROW(),"")) | N8: =IF(D8="",""," "&SUBSTITUTE(SUBSTITUTE(SUBSTITUTE(SUBSTITUTE(SUBSTITUTE(SUBSTITUTE(SUBSTITUTE(B8&" "&C8&" "&D8&" "&E8&" "&F8&" "&G8&" "&H8&" "&'01 Aluminium'!R10,"("," "),")"," "),"/"," "),"-"," "),","," "),";"," "),":"," ")&" ") -> AL 006 Extrusions per kg Thermal break aluminium extrusion With polyamide strips Powder coated Gulf Extrusions Equiv. kg aluminum alu pc
A9: =IF('01 Aluminium'!$C$11="","","Aluminium Profiles & Systems") -> Aluminium Profiles & Systems | B9: =IF('01 Aluminium'!$C$11="","",'01 Aluminium'!A11) -> AL-007 | C9: =IF('01 Aluminium'!$C$11="","",'01 Aluminium'!B11) -> Standard Sections | D9: =IF('01 Aluminium'!$C$11="","",'01 Aluminium'!C11) -> Aluminium square tube | E9: =IF('01 Aluminium'!$C$11="","",'01 Aluminium'!D11) -> 25 x 25 x 1.5 mm (0.38 kg/m) | F9: =IF('01 Aluminium'!$C$11="","",'01 Aluminium'!E11) -> Powder coated | G9: =IF('01 Aluminium'!$C$11="","",'01 Aluminium'!F11) -> Local | H9: =IF('01 Aluminium'!$C$11="","",'01 Aluminium'!G11) -> lm | I9: =IF('01 Aluminium'!$C$11="","",'01 Aluminium'!J11) -> 7.38 | J9: =IF('01 Aluminium'!$C$11="","",'01 Aluminium'!K11) -> 8.86 | K9: =IF('01 Aluminium'!$C$11="","",'01 Aluminium'!L11) -> 9.3 | L9: =IF('01 Aluminium'!$C$11="","",'01 Aluminium'!M11) -> Indicative | M9: =IF(D9="","",IF(AND(OR(Search!$C$6="All Categories",A9=Search!$C$6),OR(Search!$P$5="",ISNUMBER(SEARCH(" "&Search!$P$5,N9))),OR(Search!$P$6="",ISNUMBER(SEARCH(" "&Search!$P$6,N9))),OR(Search!$P$7="",ISNUMBER(SEARCH(" "&Search!$P$7,N9))),OR(Search!$P$8="",ISNUMBER(SEARCH(" "&Search!$P$8,N9))),OR(Search!$P$9="",ISNUMBER(SEARCH(" "&Search!$P$9,N9))),OR(Search!$P$10="",ISNUMBER(SEARCH(" "&Search!$P$10,N9)))),ROW(),"")) | N9: =IF(D9="",""," "&SUBSTITUTE(SUBSTITUTE(SUBSTITUTE(SUBSTITUTE(SUBSTITUTE(SUBSTITUTE(SUBSTITUTE(B9&" "&C9&" "&D9&" "&E9&" "&F9&" "&G9&" "&H9&" "&'01 Aluminium'!R11,"("," "),")"," "),"/"," "),"-"," "),","," "),";"," "),":"," ")&" ") -> AL 007 Standard Sections Aluminium square tube 25 x 25 x 1.5 mm 0.38 kg m Powder coated Local lm 25x25 25x25x1.5 1.5mm pipe box aluminum alu pc
A10: =IF('01 Aluminium'!$C$12="","","Aluminium Profiles & Systems") -> Aluminium Profiles & Systems | B10: =IF('01 Aluminium'!$C$12="","",'01 Aluminium'!A12) -> AL-008 | C10: =IF('01 Aluminium'!$C$12="","",'01 Aluminium'!B12) -> Standard Sections | D10: =IF('01 Aluminium'!$C$12="","",'01 Aluminium'!C12) -> Aluminium square tube | E10: =IF('01 Aluminium'!$C$12="","",'01 Aluminium'!D12) -> 40 x 40 x 2.0 mm (0.82 kg/m) | F10: =IF('01 Aluminium'!$C$12="","",'01 Aluminium'!E12) -> Powder coated | G10: =IF('01 Aluminium'!$C$12="","",'01 Aluminium'!F12) -> Local | H10: =IF('01 Aluminium'!$C$12="","",'01 Aluminium'!G12) -> lm | I10: =IF('01 Aluminium'!$C$12="","",'01 Aluminium'!J12) -> 15.93 | J10: =IF('01 Aluminium'!$C$12="","",'01 Aluminium'!K12) -> 19.12 | K10: =IF('01 Aluminium'!$C$12="","",'01 Aluminium'!L12) -> 20.08 | L10: =IF('01 Aluminium'!$C$12="","",'01 Aluminium'!M12) -> Indicative | M10: =IF(D10="","",IF(AND(OR(Search!$C$6="All Categories",A10=Search!$C$6),OR(Search!$P$5="",ISNUMBER(SEARCH(" "&Search!$P$5,N10))),OR(Search!$P$6="",ISNUMBER(SEARCH(" "&Search!$P$6,N10))),OR(Search!$P$7="",ISNUMBER(SEARCH(" "&Search!$P$7,N10))),OR(Search!$P$8="",ISNUMBER(SEARCH(" "&Search!$P$8,N10))),OR(Search!$P$9="",ISNUMBER(SEARCH(" "&Search!$P$9,N10))),OR(Search!$P$10="",ISNUMBER(SEARCH(" "&Search!$P$10,N10)))),ROW(),"")) | N10: =IF(D10="",""," "&SUBSTITUTE(SUBSTITUTE(SUBSTITUTE(SUBSTITUTE(SUBSTITUTE(SUBSTITUTE(SUBSTITUTE(B10&" "&C10&" "&D10&" "&E10&" "&F10&" "&G10&" "&H10&" "&'01 Aluminium'!R12,"("," "),")"," "),"/"," "),"-"," "),","," "),";"," "),":"," ")&" ") -> AL 008 Standard Sections Aluminium square tube 40 x 40 x 2.0 mm 0.82 kg m Powder coated Local lm 40x40 40x40x2.0 40x40x2 2.0mm pipe box aluminum alu pc
A11: =IF('01 Aluminium'!$C$13="","","Aluminium Profiles & Systems") -> Aluminium Profiles & Systems | B11: =IF('01 Aluminium'!$C$13="","",'01 Aluminium'!A13) -> AL-009 | C11: =IF('01 Aluminium'!$C$13="","",'01 Aluminium'!B13) -> Standard Sections | D11: =IF('01 Aluminium'!$C$13="","",'01 Aluminium'!C13) -> Aluminium square tube | E11: =IF('01 Aluminium'!$C$13="","",'01 Aluminium'!D13) -> 50 x 50 x 2.0 mm (1.04 kg/m) | F11: =IF('01 Aluminium'!$C$13="","",'01 Aluminium'!E13) -> Powder coated | G11: =IF('01 Aluminium'!$C$13="","",'01 Aluminium'!F13) -> Local | H11: =IF('01 Aluminium'!$C$13="","",'01 Aluminium'!G13) -> lm | I11: =IF('01 Aluminium'!$C$13="","",'01 Aluminium'!J13) -> 20.2 | J11: =IF('01 Aluminium'!$C$13="","",'01 Aluminium'!K13) -> 24.24 | K11: =IF('01 Aluminium'!$C$13="","",'01 Aluminium'!L13) -> 25.45 | L11: =IF('01 Aluminium'!$C$13="","",'01 Aluminium'!M13) -> Indicative | M11: =IF(D11="","",IF(AND(OR(Search!$C$6="All Categories",A11=Search!$C$6),OR(Search!$P$5="",ISNUMBER(SEARCH(" "&Search!$P$5,N11))),OR(Search!$P$6="",ISNUMBER(SEARCH(" "&Search!$P$6,N11))),OR(Search!$P$7="",ISNUMBER(SEARCH(" "&Search!$P$7,N11))),OR(Search!$P$8="",ISNUMBER(SEARCH(" "&Search!$P$8,N11))),OR(Search!$P$9="",ISNUMBER(SEARCH(" "&Search!$P$9,N11))),OR(Search!$P$10="",ISNUMBER(SEARCH(" "&Search!$P$10,N11)))),ROW(),"")) | N11: =IF(D11="",""," "&SUBSTITUTE(SUBSTITUTE(SUBSTITUTE(SUBSTITUTE(SUBSTITUTE(SUBSTITUTE(SUBSTITUTE(B11&" "&C11&" "&D11&" "&E11&" "&F11&" "&G11&" "&H11&" "&'01 Aluminium'!R13,"("," "),")"," "),"/"," "),"-"," "),","," "),";"," "),":"," ")&" ") -> AL 009 Standard Sections Aluminium square tube 50 x 50 x 2.0 mm 1.04 kg m Powder coated Local lm 50x50 50x50x2.0 50x50x2 2.0mm pipe box aluminum alu pc
A12: =IF('01 Aluminium'!$C$14="","","Aluminium Profiles & Systems") -> Aluminium Profiles & Systems | B12: =IF('01 Aluminium'!$C$14="","",'01 Aluminium'!A14) -> AL-010 | C12: =IF('01 Aluminium'!$C$14="","",'01 Aluminium'!B14) -> Standard Sections | D12: =IF('01 Aluminium'!$C$14="","",'01 Aluminium'!C14) -> Aluminium rectangular tube | E12: =IF('01 Aluminium'!$C$14="","",'01 Aluminium'!D14) -> 100 x 50 x 2.5 mm (1.96 kg/m) | F12: =IF('01 Aluminium'!$C$14="","",'01 Aluminium'!E14) -> Powder coated | G12: =IF('01 Aluminium'!$C$14="","",'01 Aluminium'!F14) -> Local | H12: =IF('01 Aluminium'!$C$14="","",'01 Aluminium'!G14) -> lm | I12: =IF('01 Aluminium'!$C$14="","",'01 Aluminium'!J14) -> 38.07 | J12: =IF('01 Aluminium'!$C$14="","",'01 Aluminium'!K14) -> 45.68 | K12: =IF('01 Aluminium'!$C$14="","",'01 Aluminium'!L14) -> 47.96 | L12: =IF('01 Aluminium'!$C$14="","",'01 Aluminium'!M14) -> Indicative | M12: =IF(D12="","",IF(AND(OR(Search!$C$6="All Categories",A12=Search!$C$6),OR(Search!$P$5="",ISNUMBER(SEARCH(" "&Search!$P$5,N12))),OR(Search!$P$6="",ISNUMBER(SEARCH(" "&Search!$P$6,N12))),OR(Search!$P$7="",ISNUMBER(SEARCH(" "&Search!$P$7,N12))),OR(Search!$P$8="",ISNUMBER(SEARCH(" "&Search!$P$8,N12))),OR(Search!$P$9="",ISNUMBER(SEARCH(" "&Search!$P$9,N12))),OR(Search!$P$10="",ISNUMBER(SEARCH(" "&Search!$P$10,N12)))),ROW(),"")) | N12: =IF(D12="",""," "&SUBSTITUTE(SUBSTITUTE(SUBSTITUTE(SUBSTITUTE(SUBSTITUTE(SUBSTITUTE(SUBSTITUTE(B12&" "&C12&" "&D12&" "&E12&" "&F12&" "&G12&" "&H12&" "&'01 Aluminium'!R14,"("," "),")"," "),"/"," "),"-"," "),","," "),";"," "),":"," ")&" ") -> AL 010 Standard Sections Aluminium rectangular tube 100 x 50 x 2.5 mm 1.96 kg m Powder coated Local lm 100x50 100x50x2.5 2.5mm pipe box aluminum alu pc
A13: =IF('01 Aluminium'!$C$15="","","Aluminium Profiles & Systems") -> Aluminium Profiles & Systems | B13: =IF('01 Aluminium'!$C$15="","",'01 Aluminium'!A15) -> AL-011 | C13: =IF('01 Aluminium'!$C$15="","",'01 Aluminium'!B15) -> Standard Sections | D13: =IF('01 Aluminium'!$C$15="","",'01 Aluminium'!C15) -> Aluminium rectangular tube | E13: =IF('01 Aluminium'!$C$15="","",'01 Aluminium'!D15) -> 100 x 50 x 3.0 mm (2.33 kg/m) | F13: =IF('01 Aluminium'!$C$15="","",'01 Aluminium'!E15) -> Powder coated | G13: =IF('01 Aluminium'!$C$15="","",'01 Aluminium'!F15) -> Local | H13: =IF('01 Aluminium'!$C$15="","",'01 Aluminium'!G15) -> lm | I13: =IF('01 Aluminium'!$C$15="","",'01 Aluminium'!J15) -> 45.27 | J13: =IF('01 Aluminium'!$C$15="","",'01 Aluminium'!K15) -> 54.32 | K13: =IF('01 Aluminium'!$C$15="","",'01 Aluminium'!L15) -> 57.04 | L13: =IF('01 Aluminium'!$C$15="","",'01 Aluminium'!M15) -> Indicative | M13: =IF(D13="","",IF(AND(OR(Search!$C$6="All Categories",A13=Search!$C$6),OR(Search!$P$5="",ISNUMBER(SEARCH(" "&Search!$P$5,N13))),OR(Search!$P$6="",ISNUMBER(SEARCH(" "&Search!$P$6,N13))),OR(Search!$P$7="",ISNUMBER(SEARCH(" "&Search!$P$7,N13))),OR(Search!$P$8="",ISNUMBER(SEARCH(" "&Search!$P$8,N13))),OR(Search!$P$9="",ISNUMBER(SEARCH(" "&Search!$P$9,N13))),OR(Search!$P$10="",ISNUMBER(SEARCH(" "&Search!$P$10,N13)))),ROW(),"")) | N13: =IF(D13="",""," "&SUBSTITUTE(SUBSTITUTE(SUBSTITUTE(SUBSTITUTE(SUBSTITUTE(SUBSTITUTE(SUBSTITUTE(B13&" "&C13&" "&D13&" "&E13&" "&F13&" "&G13&" "&H13&" "&'01 Aluminium'!R15,"("," "),")"," "),"/"," "),"-"," "),","," "),";"," "),":"," ")&" ") -> AL 011 Standard Sections Aluminium rectangular tube 100 x 50 x 3.0 mm 2.33 kg m Powder coated Local lm 100x50 100x50x3.0 100x50x3 3.0mm pipe box aluminum alu pc
A14: =IF('01 Aluminium'!$C$16="","","Aluminium Profiles & Systems") -> Aluminium Profiles & Systems | B14: =IF('01 Aluminium'!$C$16="","",'01 Aluminium'!A16) -> AL-012 | C14: =IF('01 Aluminium'!$C$16="","",'01 Aluminium'!B16) -> Standard Sections | D14: =IF('01 Aluminium'!$C$16="","",'01 Aluminium'!C16) -> Aluminium rectangular tube | E14: =IF('01 Aluminium'!$C$16="","",'01 Aluminium'!D16) -> 150 x 50 x 3.0 mm (3.14 kg/m) | F14: =IF('01 Aluminium'!$C$16="","",'01 Aluminium'!E16) -> Powder coated | G14: =IF('01 Aluminium'!$C$16="","",'01 Aluminium'!F16) -> Local | H14: =IF('01 Aluminium'!$C$16="","",'01 Aluminium'!G16) -> lm | I14: =IF('01 Aluminium'!$C$16="","",'01 Aluminium'!J16) -> 60.99 | J14: =IF('01 Aluminium'!$C$16="","",'01 Aluminium'!K16) -> 73.19 | K14: =IF('01 Aluminium'!$C$16="","",'01 Aluminium'!L16) -> 76.85 | L14: =IF('01 Aluminium'!$C$16="","",'01 Aluminium'!M16) -> Indicative | M14: =IF(D14="","",IF(AND(OR(Search!$C$6="All Categories",A14=Search!$C$6),OR(Search!$P$5="",ISNUMBER(SEARCH(" "&Search!$P$5,N14))),OR(Search!$P$6="",ISNUMBER(SEARCH(" "&Search!$P$6,N14))),OR(Search!$P$7="",ISNUMBER(SEARCH(" "&Search!$P$7,N14))),OR(Search!$P$8="",ISNUMBER(SEARCH(" "&Search!$P$8,N14))),OR(Search!$P$9="",ISNUMBER(SEARCH(" "&Search!$P$9,N14))),OR(Search!$P$10="",ISNUMBER(SEARCH(" "&Search!$P$10,N14)))),ROW(),"")) | N14: =IF(D14="",""," "&SUBSTITUTE(SUBSTITUTE(SUBSTITUTE(SUBSTITUTE(SUBSTITUTE(SUBSTITUTE(SUBSTITUTE(B14&" "&C14&" "&D14&" "&E14&" "&F14&" "&G14&" "&H14&" "&'01 Aluminium'!R16,"("," "),")"," "),"/"," "),"-"," "),","," "),";"," "),":"," ")&" ") -> AL 012 Standard Sections Aluminium rectangular tube 150 x 50 x 3.0 mm 3.14 kg m Powder coated Local lm 150x50 150x50x3.0 150x50x3 3.0mm pipe box aluminum alu pc
A15: =IF('01 Aluminium'!$C$17="","","Aluminium Profiles & Systems") -> Aluminium Profiles & Systems | B15: =IF('01 Aluminium'!$C$17="","",'01 Aluminium'!A17) -> AL-013 | C15: =IF('01 Aluminium'!$C$17="","",'01 Aluminium'!B17) -> Standard Sections | D15: =IF('01 Aluminium'!$C$17="","",'01 Aluminium'!C17) -> Aluminium rectangular tube | E15: =IF('01 Aluminium'!$C$17="","",'01 Aluminium'!D17) -> 200 x 50 x 3.0 mm (3.95 kg/m) | F15: =IF('01 Aluminium'!$C$17="","",'01 Aluminium'!E17) -> Powder coated | G15: =IF('01 Aluminium'!$C$17="","",'01 Aluminium'!F17) -> Local | H15: =IF('01 Aluminium'!$C$17="","",'01 Aluminium'!G17) -> lm | I15: =IF('01 Aluminium'!$C$17="","",'01 Aluminium'!J17) -> 76.73 | J15: =IF('01 Aluminium'!$C$17="","",'01 Aluminium'!K17) -> 92.08 | K15: =IF('01 Aluminium'!$C$17="","",'01 Aluminium'!L17) -> 96.68 | L15: =IF('01 Aluminium'!$C$17="","",'01 Aluminium'!M17) -> Indicative | M15: =IF(D15="","",IF(AND(OR(Search!$C$6="All Categories",A15=Search!$C$6),OR(Search!$P$5="",ISNUMBER(SEARCH(" "&Search!$P$5,N15))),OR(Search!$P$6="",ISNUMBER(SEARCH(" "&Search!$P$6,N15))),OR(Search!$P$7="",ISNUMBER(SEARCH(" "&Search!$P$7,N15))),OR(Search!$P$8="",ISNUMBER(SEARCH(" "&Search!$P$8,N15))),OR(Search!$P$9="",ISNUMBER(SEARCH(" "&Search!$P$9,N15))),OR(Search!$P$10="",ISNUMBER(SEARCH(" "&Search!$P$10,N15)))),ROW(),"")) | N15: =IF(D15="",""," "&SUBSTITUTE(SUBSTITUTE(SUBSTITUTE(SUBSTITUTE(SUBSTITUTE(SUBSTITUTE(SUBSTITUTE(B15&" "&C15&" "&D15&" "&E15&" "&F15&" "&G15&" "&H15&" "&'01 Aluminium'!R17,"("," "),")"," "),"/"," "),"-"," "),","," "),";"," "),":"," ")&" ") -> AL 013 Standard Sections Aluminium rectangular tube 200 x 50 x 3.0 mm 3.95 kg m Powder coated Local lm 200x50 200x50x3.0 200x50x3 3.0mm pipe box aluminum alu pc
A16: =IF('01 Aluminium'!$C$18="","","Aluminium Profiles & Systems") -> Aluminium Profiles & Systems | B16: =IF('01 Aluminium'!$C$18="","",'01 Aluminium'!A18) -> AL-014 | C16: =IF('01 Aluminium'!$C$18="","",'01 Aluminium'!B18) -> Standard Sections | D16: =IF('01 Aluminium'!$C$18="","",'01 Aluminium'!C18) -> Aluminium equal angle | E16: =IF('01 Aluminium'!$C$18="","",'01 Aluminium'!D18) -> 25 x 25 x 2.0 mm (0.26 kg/m) | F16: =IF('01 Aluminium'!$C$18="","",'01 Aluminium'!E18) -> Powder coated | G16: =IF('01 Aluminium'!$C$18="","",'01 Aluminium'!F18) -> Local | H16: =IF('01 Aluminium'!$C$18="","",'01 Aluminium'!G18) -> lm | I16: =IF('01 Aluminium'!$C$18="","",'01 Aluminium'!J18) -> 5.05 | J16: =IF('01 Aluminium'!$C$18="","",'01 Aluminium'!K18) -> 6.06 | K16: =IF('01 Aluminium'!$C$18="","",'01 Aluminium'!L18) -> 6.36 | L16: =IF('01 Aluminium'!$C$18="","",'01 Aluminium'!M18) -> Indicative | M16: =IF(D16="","",IF(AND(OR(Search!$C$6="All Categories",A16=Search!$C$6),OR(Search!$P$5="",ISNUMBER(SEARCH(" "&Search!$P$5,N16))),OR(Search!$P$6="",ISNUMBER(SEARCH(" "&Search!$P$6,N16))),OR(Search!$P$7="",ISNUMBER(SEARCH(" "&Search!$P$7,N16))),OR(Search!$P$8="",ISNUMBER(SEARCH(" "&Search!$P$8,N16))),OR(Search!$P$9="",ISNUMBER(SEARCH(" "&Search!$P$9,N16))),OR(Search!$P$10="",ISNUMBER(SEARCH(" "&Search!$P$10,N16)))),ROW(),"")) | N16: =IF(D16="",""," "&SUBSTITUTE(SUBSTITUTE(SUBSTITUTE(SUBSTITUTE(SUBSTITUTE(SUBSTITUTE(SUBSTITUTE(B16&" "&C16&" "&D16&" "&E16&" "&F16&" "&G16&" "&H16&" "&'01 Aluminium'!R18,"("," "),")"," "),"/"," "),"-"," "),","," "),";"," "),":"," ")&" ") -> AL 014 Standard Sections Aluminium equal angle 25 x 25 x 2.0 mm 0.26 kg m Powder coated Local lm 25x25 25x25x2.0 25x25x2 2.0mm aluminum alu pc angle l
A17: =IF('01 Aluminium'!$C$19="","","Aluminium Profiles & Systems") -> Aluminium Profiles & Systems | B17: =IF('01 Aluminium'!$C$19="","",'01 Aluminium'!A19) -> AL-015 | C17: =IF('01 Aluminium'!$C$19="","",'01 Aluminium'!B19) -> Standard Sections | D17: =IF('01 Aluminium'!$C$19="","",'01 Aluminium'!C19) -> Aluminium equal angle | E17: =IF('01 Aluminium'!$C$19="","",'01 Aluminium'!D19) -> 50 x 50 x 3.0 mm (0.79 kg/m) | F17: =IF('01 Aluminium'!$C$19="","",'01 Aluminium'!E19) -> Powder coated | G17: =IF('01 Aluminium'!$C$19="","",'01 Aluminium'!F19) -> Local | H17: =IF('01 Aluminium'!$C$19="","",'01 Aluminium'!G19) -> lm | I17: =IF('01 Aluminium'!$C$19="","",'01 Aluminium'!J19) -> 15.35 | J17: =IF('01 Aluminium'!$C$19="","",'01 Aluminium'!K19) -> 18.42 | K17: =IF('01 Aluminium'!$C$19="","",'01 Aluminium'!L19) -> 19.34 | L17: =IF('01 Aluminium'!$C$19="","",'01 Aluminium'!M19) -> Indicative | M17: =IF(D17="","",IF(AND(OR(Search!$C$6="All Categories",A17=Search!$C$6),OR(Search!$P$5="",ISNUMBER(SEARCH(" "&Search!$P$5,N17))),OR(Search!$P$6="",ISNUMBER(SEARCH(" "&Search!$P$6,N17))),OR(Search!$P$7="",ISNUMBER(SEARCH(" "&Search!$P$7,N17))),OR(Search!$P$8="",ISNUMBER(SEARCH(" "&Search!$P$8,N17))),OR(Search!$P$9="",ISNUMBER(SEARCH(" "&Search!$P$9,N17))),OR(Search!$P$10="",ISNUMBER(SEARCH(" "&Search!$P$10,N17)))),ROW(),"")) | N17: =IF(D17="",""," "&SUBSTITUTE(SUBSTITUTE(SUBSTITUTE(SUBSTITUTE(SUBSTITUTE(SUBSTITUTE(SUBSTITUTE(B17&" "&C17&" "&D17&" "&E17&" "&F17&" "&G17&" "&H17&" "&'01 Aluminium'!R19,"("," "),")"," "),"/"," "),"-"," "),","," "),";"," "),":"," ")&" ") -> AL 015 Standard Sections Aluminium equal angle 50 x 50 x 3.0 mm 0.79 kg m Powder coated Local lm 50x50 50x50x3.0 50x50x3 3.0mm aluminum alu pc angle l
A18: =IF('01 Aluminium'!$C$20="","","Aluminium Profiles & Systems") -> Aluminium Profiles & Systems | B18: =IF('01 Aluminium'!$C$20="","",'01 Aluminium'!A20) -> AL-016 | C18: =IF('01 Aluminium'!$C$20="","",'01 Aluminium'!B20) -> Standard Sections | D18: =IF('01 Aluminium'!$C$20="","",'01 Aluminium'!C20) -> Aluminium flat bar | E18: =IF('01 Aluminium'!$C$20="","",'01 Aluminium'!D20) -> 50 x 5 mm (0.68 kg/m) | F18: =IF('01 Aluminium'!$C$20="","",'01 Aluminium'!E20) -> Powder coated | G18: =IF('01 Aluminium'!$C$20="","",'01 Aluminium'!F20) -> Local | H18: =IF('01 Aluminium'!$C$20="","",'01 Aluminium'!G20) -> lm | I18: =IF('01 Aluminium'!$C$20="","",'01 Aluminium'!J20) -> 13.21 | J18: =IF('01 Aluminium'!$C$20="","",'01 Aluminium'!K20) -> 15.85 | K18: =IF('01 Aluminium'!$C$20="","",'01 Aluminium'!L20) -> 16.64 | L18: =IF('01 Aluminium'!$C$20="","",'01 Aluminium'!M20) -> Indicative | M18: =IF(D18="","",IF(AND(OR(Search!$C$6="All Categories",A18=Search!$C$6),OR(Search!$P$5="",ISNUMBER(SEARCH(" "&Search!$P$5,N18))),OR(Search!$P$6="",ISNUMBER(SEARCH(" "&Search!$P$6,N18))),OR(Search!$P$7="",ISNUMBER(SEARCH(" "&Search!$P$7,N18))),OR(Search!$P$8="",ISNUMBER(SEARCH(" "&Search!$P$8,N18))),OR(Search!$P$9="",ISNUMBER(SEARCH(" "&Search!$P$9,N18))),OR(Search!$P$10="",ISNUMBER(SEARCH(" "&Search!$P$10,N18)))),ROW(),"")) | N18: =IF(D18="",""," "&SUBSTITUTE(SUBSTITUTE(SUBSTITUTE(SUBSTITUTE(SUBSTITUTE(SUBSTITUTE(SUBSTITUTE(B18&" "&C18&" "&D18&" "&E18&" "&F18&" "&G18&" "&H18&" "&'01 Aluminium'!R20,"("," "),")"," "),"/"," "),"-"," "),","," "),";"," "),":"," ")&" ") -> AL 016 Standard Sections Aluminium flat bar 50 x 5 mm 0.68 kg m Powder coated Local lm 50x5 5mm aluminum alu pc patti strip
A19: =IF('01 Aluminium'!$C$21="","","Aluminium Profiles & Systems") -> Aluminium Profiles & Systems | B19: =IF('01 Aluminium'!$C$21="","",'01 Aluminium'!A21) -> AL-017 | C19: =IF('01 Aluminium'!$C$21="","",'01 Aluminium'!B21) -> Standard Sections | D19: =IF('01 Aluminium'!$C$21="","",'01 Aluminium'!C21) -> Aluminium flat bar | E19: =IF('01 Aluminium'!$C$21="","",'01 Aluminium'!D21) -> 100 x 6 mm (1.62 kg/m) | F19: =IF('01 Aluminium'!$C$21="","",'01 Aluminium'!E21) -> Powder coated | G19: =IF('01 Aluminium'!$C$21="","",'01 Aluminium'!F21) -> Local | H19: =IF('01 Aluminium'!$C$21="","",'01 Aluminium'!G21) -> lm | I19: =IF('01 Aluminium'!$C$21="","",'01 Aluminium'!J21) -> 31.47 | J19: =IF('01 Aluminium'!$C$21="","",'01 Aluminium'!K21) -> 37.76 | K19: =IF('01 Aluminium'!$C$21="","",'01 Aluminium'!L21) -> 39.65 | L19: =IF('01 Aluminium'!$C$21="","",'01 Aluminium'!M21) -> Indicative | M19: =IF(D19="","",IF(AND(OR(Search!$C$6="All Categories",A19=Search!$C$6),OR(Search!$P$5="",ISNUMBER(SEARCH(" "&Search!$P$5,N19))),OR(Search!$P$6="",ISNUMBER(SEARCH(" "&Search!$P$6,N19))),OR(Search!$P$7="",ISNUMBER(SEARCH(" "&Search!$P$7,N19))),OR(Search!$P$8="",ISNUMBER(SEARCH(" "&Search!$P$8,N19))),OR(Search!$P$9="",ISNUMBER(SEARCH(" "&Search!$P$9,N19))),OR(Search!$P$10="",ISNUMBER(SEARCH(" "&Search!$P$10,N19)))),ROW(),"")) | N19: =IF(D19="",""," "&SUBSTITUTE(SUBSTITUTE(SUBSTITUTE(SUBSTITUTE(SUBSTITUTE(SUBSTITUTE(SUBSTITUTE(B19&" "&C19&" "&D19&" "&E19&" "&F19&" "&G19&" "&H19&" "&'01 Aluminium'!R21,"("," "),")"," "),"/"," "),"-"," "),","," "),";"," "),":"," ")&" ") -> AL 017 Standard Sections Aluminium flat bar 100 x 6 mm 1.62 kg m Powder coated Local lm 100x6 6mm aluminum alu pc patti strip
A20: =IF('01 Aluminium'!$C$22="","","Aluminium Profiles & Systems") -> Aluminium Profiles & Systems | B20: =IF('01 Aluminium'!$C$22="","",'01 Aluminium'!A22) -> AL-018 | C20: =IF('01 Aluminium'!$C$22="","",'01 Aluminium'!B22) -> Standard Sections | D20: =IF('01 Aluminium'!$C$22="","",'01 Aluminium'!C22) -> Aluminium U-channel for glass | E20: =IF('01 Aluminium'!$C$22="","",'01 Aluminium'!D22) -> For 10-12 mm glass (0.45 kg/m) | F20: =IF('01 Aluminium'!$C$22="","",'01 Aluminium'!E22) -> Powder coated / anodized | G20: =IF('01 Aluminium'!$C$22="","",'01 Aluminium'!F22) -> Local | H20: =IF('01 Aluminium'!$C$22="","",'01 Aluminium'!G22) -> lm | I20: =IF('01 Aluminium'!$C$22="","",'01 Aluminium'!J22) -> 8.75 | J20: =IF('01 Aluminium'!$C$22="","",'01 Aluminium'!K22) -> 10.5 | K20: =IF('01 Aluminium'!$C$22="","",'01 Aluminium'!L22) -> 11.03 | L20: =IF('01 Aluminium'!$C$22="","",'01 Aluminium'!M22) -> Indicative | M20: =IF(D20="","",IF(AND(OR(Search!$C$6="All Categories",A20=Search!$C$6),OR(Search!$P$5="",ISNUMBER(SEARCH(" "&Search!$P$5,N20))),OR(Search!$P$6="",ISNUMBER(SEARCH(" "&Search!$P$6,N20))),OR(Search!$P$7="",ISNUMBER(SEARCH(" "&Search!$P$7,N20))),OR(Search!$P$8="",ISNUMBER(SEARCH(" "&Search!$P$8,N20))),OR(Search!$P$9="",ISNUMBER(SEARCH(" "&Search!$P$9,N20))),OR(Search!$P$10="",ISNUMBER(SEARCH(" "&Search!$P$10,N20)))),ROW(),"")) | N20: =IF(D20="",""," "&SUBSTITUTE(SUBSTITUTE(SUBSTITUTE(SUBSTITUTE(SUBSTITUTE(SUBSTITUTE(SUBSTITUTE(B20&" "&C20&" "&D20&" "&E20&" "&F20&" "&G20&" "&H20&" "&'01 Aluminium'!R22,"("," "),")"," "),"/"," "),"-"," "),","," "),";"," "),":"," ")&" ") -> AL 018 Standard Sections Aluminium U channel for glass For 10 12 mm glass 0.45 kg m Powder coated anodized Local lm 12mm aluminum alu pc stainless steel
A21: =IF('01 Aluminium'!$C$23="","","Aluminium Profiles & Systems") -> Aluminium Profiles & Systems | B21: =IF('01 Aluminium'!$C$23="","",'01 Aluminium'!A23) -> AL-019 | C21: =IF('01 Aluminium'!$C$23="","",'01 Aluminium'!B23) -> Standard Sections | D21: =IF('01 Aluminium'!$C$23="","",'01 Aluminium'!C23) -> Aluminium heavy U-channel (frameless partition) | E21: =IF('01 Aluminium'!$C$23="","",'01 Aluminium'!D23) -> 40 x 40 mm (0.90 kg/m) | F21: =IF('01 Aluminium'!$C$23="","",'01 Aluminium'!E23) -> Anodized / PC | G21: =IF('01 Aluminium'!$C$23="","",'01 Aluminium'!F23) -> Local | H21: =IF('01 Aluminium'!$C$23="","",'01 Aluminium'!G23) -> lm | I21: =IF('01 Aluminium'!$C$23="","",'01 Aluminium'!J23) -> 17.48 | J21: =IF('01 Aluminium'!$C$23="","",'01 Aluminium'!K23) -> 20.98 | K21: =IF('01 Aluminium'!$C$23="","",'01 Aluminium'!L23) -> 22.03 | L21: =IF('01 Aluminium'!$C$23="","",'01 Aluminium'!M23) -> Indicative | M21: =IF(D21="","",IF(AND(OR(Search!$C$6="All Categories",A21=Search!$C$6),OR(Search!$P$5="",ISNUMBER(SEARCH(" "&Search!$P$5,N21))),OR(Search!$P$6="",ISNUMBER(SEARCH(" "&Search!$P$6,N21))),OR(Search!$P$7="",ISNUMBER(SEARCH(" "&Search!$P$7,N21))),OR(Search!$P$8="",ISNUMBER(SEARCH(" "&Search!$P$8,N21))),OR(Search!$P$9="",ISNUMBER(SEARCH(" "&Search!$P$9,N21))),OR(Search!$P$10="",ISNUMBER(SEARCH(" "&Search!$P$10,N21)))),ROW(),"")) | N21: =IF(D21="",""," "&SUBSTITUTE(SUBSTITUTE(SUBSTITUTE(SUBSTITUTE(SUBSTITUTE(SUBSTITUTE(SUBSTITUTE(B21&" "&C21&" "&D21&" "&E21&" "&F21&" "&G21&" "&H21&" "&'01 Aluminium'!R23,"("," "),")"," "),"/"," "),"-"," "),","," "),";"," "),":"," ")&" ") -> AL 019 Standard Sections Aluminium heavy U channel frameless partition 40 x 40 mm 0.90 kg m Anodized PC Local lm 40x40 40mm aluminum alu stainless steel
A22: =IF('01 Aluminium'!$C$24="","","Aluminium Profiles & Systems") -> Aluminium Profiles & Systems | B22: =IF('01 Aluminium'!$C$24="","",'01 Aluminium'!A24) -> AL-020 | C22: =IF('01 Aluminium'!$C$24="","",'01 Aluminium'!B24) -> Sliding Window System | D22: =IF('01 Aluminium'!$C$24="","",'01 Aluminium'!C24) -> Sliding window outer frame - 2 track | E22: =IF('01 Aluminium'!$C$24="","",'01 Aluminium'!D24) -> Non-thermal (approx. 1.25 kg/m) | F22: =IF('01 Aluminium'!$C$24="","",'01 Aluminium'!E24) -> Powder coated | G22: =IF('01 Aluminium'!$C$24="","",'01 Aluminium'!F24) -> Gulf Extrusions / Equiv. | H22: =IF('01 Aluminium'!$C$24="","",'01 Aluminium'!G24) -> lm | I22: =IF('01 Aluminium'!$C$24="","",'01 Aluminium'!J24) -> 24.29 | J22: =IF('01 Aluminium'!$C$24="","",'01 Aluminium'!K24) -> 29.15 | K22: =IF('01 Aluminium'!$C$24="","",'01 Aluminium'!L24) -> 30.61 | L22: =IF('01 Aluminium'!$C$24="","",'01 Aluminium'!M24) -> Indicative | M22: =IF(D22="","",IF(AND(OR(Search!$C$6="All Categories",A22=Search!$C$6),OR(Search!$P$5="",ISNUMBER(SEARCH(" "&Search!$P$5,N22))),OR(Search!$P$6="",ISNUMBER(SEARCH(" "&Search!$P$6,N22))),OR(Search!$P$7="",ISNUMBER(SEARCH(" "&Search!$P$7,N22))),OR(Search!$P$8="",ISNUMBER(SEARCH(" "&Search!$P$8,N22))),OR(Search!$P$9="",ISNUMBER(SEARCH(" "&Search!$P$9,N22))),OR(Search!$P$10="",ISNUMBER(SEARCH(" "&Search!$P$10,N22)))),ROW(),"")) | N22: =IF(D22="",""," "&SUBSTITUTE(SUBSTITUTE(SUBSTITUTE(SUBSTITUTE(SUBSTITUTE(SUBSTITUTE(SUBSTITUTE(B22&" "&C22&" "&D22&" "&E22&" "&F22&" "&G22&" "&H22&" "&'01 Aluminium'!R24,"("," "),")"," "),"/"," "),"-"," "),","," "),";"," "),":"," ")&" ") -> AL 020 Sliding Window System Sliding window outer frame 2 track Non thermal approx. 1.25 kg m Powder coated Gulf Extrusions Equiv. lm pc
A23: =IF('01 Aluminium'!$C$25="","","Aluminium Profiles & Systems") -> Aluminium Profiles & Systems | B23: =IF('01 Aluminium'!$C$25="","",'01 Aluminium'!A25) -> AL-021 | C23: =IF('01 Aluminium'!$C$25="","",'01 Aluminium'!B25) -> Sliding Window System | D23: =IF('01 Aluminium'!$C$25="","",'01 Aluminium'!C25) -> Sliding window outer frame - 3 track | E23: =IF('01 Aluminium'!$C$25="","",'01 Aluminium'!D25) -> Non-thermal (approx. 1.75 kg/m) | F23: =IF('01 Aluminium'!$C$25="","",'01 Aluminium'!E25) -> Powder coated | G23: =IF('01 Aluminium'!$C$25="","",'01 Aluminium'!F25) -> Gulf Extrusions / Equiv. | H23: =IF('01 Aluminium'!$C$25="","",'01 Aluminium'!G25) -> lm | I23: =IF('01 Aluminium'!$C$25="","",'01 Aluminium'!J25) -> 34 | J23: =IF('01 Aluminium'!$C$25="","",'01 Aluminium'!K25) -> 40.8 | K23: =IF('01 Aluminium'!$C$25="","",'01 Aluminium'!L25) -> 42.84 | L23: =IF('01 Aluminium'!$C$25="","",'01 Aluminium'!M25) -> Indicative | M23: =IF(D23="","",IF(AND(OR(Search!$C$6="All Categories",A23=Search!$C$6),OR(Search!$P$5="",ISNUMBER(SEARCH(" "&Search!$P$5,N23))),OR(Search!$P$6="",ISNUMBER(SEARCH(" "&Search!$P$6,N23))),OR(Search!$P$7="",ISNUMBER(SEARCH(" "&Search!$P$7,N23))),OR(Search!$P$8="",ISNUMBER(SEARCH(" "&Search!$P$8,N23))),OR(Search!$P$9="",ISNUMBER(SEARCH(" "&Search!$P$9,N23))),OR(Search!$P$10="",ISNUMBER(SEARCH(" "&Search!$P$10,N23)))),ROW(),"")) | N23: =IF(D23="",""," "&SUBSTITUTE(SUBSTITUTE(SUBSTITUTE(SUBSTITUTE(SUBSTITUTE(SUBSTITUTE(SUBSTITUTE(B23&" "&C23&" "&D23&" "&E23&" "&F23&" "&G23&" "&H23&" "&'01 Aluminium'!R25,"("," "),")"," "),"/"," "),"-"," "),","," "),";"," "),":"," ")&" ") -> AL 021 Sliding Window System Sliding window outer frame 3 track Non thermal approx. 1.75 kg m Powder coated Gulf Extrusions Equiv. lm pc
A24: =IF('01 Aluminium'!$C$26="","","Aluminium Profiles & Systems") -> Aluminium Profiles & Systems | B24: =IF('01 Aluminium'!$C$26="","",'01 Aluminium'!A26) -> AL-022 | C24: =IF('01 Aluminium'!$C$26="","",'01 Aluminium'!B26) -> Sliding Window System | D24: =IF('01 Aluminium'!$C$26="","",'01 Aluminium'!C26) -> Sliding sash profile | E24: =IF('01 Aluminium'!$C$26="","",'01 Aluminium'!D26) -> Approx. 0.95 kg/m | F24: =IF('01 Aluminium'!$C$26="","",'01 Aluminium'!E26) -> Powder coated | G24: =IF('01 Aluminium'!$C$26="","",'01 Aluminium'!F26) -> Gulf Extrusions / Equiv. | H24: =IF('01 Aluminium'!$C$26="","",'01 Aluminium'!G26) -> lm | I24: =IF('01 Aluminium'!$C$26="","",'01 Aluminium'!J26) -> 18.46 | J24: =IF('01 Aluminium'!$C$26="","",'01 Aluminium'!K26) -> 22.15 | K24: =IF('01 Aluminium'!$C$26="","",'01 Aluminium'!L26) -> 23.26 | L24: =IF('01 Aluminium'!$C$26="","",'01 Aluminium'!M26) -> Indicative | M24: =IF(D24="","",IF(AND(OR(Search!$C$6="All Categories",A24=Search!$C$6),OR(Search!$P$5="",ISNUMBER(SEARCH(" "&Search!$P$5,N24))),OR(Search!$P$6="",ISNUMBER(SEARCH(" "&Search!$P$6,N24))),OR(Search!$P$7="",ISNUMBER(SEARCH(" "&Search!$P$7,N24))),OR(Search!$P$8="",ISNUMBER(SEARCH(" "&Search!$P$8,N24))),OR(Search!$P$9="",ISNUMBER(SEARCH(" "&Search!$P$9,N24))),OR(Search!$P$10="",ISNUMBER(SEARCH(" "&Search!$P$10,N24)))),ROW(),"")) | N24: =IF(D24="",""," "&SUBSTITUTE(SUBSTITUTE(SUBSTITUTE(SUBSTITUTE(SUBSTITUTE(SUBSTITUTE(SUBSTITUTE(B24&" "&C24&" "&D24&" "&E24&" "&F24&" "&G24&" "&H24&" "&'01 Aluminium'!R26,"("," "),")"," "),"/"," "),"-"," "),","," "),";"," "),":"," ")&" ") -> AL 022 Sliding Window System Sliding sash profile Approx. 0.95 kg m Powder coated Gulf Extrusions Equiv. lm pc
A25: =IF('01 Aluminium'!$C$27="","","Aluminium Profiles & Systems") -> Aluminium Profiles & Systems | B25: =IF('01 Aluminium'!$C$27="","",'01 Aluminium'!A27) -> AL-023 | C25: =IF('01 Aluminium'!$C$27="","",'01 Aluminium'!B27) -> Sliding Window System | D25: =IF('01 Aluminium'!$C$27="","",'01 Aluminium'!C27) -> Sliding interlock profile | E25: =IF('01 Aluminium'!$C$27="","",'01 Aluminium'!D27) -> Approx. 0.75 kg/m | F25: =IF('01 Aluminium'!$C$27="","",'01 Aluminium'!E27) -> Powder coated | G25: =IF('01 Aluminium'!$C$27="","",'01 Aluminium'!F27) -> Gulf Extrusions / Equiv. | H25: =IF('01 Aluminium'!$C$27="","",'01 Aluminium'!G27) -> lm | I25: =IF('01 Aluminium'!$C$27="","",'01 Aluminium'!J27) -> 14.57 | J25: =IF('01 Aluminium'!$C$27="","",'01 Aluminium'!K27) -> 17.48 | K25: =IF('01 Aluminium'!$C$27="","",'01 Aluminium'!L27) -> 18.35 | L25: =IF('01 Aluminium'!$C$27="","",'01 Aluminium'!M27) -> Indicative | M25: =IF(D25="","",IF(AND(OR(Search!$C$6="All Categories",A25=Search!$C$6),OR(Search!$P$5="",ISNUMBER(SEARCH(" "&Search!$P$5,N25))),OR(Search!$P$6="",ISNUMBER(SEARCH(" "&Search!$P$6,N25))),OR(Search!$P$7="",ISNUMBER(SEARCH(" "&Search!$P$7,N25))),OR(Search!$P$8="",ISNUMBER(SEARCH(" "&Search!$P$8,N25))),OR(Search!$P$9="",ISNUMBER(SEARCH(" "&Search!$P$9,N25))),OR(Search!$P$10="",ISNUMBER(SEARCH(" "&Search!$P$10,N25)))),ROW(),"")) | N25: =IF(D25="",""," "&SUBSTITUTE(SUBSTITUTE(SUBSTITUTE(SUBSTITUTE(SUBSTITUTE(SUBSTITUTE(SUBSTITUTE(B25&" "&C25&" "&D25&" "&E25&" "&F25&" "&G25&" "&H25&" "&'01 Aluminium'!R27,"("," "),")"," "),"/"," "),"-"," "),","," "),";"," "),":"," ")&" ") -> AL 023 Sliding Window System Sliding interlock profile Approx. 0.75 kg m Powder coated Gulf Extrusions Equiv. lm pc
A26: =IF('01 Aluminium'!$C$28="","","Aluminium Profiles & Systems") -> Aluminium Profiles & Systems | B26: =IF('01 Aluminium'!$C$28="","",'01 Aluminium'!A28) -> AL-024 | C26: =IF('01 Aluminium'!$C$28="","",'01 Aluminium'!B28) -> Sliding Window System | D26: =IF('01 Aluminium'!$C$28="","",'01 Aluminium'!C28) -> Thermal-break sliding frame | E26: =IF('01 Aluminium'!$C$28="","",'01 Aluminium'!D28) -> Approx. 2.40 kg/m | F26: =IF('01 Aluminium'!$C$28="","",'01 Aluminium'!E28) -> Powder coated | G26: =IF('01 Aluminium'!$C$28="","",'01 Aluminium'!F28) -> Gulf Extrusions / Equiv. | H26: =IF('01 Aluminium'!$C$28="","",'01 Aluminium'!G28) -> lm | I26: =IF('01 Aluminium'!$C$28="","",'01 Aluminium'!J28) -> 61.74 | J26: =IF('01 Aluminium'!$C$28="","",'01 Aluminium'!K28) -> 74.09 | K26: =IF('01 Aluminium'!$C$28="","",'01 Aluminium'!L28) -> 77.79 | L26: =IF('01 Aluminium'!$C$28="","",'01 Aluminium'!M28) -> Indicative | M26: =IF(D26="","",IF(AND(OR(Search!$C$6="All Categories",A26=Search!$C$6),OR(Search!$P$5="",ISNUMBER(SEARCH(" "&Search!$P$5,N26))),OR(Search!$P$6="",ISNUMBER(SEARCH(" "&Search!$P$6,N26))),OR(Search!$P$7="",ISNUMBER(SEARCH(" "&Search!$P$7,N26))),OR(Search!$P$8="",ISNUMBER(SEARCH(" "&Search!$P$8,N26))),OR(Search!$P$9="",ISNUMBER(SEARCH(" "&Search!$P$9,N26))),OR(Search!$P$10="",ISNUMBER(SEARCH(" "&Search!$P$10,N26)))),ROW(),"")) | N26: =IF(D26="",""," "&SUBSTITUTE(SUBSTITUTE(SUBSTITUTE(SUBSTITUTE(SUBSTITUTE(SUBSTITUTE(SUBSTITUTE(B26&" "&C26&" "&D26&" "&E26&" "&F26&" "&G26&" "&H26&" "&'01 Aluminium'!R28,"("," "),")"," "),"/"," "),"-"," "),","," "),";"," "),":"," ")&" ") -> AL 024 Sliding Window System Thermal break sliding frame Approx. 2.40 kg m Powder coated Gulf Extrusions Equiv. lm pc
A27: =IF('01 Aluminium'!$C$29="","","Aluminium Profiles & Systems") -> Aluminium Profiles & Systems | B27: =IF('01 Aluminium'!$C$29="","",'01 Aluminium'!A29) -> AL-025 | C27: =IF('01 Aluminium'!$C$29="","",'01 Aluminium'!B29) -> Sliding Window System | D27: =IF('01 Aluminium'!$C$29="","",'01 Aluminium'!C29) -> Lift & slide door frame (TB) | E27: =IF('01 Aluminium'!$C$29="","",'01 Aluminium'!D29) -> Approx. 3.80 kg/m | F27: =IF('01 Aluminium'!$C$29="","",'01 Aluminium'!E29) -> Powder coated | G27: =IF('01 Aluminium'!$C$29="","",'01 Aluminium'!F29) -> Gulf Extrusions / Equiv. | H27: =IF('01 Aluminium'!$C$29="","",'01 Aluminium'!G29) -> lm | I27: =IF('01 Aluminium'!$C$29="","",'01 Aluminium'!J29) -> 97.76 | J27: =IF('01 Aluminium'!$C$29="","",'01 Aluminium'!K29) -> 117.31 | K27: =IF('01 Aluminium'!$C$29="","",'01 Aluminium'!L29) -> 123.18 | L27: =IF('01 Aluminium'!$C$29="","",'01 Aluminium'!M29) -> Indicative | M27: =IF(D27="","",IF(AND(OR(Search!$C$6="All Categories",A27=Search!$C$6),OR(Search!$P$5="",ISNUMBER(SEARCH(" "&Search!$P$5,N27))),OR(Search!$P$6="",ISNUMBER(SEARCH(" "&Search!$P$6,N27))),OR(Search!$P$7="",ISNUMBER(SEARCH(" "&Search!$P$7,N27))),OR(Search!$P$8="",ISNUMBER(SEARCH(" "&Search!$P$8,N27))),OR(Search!$P$9="",ISNUMBER(SEARCH(" "&Search!$P$9,N27))),OR(Search!$P$10="",ISNUMBER(SEARCH(" "&Search!$P$10,N27)))),ROW(),"")) | N27: =IF(D27="",""," "&SUBSTITUTE(SUBSTITUTE(SUBSTITUTE(SUBSTITUTE(SUBSTITUTE(SUBSTITUTE(SUBSTITUTE(B27&" "&C27&" "&D27&" "&E27&" "&F27&" "&G27&" "&H27&" "&'01 Aluminium'!R29,"("," "),")"," "),"/"," "),"-"," "),","," "),";"," "),":"," ")&" ") -> AL 025 Sliding Window System Lift & slide door frame TB Approx. 3.80 kg m Powder coated Gulf Extrusions Equiv. lm pc
A28: =IF('01 Aluminium'!$C$30="","","Aluminium Profiles & Systems") -> Aluminium Profiles & Systems | B28: =IF('01 Aluminium'!$C$30="","",'01 Aluminium'!A30) -> AL-026 | C28: =IF('01 Aluminium'!$C$30="","",'01 Aluminium'!B30) -> Casement / Hinged System | D28: =IF('01 Aluminium'!$C$30="","",'01 Aluminium'!C30) -> Casement window frame | E28: =IF('01 Aluminium'!$C$30="","",'01 Aluminium'!D30) -> Approx. 0.95 kg/m | F28: =IF('01 Aluminium'!$C$30="","",'01 Aluminium'!E30) -> Powder coated | G28: =IF('01 Aluminium'!$C$30="","",'01 Aluminium'!F30) -> Gulf Extrusions / Equiv. | H28: =IF('01 Aluminium'!$C$30="","",'01 Aluminium'!G30) -> lm | I28: =IF('01 Aluminium'!$C$30="","",'01 Aluminium'!J30) -> 18.46 | J28: =IF('01 Aluminium'!$C$30="","",'01 Aluminium'!K30) -> 22.15 | K28: =IF('01 Aluminium'!$C$30="","",'01 Aluminium'!L30) -> 23.26 | L28: =IF('01 Aluminium'!$C$30="","",'01 Aluminium'!M30) -> Indicative | M28: =IF(D28="","",IF(AND(OR(Search!$C$6="All Categories",A28=Search!$C$6),OR(Search!$P$5="",ISNUMBER(SEARCH(" "&Search!$P$5,N28))),OR(Search!$P$6="",ISNUMBER(SEARCH(" "&Search!$P$6,N28))),OR(Search!$P$7="",ISNUMBER(SEARCH(" "&Search!$P$7,N28))),OR(Search!$P$8="",ISNUMBER(SEARCH(" "&Search!$P$8,N28))),OR(Search!$P$9="",ISNUMBER(SEARCH(" "&Search!$P$9,N28))),OR(Search!$P$10="",ISNUMBER(SEARCH(" "&Search!$P$10,N28)))),ROW(),"")) | N28: =IF(D28="",""," "&SUBSTITUTE(SUBSTITUTE(SUBSTITUTE(SUBSTITUTE(SUBSTITUTE(SUBSTITUTE(SUBSTITUTE(B28&" "&C28&" "&D28&" "&E28&" "&F28&" "&G28&" "&H28&" "&'01 Aluminium'!R30,"("," "),")"," "),"/"," "),"-"," "),","," "),";"," "),":"," ")&" ") -> AL 026 Casement Hinged System Casement window frame Approx. 0.95 kg m Powder coated Gulf Extrusions Equiv. lm pc
A29: =IF('01 Aluminium'!$C$31="","","Aluminium Profiles & Systems") -> Aluminium Profiles & Systems | B29: =IF('01 Aluminium'!$C$31="","",'01 Aluminium'!A31) -> AL-027 | C29: =IF('01 Aluminium'!$C$31="","",'01 Aluminium'!B31) -> Casement / Hinged System | D29: =IF('01 Aluminium'!$C$31="","",'01 Aluminium'!C31) -> Casement window sash | E29: =IF('01 Aluminium'!$C$31="","",'01 Aluminium'!D31) -> Approx. 1.05 kg/m | F29: =IF('01 Aluminium'!$C$31="","",'01 Aluminium'!E31) -> Powder coated | G29: =IF('01 Aluminium'!$C$31="","",'01 Aluminium'!F31) -> Gulf Extrusions / Equiv. | H29: =IF('01 Aluminium'!$C$31="","",'01 Aluminium'!G31) -> lm | I29: =IF('01 Aluminium'!$C$31="","",'01 Aluminium'!J31) -> 20.4 | J29: =IF('01 Aluminium'!$C$31="","",'01 Aluminium'!K31) -> 24.48 | K29: =IF('01 Aluminium'!$C$31="","",'01 Aluminium'!L31) -> 25.7 | L29: =IF('01 Aluminium'!$C$31="","",'01 Aluminium'!M31) -> Indicative | M29: =IF(D29="","",IF(AND(OR(Search!$C$6="All Categories",A29=Search!$C$6),OR(Search!$P$5="",ISNUMBER(SEARCH(" "&Search!$P$5,N29))),OR(Search!$P$6="",ISNUMBER(SEARCH(" "&Search!$P$6,N29))),OR(Search!$P$7="",ISNUMBER(SEARCH(" "&Search!$P$7,N29))),OR(Search!$P$8="",ISNUMBER(SEARCH(" "&Search!$P$8,N29))),OR(Search!$P$9="",ISNUMBER(SEARCH(" "&Search!$P$9,N29))),OR(Search!$P$10="",ISNUMBER(SEARCH(" "&Search!$P$10,N29)))),ROW(),"")) | N29: =IF(D29="",""," "&SUBSTITUTE(SUBSTITUTE(SUBSTITUTE(SUBSTITUTE(SUBSTITUTE(SUBSTITUTE(SUBSTITUTE(B29&" "&C29&" "&D29&" "&E29&" "&F29&" "&G29&" "&H29&" "&'01 Aluminium'!R31,"("," "),")"," "),"/"," "),"-"," "),","," "),";"," "),":"," ")&" ") -> AL 027 Casement Hinged System Casement window sash Approx. 1.05 kg m Powder coated Gulf Extrusions Equiv. lm pc
A30: =IF('01 Aluminium'!$C$32="","","Aluminium Profiles & Systems") -> Aluminium Profiles & Systems | B30: =IF('01 Aluminium'!$C$32="","",'01 Aluminium'!A32) -> AL-028 | C30: =IF('01 Aluminium'!$C$32="","",'01 Aluminium'!B32) -> Casement / Hinged System | D30: =IF('01 Aluminium'!$C$32="","",'01 Aluminium'!C32) -> Window mullion / transom | E30: =IF('01 Aluminium'!$C$32="","",'01 Aluminium'!D32) -> Approx. 1.30 kg/m | F30: =IF('01 Aluminium'!$C$32="","",'01 Aluminium'!E32) -> Powder coated | G30: =IF('01 Aluminium'!$C$32="","",'01 Aluminium'!F32) -> Gulf Extrusions / Equiv. | H30: =IF('01 Aluminium'!$C$32="","",'01 Aluminium'!G32) -> lm | I30: =IF('01 Aluminium'!$C$32="","",'01 Aluminium'!J32) -> 25.25 | J30: =IF('01 Aluminium'!$C$32="","",'01 Aluminium'!K32) -> 30.3 | K30: =IF('01 Aluminium'!$C$32="","",'01 Aluminium'!L32) -> 31.82 | L30: =IF('01 Aluminium'!$C$32="","",'01 Aluminium'!M32) -> Indicative | M30: =IF(D30="","",IF(AND(OR(Search!$C$6="All Categories",A30=Search!$C$6),OR(Search!$P$5="",ISNUMBER(SEARCH(" "&Search!$P$5,N30))),OR(Search!$P$6="",ISNUMBER(SEARCH(" "&Search!$P$6,N30))),OR(Search!$P$7="",ISNUMBER(SEARCH(" "&Search!$P$7,N30))),OR(Search!$P$8="",ISNUMBER(SEARCH(" "&Search!$P$8,N30))),OR(Search!$P$9="",ISNUMBER(SEARCH(" "&Search!$P$9,N30))),OR(Search!$P$10="",ISNUMBER(SEARCH(" "&Search!$P$10,N30)))),ROW(),"")) | N30: =IF(D30="",""," "&SUBSTITUTE(SUBSTITUTE(SUBSTITUTE(SUBSTITUTE(SUBSTITUTE(SUBSTITUTE(SUBSTITUTE(B30&" "&C30&" "&D30&" "&E30&" "&F30&" "&G30&" "&H30&" "&'01 Aluminium'!R32,"("," "),")"," "),"/"," "),"-"," "),","," "),";"," "),":"," ")&" ") -> AL 028 Casement Hinged System Window mullion transom Approx. 1.30 kg m Powder coated Gulf Extrusions Equiv. lm pc
A31: =IF('01 Aluminium'!$C$33="","","Aluminium Profiles & Systems") -> Aluminium Profiles & Systems | B31: =IF('01 Aluminium'!$C$33="","",'01 Aluminium'!A33) -> AL-029 | C31: =IF('01 Aluminium'!$C$33="","",'01 Aluminium'!B33) -> Casement / Hinged System | D31: =IF('01 Aluminium'!$C$33="","",'01 Aluminium'!C33) -> Thermal-break casement frame | E31: =IF('01 Aluminium'!$C$33="","",'01 Aluminium'!D33) -> Approx. 1.50 kg/m | F31: =IF('01 Aluminium'!$C$33="","",'01 Aluminium'!E33) -> Powder coated | G31: =IF('01 Aluminium'!$C$33="","",'01 Aluminium'!F33) -> Gulf Extrusions / Equiv. | H31: =IF('01 Aluminium'!$C$33="","",'01 Aluminium'!G33) -> lm | I31: =IF('01 Aluminium'!$C$33="","",'01 Aluminium'!J33) -> 38.59 | J31: =IF('01 Aluminium'!$C$33="","",'01 Aluminium'!K33) -> 46.31 | K31: =IF('01 Aluminium'!$C$33="","",'01 Aluminium'!L33) -> 48.63 | L31: =IF('01 Aluminium'!$C$33="","",'01 Aluminium'!M33) -> Indicative | M31: =IF(D31="","",IF(AND(OR(Search!$C$6="All Categories",A31=Search!$C$6),OR(Search!$P$5="",ISNUMBER(SEARCH(" "&Search!$P$5,N31))),OR(Search!$P$6="",ISNUMBER(SEARCH(" "&Search!$P$6,N31))),OR(Search!$P$7="",ISNUMBER(SEARCH(" "&Search!$P$7,N31))),OR(Search!$P$8="",ISNUMBER(SEARCH(" "&Search!$P$8,N31))),OR(Search!$P$9="",ISNUMBER(SEARCH(" "&Search!$P$9,N31))),OR(Search!$P$10="",ISNUMBER(SEARCH(" "&Search!$P$10,N31)))),ROW(),"")) | N31: =IF(D31="",""," "&SUBSTITUTE(SUBSTITUTE(SUBSTITUTE(SUBSTITUTE(SUBSTITUTE(SUBSTITUTE(SUBSTITUTE(B31&" "&C31&" "&D31&" "&E31&" "&F31&" "&G31&" "&H31&" "&'01 Aluminium'!R33,"("," "),")"," "),"/"," "),"-"," "),","," "),";"," "),":"," ")&" ") -> AL 029 Casement Hinged System Thermal break casement frame Approx. 1.50 kg m Powder coated Gulf Extrusions Equiv. lm pc
A32: =IF('01 Aluminium'!$C$34="","","Aluminium Profiles & Systems") -> Aluminium Profiles & Systems | B32: =IF('01 Aluminium'!$C$34="","",'01 Aluminium'!A34) -> AL-030 | C32: =IF('01 Aluminium'!$C$34="","",'01 Aluminium'!B34) -> Casement / Hinged System | D32: =IF('01 Aluminium'!$C$34="","",'01 Aluminium'!C34) -> Hinged door frame | E32: =IF('01 Aluminium'!$C$34="","",'01 Aluminium'!D34) -> Approx. 1.60 kg/m | F32: =IF('01 Aluminium'!$C$34="","",'01 Aluminium'!E34) -> Powder coated | G32: =IF('01 Aluminium'!$C$34="","",'01 Aluminium'!F34) -> Gulf Extrusions / Equiv. | H32: =IF('01 Aluminium'!$C$34="","",'01 Aluminium'!G34) -> lm | I32: =IF('01 Aluminium'!$C$34="","",'01 Aluminium'!J34) -> 31.08 | J32: =IF('01 Aluminium'!$C$34="","",'01 Aluminium'!K34) -> 37.3 | K32: =IF('01 Aluminium'!$C$34="","",'01 Aluminium'!L34) -> 39.17 | L32: =IF('01 Aluminium'!$C$34="","",'01 Aluminium'!M34) -> Indicative | M32: =IF(D32="","",IF(AND(OR(Search!$C$6="All Categories",A32=Search!$C$6),OR(Search!$P$5="",ISNUMBER(SEARCH(" "&Search!$P$5,N32))),OR(Search!$P$6="",ISNUMBER(SEARCH(" "&Search!$P$6,N32))),OR(Search!$P$7="",ISNUMBER(SEARCH(" "&Search!$P$7,N32))),OR(Search!$P$8="",ISNUMBER(SEARCH(" "&Search!$P$8,N32))),OR(Search!$P$9="",ISNUMBER(SEARCH(" "&Search!$P$9,N32))),OR(Search!$P$10="",ISNUMBER(SEARCH(" "&Search!$P$10,N32)))),ROW(),"")) | N32: =IF(D32="",""," "&SUBSTITUTE(SUBSTITUTE(SUBSTITUTE(SUBSTITUTE(SUBSTITUTE(SUBSTITUTE(SUBSTITUTE(B32&" "&C32&" "&D32&" "&E32&" "&F32&" "&G32&" "&H32&" "&'01 Aluminium'!R34,"("," "),")"," "),"/"," "),"-"," "),","," "),";"," "),":"," ")&" ") -> AL 030 Casement Hinged System Hinged door frame Approx. 1.60 kg m Powder coated Gulf Extrusions Equiv. lm pc
A33: =IF('01 Aluminium'!$C$35="","","Aluminium Profiles & Systems") -> Aluminium Profiles & Systems | B33: =IF('01 Aluminium'!$C$35="","",'01 Aluminium'!A35) -> AL-031 | C33: =IF('01 Aluminium'!$C$35="","",'01 Aluminium'!B35) -> Casement / Hinged System | D33: =IF('01 Aluminium'!$C$35="","",'01 Aluminium'!C35) -> Hinged door leaf (stile) | E33: =IF('01 Aluminium'!$C$35="","",'01 Aluminium'!D35) -> Approx. 2.10 kg/m | F33: =IF('01 Aluminium'!$C$35="","",'01 Aluminium'!E35) -> Powder coated | G33: =IF('01 Aluminium'!$C$35="","",'01 Aluminium'!F35) -> Gulf Extrusions / Equiv. | H33: =IF('01 Aluminium'!$C$35="","",'01 Aluminium'!G35) -> lm | I33: =IF('01 Aluminium'!$C$35="","",'01 Aluminium'!J35) -> 40.79 | J33: =IF('01 Aluminium'!$C$35="","",'01 Aluminium'!K35) -> 48.95 | K33: =IF('01 Aluminium'!$C$35="","",'01 Aluminium'!L35) -> 51.4 | L33: =IF('01 Aluminium'!$C$35="","",'01 Aluminium'!M35) -> Indicative | M33: =IF(D33="","",IF(AND(OR(Search!$C$6="All Categories",A33=Search!$C$6),OR(Search!$P$5="",ISNUMBER(SEARCH(" "&Search!$P$5,N33))),OR(Search!$P$6="",ISNUMBER(SEARCH(" "&Search!$P$6,N33))),OR(Search!$P$7="",ISNUMBER(SEARCH(" "&Search!$P$7,N33))),OR(Search!$P$8="",ISNUMBER(SEARCH(" "&Search!$P$8,N33))),OR(Search!$P$9="",ISNUMBER(SEARCH(" "&Search!$P$9,N33))),OR(Search!$P$10="",ISNUMBER(SEARCH(" "&Search!$P$10,N33)))),ROW(),"")) | N33: =IF(D33="",""," "&SUBSTITUTE(SUBSTITUTE(SUBSTITUTE(SUBSTITUTE(SUBSTITUTE(SUBSTITUTE(SUBSTITUTE(B33&" "&C33&" "&D33&" "&E33&" "&F33&" "&G33&" "&H33&" "&'01 Aluminium'!R35,"("," "),")"," "),"/"," "),"-"," "),","," "),";"," "),":"," ")&" ") -> AL 031 Casement Hinged System Hinged door leaf stile Approx. 2.10 kg m Powder coated Gulf Extrusions Equiv. lm pc
A34: =IF('01 Aluminium'!$C$36="","","Aluminium Profiles & Systems") -> Aluminium Profiles & Systems | B34: =IF('01 Aluminium'!$C$36="","",'01 Aluminium'!A36) -> AL-032 | C34: =IF('01 Aluminium'!$C$36="","",'01 Aluminium'!B36) -> Casement / Hinged System | D34: =IF('01 Aluminium'!$C$36="","",'01 Aluminium'!C36) -> Door bottom rail (deep) | E34: =IF('01 Aluminium'!$C$36="","",'01 Aluminium'!D36) -> Approx. 2.80 kg/m | F34: =IF('01 Aluminium'!$C$36="","",'01 Aluminium'!E36) -> Powder coated | G34: =IF('01 Aluminium'!$C$36="","",'01 Aluminium'!F36) -> Gulf Extrusions / Equiv. | H34: =IF('01 Aluminium'!$C$36="","",'01 Aluminium'!G36) -> lm | I34: =IF('01 Aluminium'!$C$36="","",'01 Aluminium'!J36) -> 54.39 | J34: =IF('01 Aluminium'!$C$36="","",'01 Aluminium'!K36) -> 65.27 | K34: =IF('01 Aluminium'!$C$36="","",'01 Aluminium'!L36) -> 68.53 | L34: =IF('01 Aluminium'!$C$36="","",'01 Aluminium'!M36) -> Indicative | M34: =IF(D34="","",IF(AND(OR(Search!$C$6="All Categories",A34=Search!$C$6),OR(Search!$P$5="",ISNUMBER(SEARCH(" "&Search!$P$5,N34))),OR(Search!$P$6="",ISNUMBER(SEARCH(" "&Search!$P$6,N34))),OR(Search!$P$7="",ISNUMBER(SEARCH(" "&Search!$P$7,N34))),OR(Search!$P$8="",ISNUMBER(SEARCH(" "&Search!$P$8,N34))),OR(Search!$P$9="",ISNUMBER(SEARCH(" "&Search!$P$9,N34))),OR(Search!$P$10="",ISNUMBER(SEARCH(" "&Search!$P$10,N34)))),ROW(),"")) | N34: =IF(D34="",""," "&SUBSTITUTE(SUBSTITUTE(SUBSTITUTE(SUBSTITUTE(SUBSTITUTE(SUBSTITUTE(SUBSTITUTE(B34&" "&C34&" "&D34&" "&E34&" "&F34&" "&G34&" "&H34&" "&'01 Aluminium'!R36,"("," "),")"," "),"/"," "),"-"," "),","," "),";"," "),":"," ")&" ") -> AL 032 Casement Hinged System Door bottom rail deep Approx. 2.80 kg m Powder coated Gulf Extrusions Equiv. lm pc
A35: =IF('01 Aluminium'!$C$37="","","Aluminium Profiles & Systems") -> Aluminium Profiles & Systems | B35: =IF('01 Aluminium'!$C$37="","",'01 Aluminium'!A37) -> AL-033 | C35: =IF('01 Aluminium'!$C$37="","",'01 Aluminium'!B37) -> Casement / Hinged System | D35: =IF('01 Aluminium'!$C$37="","",'01 Aluminium'!C37) -> Glazing bead | E35: =IF('01 Aluminium'!$C$37="","",'01 Aluminium'!D37) -> Approx. 0.25 kg/m | F35: =IF('01 Aluminium'!$C$37="","",'01 Aluminium'!E37) -> Powder coated | G35: =IF('01 Aluminium'!$C$37="","",'01 Aluminium'!F37) -> Gulf Extrusions / Equiv. | H35: =IF('01 Aluminium'!$C$37="","",'01 Aluminium'!G37) -> lm | I35: =IF('01 Aluminium'!$C$37="","",'01 Aluminium'!J37) -> 4.86 | J35: =IF('01 Aluminium'!$C$37="","",'01 Aluminium'!K37) -> 5.83 | K35: =IF('01 Aluminium'!$C$37="","",'01 Aluminium'!L37) -> 6.12 | L35: =IF('01 Aluminium'!$C$37="","",'01 Aluminium'!M37) -> Indicative | M35: =IF(D35="","",IF(AND(OR(Search!$C$6="All Categories",A35=Search!$C$6),OR(Search!$P$5="",ISNUMBER(SEARCH(" "&Search!$P$5,N35))),OR(Search!$P$6="",ISNUMBER(SEARCH(" "&Search!$P$6,N35))),OR(Search!$P$7="",ISNUMBER(SEARCH(" "&Search!$P$7,N35))),OR(Search!$P$8="",ISNUMBER(SEARCH(" "&Search!$P$8,N35))),OR(Search!$P$9="",ISNUMBER(SEARCH(" "&Search!$P$9,N35))),OR(Search!$P$10="",ISNUMBER(SEARCH(" "&Search!$P$10,N35)))),ROW(),"")) | N35: =IF(D35="",""," "&SUBSTITUTE(SUBSTITUTE(SUBSTITUTE(SUBSTITUTE(SUBSTITUTE(SUBSTITUTE(SUBSTITUTE(B35&" "&C35&" "&D35&" "&E35&" "&F35&" "&G35&" "&H35&" "&'01 Aluminium'!R37,"("," "),")"," "),"/"," "),"-"," "),","," "),";"," "),":"," ")&" ") -> AL 033 Casement Hinged System Glazing bead Approx. 0.25 kg m Powder coated Gulf Extrusions Equiv. lm pc
A36: =IF('01 Aluminium'!$C$38="","","Aluminium Profiles & Systems") -> Aluminium Profiles & Systems | B36: =IF('01 Aluminium'!$C$38="","",'01 Aluminium'!A38) -> AL-034 | C36: =IF('01 Aluminium'!$C$38="","",'01 Aluminium'!B38) -> Curtain Wall System | D36: =IF('01 Aluminium'!$C$38="","",'01 Aluminium'!C38) -> Curtain wall mullion - 150 mm deep | E36: =IF('01 Aluminium'!$C$38="","",'01 Aluminium'!D38) -> Stick system (approx. 3.80 kg/m) | F36: =IF('01 Aluminium'!$C$38="","",'01 Aluminium'!E38) -> Powder coated | G36: =IF('01 Aluminium'!$C$38="","",'01 Aluminium'!F38) -> Gulf Extrusions / Equiv. | H36: =IF('01 Aluminium'!$C$38="","",'01 Aluminium'!G38) -> lm | I36: =IF('01 Aluminium'!$C$38="","",'01 Aluminium'!J38) -> 73.82 | J36: =IF('01 Aluminium'!$C$38="","",'01 Aluminium'!K38) -> 88.58 | K36: =IF('01 Aluminium'!$C$38="","",'01 Aluminium'!L38) -> 93.01 | L36: =IF('01 Aluminium'!$C$38="","",'01 Aluminium'!M38) -> Indicative | M36: =IF(D36="","",IF(AND(OR(Search!$C$6="All Categories",A36=Search!$C$6),OR(Search!$P$5="",ISNUMBER(SEARCH(" "&Search!$P$5,N36))),OR(Search!$P$6="",ISNUMBER(SEARCH(" "&Search!$P$6,N36))),OR(Search!$P$7="",ISNUMBER(SEARCH(" "&Search!$P$7,N36))),OR(Search!$P$8="",ISNUMBER(SEARCH(" "&Search!$P$8,N36))),OR(Search!$P$9="",ISNUMBER(SEARCH(" "&Search!$P$9,N36))),OR(Search!$P$10="",ISNUMBER(SEARCH(" "&Search!$P$10,N36)))),ROW(),"")) | N36: =IF(D36="",""," "&SUBSTITUTE(SUBSTITUTE(SUBSTITUTE(SUBSTITUTE(SUBSTITUTE(SUBSTITUTE(SUBSTITUTE(B36&" "&C36&" "&D36&" "&E36&" "&F36&" "&G36&" "&H36&" "&'01 Aluminium'!R38,"("," "),")"," "),"/"," "),"-"," "),","," "),";"," "),":"," ")&" ") -> AL 034 Curtain Wall System Curtain wall mullion 150 mm deep Stick system approx. 3.80 kg m Powder coated Gulf Extrusions Equiv. lm 150mm pc
A37: =IF('01 Aluminium'!$C$39="","","Aluminium Profiles & Systems") -> Aluminium Profiles & Systems | B37: =IF('01 Aluminium'!$C$39="","",'01 Aluminium'!A39) -> AL-035 | C37: =IF('01 Aluminium'!$C$39="","",'01 Aluminium'!B39) -> Curtain Wall System | D37: =IF('01 Aluminium'!$C$39="","",'01 Aluminium'!C39) -> Curtain wall mullion - 180 mm deep | E37: =IF('01 Aluminium'!$C$39="","",'01 Aluminium'!D39) -> Stick system (approx. 4.60 kg/m) | F37: =IF('01 Aluminium'!$C$39="","",'01 Aluminium'!E39) -> Powder coated | G37: =IF('01 Aluminium'!$C$39="","",'01 Aluminium'!F39) -> Gulf Extrusions / Equiv. | H37: =IF('01 Aluminium'!$C$39="","",'01 Aluminium'!G39) -> lm | I37: =IF('01 Aluminium'!$C$39="","",'01 Aluminium'!J39) -> 89.36 | J37: =IF('01 Aluminium'!$C$39="","",'01 Aluminium'!K39) -> 107.23 | K37: =IF('01 Aluminium'!$C$39="","",'01 Aluminium'!L39) -> 112.59 | L37: =IF('01 Aluminium'!$C$39="","",'01 Aluminium'!M39) -> Indicative | M37: =IF(D37="","",IF(AND(OR(Search!$C$6="All Categories",A37=Search!$C$6),OR(Search!$P$5="",ISNUMBER(SEARCH(" "&Search!$P$5,N37))),OR(Search!$P$6="",ISNUMBER(SEARCH(" "&Search!$P$6,N37))),OR(Search!$P$7="",ISNUMBER(SEARCH(" "&Search!$P$7,N37))),OR(Search!$P$8="",ISNUMBER(SEARCH(" "&Search!$P$8,N37))),OR(Search!$P$9="",ISNUMBER(SEARCH(" "&Search!$P$9,N37))),OR(Search!$P$10="",ISNUMBER(SEARCH(" "&Search!$P$10,N37)))),ROW(),"")) | N37: =IF(D37="",""," "&SUBSTITUTE(SUBSTITUTE(SUBSTITUTE(SUBSTITUTE(SUBSTITUTE(SUBSTITUTE(SUBSTITUTE(B37&" "&C37&" "&D37&" "&E37&" "&F37&" "&G37&" "&H37&" "&'01 Aluminium'!R39,"("," "),")"," "),"/"," "),"-"," "),","," "),";"," "),":"," ")&" ") -> AL 035 Curtain Wall System Curtain wall mullion 180 mm deep Stick system approx. 4.60 kg m Powder coated Gulf Extrusions Equiv. lm 180mm pc
A38: =IF('01 Aluminium'!$C$40="","","Aluminium Profiles & Systems") -> Aluminium Profiles & Systems | B38: =IF('01 Aluminium'!$C$40="","",'01 Aluminium'!A40) -> AL-036 | C38: =IF('01 Aluminium'!$C$40="","",'01 Aluminium'!B40) -> Curtain Wall System | D38: =IF('01 Aluminium'!$C$40="","",'01 Aluminium'!C40) -> Curtain wall mullion - 200 mm deep | E38: =IF('01 Aluminium'!$C$40="","",'01 Aluminium'!D40) -> Stick system (approx. 5.40 kg/m) | F38: =IF('01 Aluminium'!$C$40="","",'01 Aluminium'!E40) -> Powder coated | G38: =IF('01 Aluminium'!$C$40="","",'01 Aluminium'!F40) -> Gulf Extrusions / Equiv. | H38: =IF('01 Aluminium'!$C$40="","",'01 Aluminium'!G40) -> lm | I38: =IF('01 Aluminium'!$C$40="","",'01 Aluminium'!J40) -> 104.9 | J38: =IF('01 Aluminium'!$C$40="","",'01 Aluminium'!K40) -> 125.88 | K38: =IF('01 Aluminium'!$C$40="","",'01 Aluminium'!L40) -> 132.17 | L38: =IF('01 Aluminium'!$C$40="","",'01 Aluminium'!M40) -> Indicative | M38: =IF(D38="","",IF(AND(OR(Search!$C$6="All Categories",A38=Search!$C$6),OR(Search!$P$5="",ISNUMBER(SEARCH(" "&Search!$P$5,N38))),OR(Search!$P$6="",ISNUMBER(SEARCH(" "&Search!$P$6,N38))),OR(Search!$P$7="",ISNUMBER(SEARCH(" "&Search!$P$7,N38))),OR(Search!$P$8="",ISNUMBER(SEARCH(" "&Search!$P$8,N38))),OR(Search!$P$9="",ISNUMBER(SEARCH(" "&Search!$P$9,N38))),OR(Search!$P$10="",ISNUMBER(SEARCH(" "&Search!$P$10,N38)))),ROW(),"")) | N38: =IF(D38="",""," "&SUBSTITUTE(SUBSTITUTE(SUBSTITUTE(SUBSTITUTE(SUBSTITUTE(SUBSTITUTE(SUBSTITUTE(B38&" "&C38&" "&D38&" "&E38&" "&F38&" "&G38&" "&H38&" "&'01 Aluminium'!R40,"("," "),")"," "),"/"," "),"-"," "),","," "),";"," "),":"," ")&" ") -> AL 036 Curtain Wall System Curtain wall mullion 200 mm deep Stick system approx. 5.40 kg m Powder coated Gulf Extrusions Equiv. lm 200mm pc
A39: =IF('01 Aluminium'!$C$41="","","Aluminium Profiles & Systems") -> Aluminium Profiles & Systems | B39: =IF('01 Aluminium'!$C$41="","",'01 Aluminium'!A41) -> AL-037 | C39: =IF('01 Aluminium'!$C$41="","",'01 Aluminium'!B41) -> Curtain Wall System | D39: =IF('01 Aluminium'!$C$41="","",'01 Aluminium'!C41) -> Curtain wall transom - 120 mm | E39: =IF('01 Aluminium'!$C$41="","",'01 Aluminium'!D41) -> Approx. 2.40 kg/m | F39: =IF('01 Aluminium'!$C$41="","",'01 Aluminium'!E41) -> Powder coated | G39: =IF('01 Aluminium'!$C$41="","",'01 Aluminium'!F41) -> Gulf Extrusions / Equiv. | H39: =IF('01 Aluminium'!$C$41="","",'01 Aluminium'!G41) -> lm | I39: =IF('01 Aluminium'!$C$41="","",'01 Aluminium'!J41) -> 46.62 | J39: =IF('01 Aluminium'!$C$41="","",'01 Aluminium'!K41) -> 55.94 | K39: =IF('01 Aluminium'!$C$41="","",'01 Aluminium'!L41) -> 58.74 | L39: =IF('01 Aluminium'!$C$41="","",'01 Aluminium'!M41) -> Indicative | M39: =IF(D39="","",IF(AND(OR(Search!$C$6="All Categories",A39=Search!$C$6),OR(Search!$P$5="",ISNUMBER(SEARCH(" "&Search!$P$5,N39))),OR(Search!$P$6="",ISNUMBER(SEARCH(" "&Search!$P$6,N39))),OR(Search!$P$7="",ISNUMBER(SEARCH(" "&Search!$P$7,N39))),OR(Search!$P$8="",ISNUMBER(SEARCH(" "&Search!$P$8,N39))),OR(Search!$P$9="",ISNUMBER(SEARCH(" "&Search!$P$9,N39))),OR(Search!$P$10="",ISNUMBER(SEARCH(" "&Search!$P$10,N39)))),ROW(),"")) | N39: =IF(D39="",""," "&SUBSTITUTE(SUBSTITUTE(SUBSTITUTE(SUBSTITUTE(SUBSTITUTE(SUBSTITUTE(SUBSTITUTE(B39&" "&C39&" "&D39&" "&E39&" "&F39&" "&G39&" "&H39&" "&'01 Aluminium'!R41,"("," "),")"," "),"/"," "),"-"," "),","," "),";"," "),":"," ")&" ") -> AL 037 Curtain Wall System Curtain wall transom 120 mm Approx. 2.40 kg m Powder coated Gulf Extrusions Equiv. lm 120mm pc
A40: =IF('01 Aluminium'!$C$42="","","Aluminium Profiles & Systems") -> Aluminium Profiles & Systems | B40: =IF('01 Aluminium'!$C$42="","",'01 Aluminium'!A42) -> AL-038 | C40: =IF('01 Aluminium'!$C$42="","",'01 Aluminium'!B42) -> Curtain Wall System | D40: =IF('01 Aluminium'!$C$42="","",'01 Aluminium'!C42) -> Pressure plate | E40: =IF('01 Aluminium'!$C$42="","",'01 Aluminium'!D42) -> Approx. 0.55 kg/m | F40: =IF('01 Aluminium'!$C$42="","",'01 Aluminium'!E42) -> Mill finish | G40: =IF('01 Aluminium'!$C$42="","",'01 Aluminium'!F42) -> Gulf Extrusions / Equiv. | H40: =IF('01 Aluminium'!$C$42="","",'01 Aluminium'!G42) -> lm | I40: =IF('01 Aluminium'!$C$42="","",'01 Aluminium'!J42) -> 8.96 | J40: =IF('01 Aluminium'!$C$42="","",'01 Aluminium'!K42) -> 10.75 | K40: =IF('01 Aluminium'!$C$42="","",'01 Aluminium'!L42) -> 11.29 | L40: =IF('01 Aluminium'!$C$42="","",'01 Aluminium'!M42) -> Indicative | M40: =IF(D40="","",IF(AND(OR(Search!$C$6="All Categories",A40=Search!$C$6),OR(Search!$P$5="",ISNUMBER(SEARCH(" "&Search!$P$5,N40))),OR(Search!$P$6="",ISNUMBER(SEARCH(" "&Search!$P$6,N40))),OR(Search!$P$7="",ISNUMBER(SEARCH(" "&Search!$P$7,N40))),OR(Search!$P$8="",ISNUMBER(SEARCH(" "&Search!$P$8,N40))),OR(Search!$P$9="",ISNUMBER(SEARCH(" "&Search!$P$9,N40))),OR(Search!$P$10="",ISNUMBER(SEARCH(" "&Search!$P$10,N40)))),ROW(),"")) | N40: =IF(D40="",""," "&SUBSTITUTE(SUBSTITUTE(SUBSTITUTE(SUBSTITUTE(SUBSTITUTE(SUBSTITUTE(SUBSTITUTE(B40&" "&C40&" "&D40&" "&E40&" "&F40&" "&G40&" "&H40&" "&'01 Aluminium'!R42,"("," "),")"," "),"/"," "),"-"," "),","," "),";"," "),":"," ")&" ") -> AL 038 Curtain Wall System Pressure plate Approx. 0.55 kg m Mill finish Gulf Extrusions Equiv. lm
A41: =IF('01 Aluminium'!$C$43="","","Aluminium Profiles & Systems") -> Aluminium Profiles & Systems | B41: =IF('01 Aluminium'!$C$43="","",'01 Aluminium'!A43) -> AL-039 | C41: =IF('01 Aluminium'!$C$43="","",'01 Aluminium'!B43) -> Curtain Wall System | D41: =IF('01 Aluminium'!$C$43="","",'01 Aluminium'!C43) -> Snap-on cover cap | E41: =IF('01 Aluminium'!$C$43="","",'01 Aluminium'!D43) -> Approx. 0.45 kg/m | F41: =IF('01 Aluminium'!$C$43="","",'01 Aluminium'!E43) -> Powder coated / PVDF | G41: =IF('01 Aluminium'!$C$43="","",'01 Aluminium'!F43) -> Gulf Extrusions / Equiv. | H41: =IF('01 Aluminium'!$C$43="","",'01 Aluminium'!G43) -> lm | I41: =IF('01 Aluminium'!$C$43="","",'01 Aluminium'!J43) -> 8.75 | J41: =IF('01 Aluminium'!$C$43="","",'01 Aluminium'!K43) -> 10.5 | K41: =IF('01 Aluminium'!$C$43="","",'01 Aluminium'!L43) -> 11.03 | L41: =IF('01 Aluminium'!$C$43="","",'01 Aluminium'!M43) -> Indicative | M41: =IF(D41="","",IF(AND(OR(Search!$C$6="All Categories",A41=Search!$C$6),OR(Search!$P$5="",ISNUMBER(SEARCH(" "&Search!$P$5,N41))),OR(Search!$P$6="",ISNUMBER(SEARCH(" "&Search!$P$6,N41))),OR(Search!$P$7="",ISNUMBER(SEARCH(" "&Search!$P$7,N41))),OR(Search!$P$8="",ISNUMBER(SEARCH(" "&Search!$P$8,N41))),OR(Search!$P$9="",ISNUMBER(SEARCH(" "&Search!$P$9,N41))),OR(Search!$P$10="",ISNUMBER(SEARCH(" "&Search!$P$10,N41)))),ROW(),"")) | N41: =IF(D41="",""," "&SUBSTITUTE(SUBSTITUTE(SUBSTITUTE(SUBSTITUTE(SUBSTITUTE(SUBSTITUTE(SUBSTITUTE(B41&" "&C41&" "&D41&" "&E41&" "&F41&" "&G41&" "&H41&" "&'01 Aluminium'!R43,"("," "),")"," "),"/"," "),"-"," "),","," "),";"," "),":"," ")&" ") -> AL 039 Curtain Wall System Snap on cover cap Approx. 0.45 kg m Powder coated PVDF Gulf Extrusions Equiv. lm pc
A42: =IF('01 Aluminium'!$C$44="","","Aluminium Profiles & Systems") -> Aluminium Profiles & Systems | B42: =IF('01 Aluminium'!$C$44="","",'01 Aluminium'!A44) -> AL-040 | C42: =IF('01 Aluminium'!$C$44="","",'01 Aluminium'!B44) -> Curtain Wall System | D42: =IF('01 Aluminium'!$C$44="","",'01 Aluminium'!C44) -> Unitized frame profile (male/female) | E42: =IF('01 Aluminium'!$C$44="","",'01 Aluminium'!D44) -> Approx. 4.80 kg/m | F42: =IF('01 Aluminium'!$C$44="","",'01 Aluminium'!E44) -> PVDF | G42: =IF('01 Aluminium'!$C$44="","",'01 Aluminium'!F44) -> Gulf Extrusions / Equiv. | H42: =IF('01 Aluminium'!$C$44="","",'01 Aluminium'!G44) -> lm | I42: =IF('01 Aluminium'!$C$44="","",'01 Aluminium'!J44) -> 120.96 | J42: =IF('01 Aluminium'!$C$44="","",'01 Aluminium'!K44) -> 145.15 | K42: =IF('01 Aluminium'!$C$44="","",'01 Aluminium'!L44) -> 152.41 | L42: =IF('01 Aluminium'!$C$44="","",'01 Aluminium'!M44) -> Indicative | M42: =IF(D42="","",IF(AND(OR(Search!$C$6="All Categories",A42=Search!$C$6),OR(Search!$P$5="",ISNUMBER(SEARCH(" "&Search!$P$5,N42))),OR(Search!$P$6="",ISNUMBER(SEARCH(" "&Search!$P$6,N42))),OR(Search!$P$7="",ISNUMBER(SEARCH(" "&Search!$P$7,N42))),OR(Search!$P$8="",ISNUMBER(SEARCH(" "&Search!$P$8,N42))),OR(Search!$P$9="",ISNUMBER(SEARCH(" "&Search!$P$9,N42))),OR(Search!$P$10="",ISNUMBER(SEARCH(" "&Search!$P$10,N42)))),ROW(),"")) | N42: =IF(D42="",""," "&SUBSTITUTE(SUBSTITUTE(SUBSTITUTE(SUBSTITUTE(SUBSTITUTE(SUBSTITUTE(SUBSTITUTE(B42&" "&C42&" "&D42&" "&E42&" "&F42&" "&G42&" "&H42&" "&'01 Aluminium'!R44,"("," "),")"," "),"/"," "),"-"," "),","," "),";"," "),":"," ")&" ") -> AL 040 Curtain Wall System Unitized frame profile male female Approx. 4.80 kg m PVDF Gulf Extrusions Equiv. lm
A43: =IF('01 Aluminium'!$C$45="","","Aluminium Profiles & Systems") -> Aluminium Profiles & Systems | B43: =IF('01 Aluminium'!$C$45="","",'01 Aluminium'!A45) -> AL-041 | C43: =IF('01 Aluminium'!$C$45="","",'01 Aluminium'!B45) -> Curtain Wall System | D43: =IF('01 Aluminium'!$C$45="","",'01 Aluminium'!C45) -> Structural glazing (SSG) carrier frame | E43: =IF('01 Aluminium'!$C$45="","",'01 Aluminium'!D45) -> Approx. 0.85 kg/m | F43: =IF('01 Aluminium'!$C$45="","",'01 Aluminium'!E45) -> Mill finish | G43: =IF('01 Aluminium'!$C$45="","",'01 Aluminium'!F45) -> Gulf Extrusions / Equiv. | H43: =IF('01 Aluminium'!$C$45="","",'01 Aluminium'!G45) -> lm | I43: =IF('01 Aluminium'!$C$45="","",'01 Aluminium'!J45) -> 13.84 | J43: =IF('01 Aluminium'!$C$45="","",'01 Aluminium'!K45) -> 16.61 | K43: =IF('01 Aluminium'!$C$45="","",'01 Aluminium'!L45) -> 17.44 | L43: =IF('01 Aluminium'!$C$45="","",'01 Aluminium'!M45) -> Indicative | M43: =IF(D43="","",IF(AND(OR(Search!$C$6="All Categories",A43=Search!$C$6),OR(Search!$P$5="",ISNUMBER(SEARCH(" "&Search!$P$5,N43))),OR(Search!$P$6="",ISNUMBER(SEARCH(" "&Search!$P$6,N43))),OR(Search!$P$7="",ISNUMBER(SEARCH(" "&Search!$P$7,N43))),OR(Search!$P$8="",ISNUMBER(SEARCH(" "&Search!$P$8,N43))),OR(Search!$P$9="",ISNUMBER(SEARCH(" "&Search!$P$9,N43))),OR(Search!$P$10="",ISNUMBER(SEARCH(" "&Search!$P$10,N43)))),ROW(),"")) | N43: =IF(D43="",""," "&SUBSTITUTE(SUBSTITUTE(SUBSTITUTE(SUBSTITUTE(SUBSTITUTE(SUBSTITUTE(SUBSTITUTE(B43&" "&C43&" "&D43&" "&E43&" "&F43&" "&G43&" "&H43&" "&'01 Aluminium'!R45,"("," "),")"," "),"/"," "),"-"," "),","," "),";"," "),":"," ")&" ") -> AL 041 Curtain Wall System Structural glazing SSG carrier frame Approx. 0.85 kg m Mill finish Gulf Extrusions Equiv. lm
A44: =IF('01 Aluminium'!$C$46="","","Aluminium Profiles & Systems") -> Aluminium Profiles & Systems | B44: =IF('01 Aluminium'!$C$46="","",'01 Aluminium'!A46) -> AL-042 | C44: =IF('01 Aluminium'!$C$46="","",'01 Aluminium'!B46) -> Pergola / Louver / Skylight | D44: =IF('01 Aluminium'!$C$46="","",'01 Aluminium'!C46) -> Pergola main beam | E44: =IF('01 Aluminium'!$C$46="","",'01 Aluminium'!D46) -> 150 x 50 x 3 mm (3.14 kg/m) | F44: =IF('01 Aluminium'!$C$46="","",'01 Aluminium'!E46) -> Powder coated / wood-grain | G44: =IF('01 Aluminium'!$C$46="","",'01 Aluminium'!F46) -> Local | H44: =IF('01 Aluminium'!$C$46="","",'01 Aluminium'!G46) -> lm | I44: =IF('01 Aluminium'!$C$46="","",'01 Aluminium'!J46) -> 60.99 | J44: =IF('01 Aluminium'!$C$46="","",'01 Aluminium'!K46) -> 73.19 | K44: =IF('01 Aluminium'!$C$46="","",'01 Aluminium'!L46) -> 76.85 | L44: =IF('01 Aluminium'!$C$46="","",'01 Aluminium'!M46) -> Indicative | M44: =IF(D44="","",IF(AND(OR(Search!$C$6="All Categories",A44=Search!$C$6),OR(Search!$P$5="",ISNUMBER(SEARCH(" "&Search!$P$5,N44))),OR(Search!$P$6="",ISNUMBER(SEARCH(" "&Search!$P$6,N44))),OR(Search!$P$7="",ISNUMBER(SEARCH(" "&Search!$P$7,N44))),OR(Search!$P$8="",ISNUMBER(SEARCH(" "&Search!$P$8,N44))),OR(Search!$P$9="",ISNUMBER(SEARCH(" "&Search!$P$9,N44))),OR(Search!$P$10="",ISNUMBER(SEARCH(" "&Search!$P$10,N44)))),ROW(),"")) | N44: =IF(D44="",""," "&SUBSTITUTE(SUBSTITUTE(SUBSTITUTE(SUBSTITUTE(SUBSTITUTE(SUBSTITUTE(SUBSTITUTE(B44&" "&C44&" "&D44&" "&E44&" "&F44&" "&G44&" "&H44&" "&'01 Aluminium'!R46,"("," "),")"," "),"/"," "),"-"," "),","," "),";"," "),":"," ")&" ") -> AL 042 Pergola Louver Skylight Pergola main beam 150 x 50 x 3 mm 3.14 kg m Powder coated wood grain Local lm 150x50 150x50x3 3mm pc louvre shade
A45: =IF('01 Aluminium'!$C$47="","","Aluminium Profiles & Systems") -> Aluminium Profiles & Systems | B45: =IF('01 Aluminium'!$C$47="","",'01 Aluminium'!A47) -> AL-043 | C45: =IF('01 Aluminium'!$C$47="","",'01 Aluminium'!B47) -> Pergola / Louver / Skylight | D45: =IF('01 Aluminium'!$C$47="","",'01 Aluminium'!C47) -> Pergola rafter / slat | E45: =IF('01 Aluminium'!$C$47="","",'01 Aluminium'!D47) -> 100 x 50 x 2.5 mm (1.96 kg/m) | F45: =IF('01 Aluminium'!$C$47="","",'01 Aluminium'!E47) -> Powder coated / wood-grain | G45: =IF('01 Aluminium'!$C$47="","",'01 Aluminium'!F47) -> Local | H45: =IF('01 Aluminium'!$C$47="","",'01 Aluminium'!G47) -> lm | I45: =IF('01 Aluminium'!$C$47="","",'01 Aluminium'!J47) -> 38.07 | J45: =IF('01 Aluminium'!$C$47="","",'01 Aluminium'!K47) -> 45.68 | K45: =IF('01 Aluminium'!$C$47="","",'01 Aluminium'!L47) -> 47.96 | L45: =IF('01 Aluminium'!$C$47="","",'01 Aluminium'!M47) -> Indicative | M45: =IF(D45="","",IF(AND(OR(Search!$C$6="All Categories",A45=Search!$C$6),OR(Search!$P$5="",ISNUMBER(SEARCH(" "&Search!$P$5,N45))),OR(Search!$P$6="",ISNUMBER(SEARCH(" "&Search!$P$6,N45))),OR(Search!$P$7="",ISNUMBER(SEARCH(" "&Search!$P$7,N45))),OR(Search!$P$8="",ISNUMBER(SEARCH(" "&Search!$P$8,N45))),OR(Search!$P$9="",ISNUMBER(SEARCH(" "&Search!$P$9,N45))),OR(Search!$P$10="",ISNUMBER(SEARCH(" "&Search!$P$10,N45)))),ROW(),"")) | N45: =IF(D45="",""," "&SUBSTITUTE(SUBSTITUTE(SUBSTITUTE(SUBSTITUTE(SUBSTITUTE(SUBSTITUTE(SUBSTITUTE(B45&" "&C45&" "&D45&" "&E45&" "&F45&" "&G45&" "&H45&" "&'01 Aluminium'!R47,"("," "),")"," "),"/"," "),"-"," "),","," "),";"," "),":"," ")&" ") -> AL 043 Pergola Louver Skylight Pergola rafter slat 100 x 50 x 2.5 mm 1.96 kg m Powder coated wood grain Local lm 100x50 100x50x2.5 2.5mm pc louvre shade
A46: =IF('01 Aluminium'!$C$48="","","Aluminium Profiles & Systems") -> Aluminium Profiles & Systems | B46: =IF('01 Aluminium'!$C$48="","",'01 Aluminium'!A48) -> AL-044 | C46: =IF('01 Aluminium'!$C$48="","",'01 Aluminium'!B48) -> Pergola / Louver / Skylight | D46: =IF('01 Aluminium'!$C$48="","",'01 Aluminium'!C48) -> Bioclimatic pergola louver blade | E46: =IF('01 Aluminium'!$C$48="","",'01 Aluminium'!D48) -> Approx. 2.60 kg/m | F46: =IF('01 Aluminium'!$C$48="","",'01 Aluminium'!E48) -> Powder coated | G46: =IF('01 Aluminium'!$C$48="","",'01 Aluminium'!F48) -> Local / Imported | H46: =IF('01 Aluminium'!$C$48="","",'01 Aluminium'!G48) -> lm | I46: =IF('01 Aluminium'!$C$48="","",'01 Aluminium'!J48) -> 50.51 | J46: =IF('01 Aluminium'!$C$48="","",'01 Aluminium'!K48) -> 60.61 | K46: =IF('01 Aluminium'!$C$48="","",'01 Aluminium'!L48) -> 63.64 | L46: =IF('01 Aluminium'!$C$48="","",'01 Aluminium'!M48) -> Indicative | M46: =IF(D46="","",IF(AND(OR(Search!$C$6="All Categories",A46=Search!$C$6),OR(Search!$P$5="",ISNUMBER(SEARCH(" "&Search!$P$5,N46))),OR(Search!$P$6="",ISNUMBER(SEARCH(" "&Search!$P$6,N46))),OR(Search!$P$7="",ISNUMBER(SEARCH(" "&Search!$P$7,N46))),OR(Search!$P$8="",ISNUMBER(SEARCH(" "&Search!$P$8,N46))),OR(Search!$P$9="",ISNUMBER(SEARCH(" "&Search!$P$9,N46))),OR(Search!$P$10="",ISNUMBER(SEARCH(" "&Search!$P$10,N46)))),ROW(),"")) | N46: =IF(D46="",""," "&SUBSTITUTE(SUBSTITUTE(SUBSTITUTE(SUBSTITUTE(SUBSTITUTE(SUBSTITUTE(SUBSTITUTE(B46&" "&C46&" "&D46&" "&E46&" "&F46&" "&G46&" "&H46&" "&'01 Aluminium'!R48,"("," "),")"," "),"/"," "),"-"," "),","," "),";"," "),":"," ")&" ") -> AL 044 Pergola Louver Skylight Bioclimatic pergola louver blade Approx. 2.60 kg m Powder coated Local Imported lm pc louvre shade
A47: =IF('01 Aluminium'!$C$49="","","Aluminium Profiles & Systems") -> Aluminium Profiles & Systems | B47: =IF('01 Aluminium'!$C$49="","",'01 Aluminium'!A49) -> AL-045 | C47: =IF('01 Aluminium'!$C$49="","",'01 Aluminium'!B49) -> Pergola / Louver / Skylight | D47: =IF('01 Aluminium'!$C$49="","",'01 Aluminium'!C49) -> Louver blade - Z type 100 mm | E47: =IF('01 Aluminium'!$C$49="","",'01 Aluminium'!D49) -> Approx. 0.85 kg/m | F47: =IF('01 Aluminium'!$C$49="","",'01 Aluminium'!E49) -> Powder coated | G47: =IF('01 Aluminium'!$C$49="","",'01 Aluminium'!F49) -> Local | H47: =IF('01 Aluminium'!$C$49="","",'01 Aluminium'!G49) -> lm | I47: =IF('01 Aluminium'!$C$49="","",'01 Aluminium'!J49) -> 16.52 | J47: =IF('01 Aluminium'!$C$49="","",'01 Aluminium'!K49) -> 19.82 | K47: =IF('01 Aluminium'!$C$49="","",'01 Aluminium'!L49) -> 20.81 | L47: =IF('01 Aluminium'!$C$49="","",'01 Aluminium'!M49) -> Indicative | M47: =IF(D47="","",IF(AND(OR(Search!$C$6="All Categories",A47=Search!$C$6),OR(Search!$P$5="",ISNUMBER(SEARCH(" "&Search!$P$5,N47))),OR(Search!$P$6="",ISNUMBER(SEARCH(" "&Search!$P$6,N47))),OR(Search!$P$7="",ISNUMBER(SEARCH(" "&Search!$P$7,N47))),OR(Search!$P$8="",ISNUMBER(SEARCH(" "&Search!$P$8,N47))),OR(Search!$P$9="",ISNUMBER(SEARCH(" "&Search!$P$9,N47))),OR(Search!$P$10="",ISNUMBER(SEARCH(" "&Search!$P$10,N47)))),ROW(),"")) | N47: =IF(D47="",""," "&SUBSTITUTE(SUBSTITUTE(SUBSTITUTE(SUBSTITUTE(SUBSTITUTE(SUBSTITUTE(SUBSTITUTE(B47&" "&C47&" "&D47&" "&E47&" "&F47&" "&G47&" "&H47&" "&'01 Aluminium'!R49,"("," "),")"," "),"/"," "),"-"," "),","," "),";"," "),":"," ")&" ") -> AL 045 Pergola Louver Skylight Louver blade Z type 100 mm Approx. 0.85 kg m Powder coated Local lm 100mm pc louvre shade
A48: =IF('01 Aluminium'!$C$50="","","Aluminium Profiles & Systems") -> Aluminium Profiles & Systems | B48: =IF('01 Aluminium'!$C$50="","",'01 Aluminium'!A50) -> AL-046 | C48: =IF('01 Aluminium'!$C$50="","",'01 Aluminium'!B50) -> Pergola / Louver / Skylight | D48: =IF('01 Aluminium'!$C$50="","",'01 Aluminium'!C50) -> Louver blade - aerofoil 200 mm | E48: =IF('01 Aluminium'!$C$50="","",'01 Aluminium'!D50) -> Approx. 2.30 kg/m | F48: =IF('01 Aluminium'!$C$50="","",'01 Aluminium'!E50) -> Powder coated | G48: =IF('01 Aluminium'!$C$50="","",'01 Aluminium'!F50) -> Local | H48: =IF('01 Aluminium'!$C$50="","",'01 Aluminium'!G50) -> lm | I48: =IF('01 Aluminium'!$C$50="","",'01 Aluminium'!J50) -> 44.68 | J48: =IF('01 Aluminium'!$C$50="","",'01 Aluminium'!K50) -> 53.62 | K48: =IF('01 Aluminium'!$C$50="","",'01 Aluminium'!L50) -> 56.3 | L48: =IF('01 Aluminium'!$C$50="","",'01 Aluminium'!M50) -> Indicative | M48: =IF(D48="","",IF(AND(OR(Search!$C$6="All Categories",A48=Search!$C$6),OR(Search!$P$5="",ISNUMBER(SEARCH(" "&Search!$P$5,N48))),OR(Search!$P$6="",ISNUMBER(SEARCH(" "&Search!$P$6,N48))),OR(Search!$P$7="",ISNUMBER(SEARCH(" "&Search!$P$7,N48))),OR(Search!$P$8="",ISNUMBER(SEARCH(" "&Search!$P$8,N48))),OR(Search!$P$9="",ISNUMBER(SEARCH(" "&Search!$P$9,N48))),OR(Search!$P$10="",ISNUMBER(SEARCH(" "&Search!$P$10,N48)))),ROW(),"")) | N48: =IF(D48="",""," "&SUBSTITUTE(SUBSTITUTE(SUBSTITUTE(SUBSTITUTE(SUBSTITUTE(SUBSTITUTE(SUBSTITUTE(B48&" "&C48&" "&D48&" "&E48&" "&F48&" "&G48&" "&H48&" "&'01 Aluminium'!R50,"("," "),")"," "),"/"," "),"-"," "),","," "),";"," "),":"," ")&" ") -> AL 046 Pergola Louver Skylight Louver blade aerofoil 200 mm Approx. 2.30 kg m Powder coated Local lm 200mm pc louvre shade
A49: =IF('01 Aluminium'!$C$51="","","Aluminium Profiles & Systems") -> Aluminium Profiles & Systems | B49: =IF('01 Aluminium'!$C$51="","",'01 Aluminium'!A51) -> AL-047 | C49: =IF('01 Aluminium'!$C$51="","",'01 Aluminium'!B51) -> Pergola / Louver / Skylight | D49: =IF('01 Aluminium'!$C$51="","",'01 Aluminium'!C51) -> Skylight rafter profile | E49: =IF('01 Aluminium'!$C$51="","",'01 Aluminium'!D51) -> Approx. 3.20 kg/m | F49: =IF('01 Aluminium'!$C$51="","",'01 Aluminium'!E51) -> Powder coated | G49: =IF('01 Aluminium'!$C$51="","",'01 Aluminium'!F51) -> Gulf Extrusions / Equiv. | H49: =IF('01 Aluminium'!$C$51="","",'01 Aluminium'!G51) -> lm | I49: =IF('01 Aluminium'!$C$51="","",'01 Aluminium'!J51) -> 62.16 | J49: =IF('01 Aluminium'!$C$51="","",'01 Aluminium'!K51) -> 74.59 | K49: =IF('01 Aluminium'!$C$51="","",'01 Aluminium'!L51) -> 78.32 | L49: =IF('01 Aluminium'!$C$51="","",'01 Aluminium'!M51) -> Indicative | M49: =IF(D49="","",IF(AND(OR(Search!$C$6="All Categories",A49=Search!$C$6),OR(Search!$P$5="",ISNUMBER(SEARCH(" "&Search!$P$5,N49))),OR(Search!$P$6="",ISNUMBER(SEARCH(" "&Search!$P$6,N49))),OR(Search!$P$7="",ISNUMBER(SEARCH(" "&Search!$P$7,N49))),OR(Search!$P$8="",ISNUMBER(SEARCH(" "&Search!$P$8,N49))),OR(Search!$P$9="",ISNUMBER(SEARCH(" "&Search!$P$9,N49))),OR(Search!$P$10="",ISNUMBER(SEARCH(" "&Search!$P$10,N49)))),ROW(),"")) | N49: =IF(D49="",""," "&SUBSTITUTE(SUBSTITUTE(SUBSTITUTE(SUBSTITUTE(SUBSTITUTE(SUBSTITUTE(SUBSTITUTE(B49&" "&C49&" "&D49&" "&E49&" "&F49&" "&G49&" "&H49&" "&'01 Aluminium'!R51,"("," "),")"," "),"/"," "),"-"," "),","," "),";"," "),":"," ")&" ") -> AL 047 Pergola Louver Skylight Skylight rafter profile Approx. 3.20 kg m Powder coated Gulf Extrusions Equiv. lm pc louvre shade
A50: =IF('01 Aluminium'!$C$52="","","Aluminium Profiles & Systems") -> Aluminium Profiles & Systems | B50: =IF('01 Aluminium'!$C$52="","",'01 Aluminium'!A52) -> AL-048 | C50: =IF('01 Aluminium'!$C$52="","",'01 Aluminium'!B52) -> Balustrade / Handrail | D50: =IF('01 Aluminium'!$C$52="","",'01 Aluminium'!C52) -> Glass balustrade base shoe profile | E50: =IF('01 Aluminium'!$C$52="","",'01 Aluminium'!D52) -> Heavy duty, for 12-21.52 mm glass (6.8 kg/m) | F50: =IF('01 Aluminium'!$C$52="","",'01 Aluminium'!E52) -> Anodized / PC | G50: =IF('01 Aluminium'!$C$52="","",'01 Aluminium'!F52) -> Local / Imported | H50: =IF('01 Aluminium'!$C$52="","",'01 Aluminium'!G52) -> lm | I50: =IF('01 Aluminium'!$C$52="","",'01 Aluminium'!J52) -> 132.09 | J50: =IF('01 Aluminium'!$C$52="","",'01 Aluminium'!K52) -> 158.51 | K50: =IF('01 Aluminium'!$C$52="","",'01 Aluminium'!L52) -> 166.44 | L50: =IF('01 Aluminium'!$C$52="","",'01 Aluminium'!M52) -> Indicative | M50: =IF(D50="","",IF(AND(OR(Search!$C$6="All Categories",A50=Search!$C$6),OR(Search!$P$5="",ISNUMBER(SEARCH(" "&Search!$P$5,N50))),OR(Search!$P$6="",ISNUMBER(SEARCH(" "&Search!$P$6,N50))),OR(Search!$P$7="",ISNUMBER(SEARCH(" "&Search!$P$7,N50))),OR(Search!$P$8="",ISNUMBER(SEARCH(" "&Search!$P$8,N50))),OR(Search!$P$9="",ISNUMBER(SEARCH(" "&Search!$P$9,N50))),OR(Search!$P$10="",ISNUMBER(SEARCH(" "&Search!$P$10,N50)))),ROW(),"")) | N50: =IF(D50="",""," "&SUBSTITUTE(SUBSTITUTE(SUBSTITUTE(SUBSTITUTE(SUBSTITUTE(SUBSTITUTE(SUBSTITUTE(B50&" "&C50&" "&D50&" "&E50&" "&F50&" "&G50&" "&H50&" "&'01 Aluminium'!R52,"("," "),")"," "),"/"," "),"-"," "),","," "),";"," "),":"," ")&" ") -> AL 048 Balustrade Handrail Glass balustrade base shoe profile Heavy duty for 12 21.52 mm glass 6.8 kg m Anodized PC Local Imported lm 21.52mm railing handrail balustrade stainless steel
A51: =IF('01 Aluminium'!$C$53="","","Aluminium Profiles & Systems") -> Aluminium Profiles & Systems | B51: =IF('01 Aluminium'!$C$53="","",'01 Aluminium'!A53) -> AL-049 | C51: =IF('01 Aluminium'!$C$53="","",'01 Aluminium'!B53) -> Balustrade / Handrail | D51: =IF('01 Aluminium'!$C$53="","",'01 Aluminium'!C53) -> Aluminium handrail - oval / round | E51: =IF('01 Aluminium'!$C$53="","",'01 Aluminium'!D53) -> Approx. 0.90 kg/m | F51: =IF('01 Aluminium'!$C$53="","",'01 Aluminium'!E53) -> Powder coated | G51: =IF('01 Aluminium'!$C$53="","",'01 Aluminium'!F53) -> Local | H51: =IF('01 Aluminium'!$C$53="","",'01 Aluminium'!G53) -> lm | I51: =IF('01 Aluminium'!$C$53="","",'01 Aluminium'!J53) -> 17.48 | J51: =IF('01 Aluminium'!$C$53="","",'01 Aluminium'!K53) -> 20.98 | K51: =IF('01 Aluminium'!$C$53="","",'01 Aluminium'!L53) -> 22.03 | L51: =IF('01 Aluminium'!$C$53="","",'01 Aluminium'!M53) -> Indicative | M51: =IF(D51="","",IF(AND(OR(Search!$C$6="All Categories",A51=Search!$C$6),OR(Search!$P$5="",ISNUMBER(SEARCH(" "&Search!$P$5,N51))),OR(Search!$P$6="",ISNUMBER(SEARCH(" "&Search!$P$6,N51))),OR(Search!$P$7="",ISNUMBER(SEARCH(" "&Search!$P$7,N51))),OR(Search!$P$8="",ISNUMBER(SEARCH(" "&Search!$P$8,N51))),OR(Search!$P$9="",ISNUMBER(SEARCH(" "&Search!$P$9,N51))),OR(Search!$P$10="",ISNUMBER(SEARCH(" "&Search!$P$10,N51)))),ROW(),"")) | N51: =IF(D51="",""," "&SUBSTITUTE(SUBSTITUTE(SUBSTITUTE(SUBSTITUTE(SUBSTITUTE(SUBSTITUTE(SUBSTITUTE(B51&" "&C51&" "&D51&" "&E51&" "&F51&" "&G51&" "&H51&" "&'01 Aluminium'!R53,"("," "),")"," "),"/"," "),"-"," "),","," "),";"," "),":"," ")&" ") -> AL 049 Balustrade Handrail Aluminium handrail oval round Approx. 0.90 kg m Powder coated Local lm aluminum alu pc railing handrail balustrade
A52: =IF('01 Aluminium'!$C$54="","","Aluminium Profiles & Systems") -> Aluminium Profiles & Systems | B52: =IF('01 Aluminium'!$C$54="","",'01 Aluminium'!A54) -> AL-050 | C52: =IF('01 Aluminium'!$C$54="","",'01 Aluminium'!B54) -> Balustrade / Handrail | D52: =IF('01 Aluminium'!$C$54="","",'01 Aluminium'!C54) -> Glass top cap (U-cap) profile | E52: =IF('01 Aluminium'!$C$54="","",'01 Aluminium'!D54) -> For 12-17.52 mm glass (0.55 kg/m) | F52: =IF('01 Aluminium'!$C$54="","",'01 Aluminium'!E54) -> Anodized / PC | G52: =IF('01 Aluminium'!$C$54="","",'01 Aluminium'!F54) -> Local | H52: =IF('01 Aluminium'!$C$54="","",'01 Aluminium'!G54) -> lm | I52: =IF('01 Aluminium'!$C$54="","",'01 Aluminium'!J54) -> 10.69 | J52: =IF('01 Aluminium'!$C$54="","",'01 Aluminium'!K54) -> 12.83 | K52: =IF('01 Aluminium'!$C$54="","",'01 Aluminium'!L54) -> 13.47 | L52: =IF('01 Aluminium'!$C$54="","",'01 Aluminium'!M54) -> Indicative | M52: =IF(D52="","",IF(AND(OR(Search!$C$6="All Categories",A52=Search!$C$6),OR(Search!$P$5="",ISNUMBER(SEARCH(" "&Search!$P$5,N52))),OR(Search!$P$6="",ISNUMBER(SEARCH(" "&Search!$P$6,N52))),OR(Search!$P$7="",ISNUMBER(SEARCH(" "&Search!$P$7,N52))),OR(Search!$P$8="",ISNUMBER(SEARCH(" "&Search!$P$8,N52))),OR(Search!$P$9="",ISNUMBER(SEARCH(" "&Search!$P$9,N52))),OR(Search!$P$10="",ISNUMBER(SEARCH(" "&Search!$P$10,N52)))),ROW(),"")) | N52: =IF(D52="",""," "&SUBSTITUTE(SUBSTITUTE(SUBSTITUTE(SUBSTITUTE(SUBSTITUTE(SUBSTITUTE(SUBSTITUTE(B52&" "&C52&" "&D52&" "&E52&" "&F52&" "&G52&" "&H52&" "&'01 Aluminium'!R54,"("," "),")"," "),"/"," "),"-"," "),","," "),";"," "),":"," ")&" ") -> AL 050 Balustrade Handrail Glass top cap U cap profile For 12 17.52 mm glass 0.55 kg m Anodized PC Local lm 17.52mm railing handrail balustrade stainless steel
A53: =IF('01 Aluminium'!$C$55="","","Aluminium Profiles & Systems") -> Aluminium Profiles & Systems | B53: =IF('01 Aluminium'!$C$55="","",'01 Aluminium'!A55) -> AL-051 | C53: =IF('01 Aluminium'!$C$55="","",'01 Aluminium'!B55) -> Sheet & Panel | D53: =IF('01 Aluminium'!$C$55="","",'01 Aluminium'!C55) -> Aluminium flat sheet | E53: =IF('01 Aluminium'!$C$55="","",'01 Aluminium'!D55) -> 2.0 mm, 1250 x 2500 | F53: =IF('01 Aluminium'!$C$55="","",'01 Aluminium'!E55) -> Mill finish | G53: =IF('01 Aluminium'!$C$55="","",'01 Aluminium'!F55) -> Local / Imported | H53: =IF('01 Aluminium'!$C$55="","",'01 Aluminium'!G55) -> m2 | I53: =IF('01 Aluminium'!$C$55="","",'01 Aluminium'!J55) -> 50.4 | J53: =IF('01 Aluminium'!$C$55="","",'01 Aluminium'!K55) -> 60.48 | K53: =IF('01 Aluminium'!$C$55="","",'01 Aluminium'!L55) -> 63.5 | L53: =IF('01 Aluminium'!$C$55="","",'01 Aluminium'!M55) -> Indicative | M53: =IF(D53="","",IF(AND(OR(Search!$C$6="All Categories",A53=Search!$C$6),OR(Search!$P$5="",ISNUMBER(SEARCH(" "&Search!$P$5,N53))),OR(Search!$P$6="",ISNUMBER(SEARCH(" "&Search!$P$6,N53))),OR(Search!$P$7="",ISNUMBER(SEARCH(" "&Search!$P$7,N53))),OR(Search!$P$8="",ISNUMBER(SEARCH(" "&Search!$P$8,N53))),OR(Search!$P$9="",ISNUMBER(SEARCH(" "&Search!$P$9,N53))),OR(Search!$P$10="",ISNUMBER(SEARCH(" "&Search!$P$10,N53)))),ROW(),"")) -> 53 | N53: =IF(D53="",""," "&SUBSTITUTE(SUBSTITUTE(SUBSTITUTE(SUBSTITUTE(SUBSTITUTE(SUBSTITUTE(SUBSTITUTE(B53&" "&C53&" "&D53&" "&E53&" "&F53&" "&G53&" "&H53&" "&'01 Aluminium'!R55,"("," "),")"," "),"/"," "),"-"," "),","," "),";"," "),":"," ")&" ") -> AL 051 Sheet & Panel Aluminium flat sheet 2.0 mm 1250 x 2500 Mill finish Local Imported m2 1250x2500 2.0mm aluminum alu
A54: =IF('01 Aluminium'!$C$56="","","Aluminium Profiles & Systems") -> Aluminium Profiles & Systems | B54: =IF('01 Aluminium'!$C$56="","",'01 Aluminium'!A56) -> AL-052 | C54: =IF('01 Aluminium'!$C$56="","",'01 Aluminium'!B56) -> Sheet & Panel | D54: =IF('01 Aluminium'!$C$56="","",'01 Aluminium'!C56) -> Aluminium flat sheet | E54: =IF('01 Aluminium'!$C$56="","",'01 Aluminium'!D56) -> 3.0 mm, 1250 x 2500 | F54: =IF('01 Aluminium'!$C$56="","",'01 Aluminium'!E56) -> Mill finish | G54: =IF('01 Aluminium'!$C$56="","",'01 Aluminium'!F56) -> Local / Imported | H54: =IF('01 Aluminium'!$C$56="","",'01 Aluminium'!G56) -> m2 | I54: =IF('01 Aluminium'!$C$56="","",'01 Aluminium'!J56) -> 73.5 | J54: =IF('01 Aluminium'!$C$56="","",'01 Aluminium'!K56) -> 88.2 | K54: =IF('01 Aluminium'!$C$56="","",'01 Aluminium'!L56) -> 92.61 | L54: =IF('01 Aluminium'!$C$56="","",'01 Aluminium'!M56) -> Indicative | M54: =IF(D54="","",IF(AND(OR(Search!$C$6="All Categories",A54=Search!$C$6),OR(Search!$P$5="",ISNUMBER(SEARCH(" "&Search!$P$5,N54))),OR(Search!$P$6="",ISNUMBER(SEARCH(" "&Search!$P$6,N54))),OR(Search!$P$7="",ISNUMBER(SEARCH(" "&Search!$P$7,N54))),OR(Search!$P$8="",ISNUMBER(SEARCH(" "&Search!$P$8,N54))),OR(Search!$P$9="",ISNUMBER(SEARCH(" "&Search!$P$9,N54))),OR(Search!$P$10="",ISNUMBER(SEARCH(" "&Search!$P$10,N54)))),ROW(),"")) -> 54 | N54: =IF(D54="",""," "&SUBSTITUTE(SUBSTITUTE(SUBSTITUTE(SUBSTITUTE(SUBSTITUTE(SUBSTITUTE(SUBSTITUTE(B54&" "&C54&" "&D54&" "&E54&" "&F54&" "&G54&" "&H54&" "&'01 Aluminium'!R56,"("," "),")"," "),"/"," "),"-"," "),","," "),";"," "),":"," ")&" ") -> AL 052 Sheet & Panel Aluminium flat sheet 3.0 mm 1250 x 2500 Mill finish Local Imported m2 1250x2500 3.0mm aluminum alu
A55: =IF('01 Aluminium'!$C$57="","","Aluminium Profiles & Systems") -> Aluminium Profiles & Systems | B55: =IF('01 Aluminium'!$C$57="","",'01 Aluminium'!A57) -> AL-053 | C55: =IF('01 Aluminium'!$C$57="","",'01 Aluminium'!B57) -> Sheet & Panel | D55: =IF('01 Aluminium'!$C$57="","",'01 Aluminium'!C57) -> Aluminium chequered plate | E55: =IF('01 Aluminium'!$C$57="","",'01 Aluminium'!D57) -> 3.0 mm tread | F55: =IF('01 Aluminium'!$C$57="","",'01 Aluminium'!E57) -> Mill finish | G55: =IF('01 Aluminium'!$C$57="","",'01 Aluminium'!F57) -> Local / Imported | H55: =IF('01 Aluminium'!$C$57="","",'01 Aluminium'!G57) -> m2 | I55: =IF('01 Aluminium'!$C$57="","",'01 Aluminium'!J57) -> 89.25 | J55: =IF('01 Aluminium'!$C$57="","",'01 Aluminium'!K57) -> 107.1 | K55: =IF('01 Aluminium'!$C$57="","",'01 Aluminium'!L57) -> 112.46 | L55: =IF('01 Aluminium'!$C$57="","",'01 Aluminium'!M57) -> Indicative | M55: =IF(D55="","",IF(AND(OR(Search!$C$6="All Categories",A55=Search!$C$6),OR(Search!$P$5="",ISNUMBER(SEARCH(" "&Search!$P$5,N55))),OR(Search!$P$6="",ISNUMBER(SEARCH(" "&Search!$P$6,N55))),OR(Search!$P$7="",ISNUMBER(SEARCH(" "&Search!$P$7,N55))),OR(Search!$P$8="",ISNUMBER(SEARCH(" "&Search!$P$8,N55))),OR(Search!$P$9="",ISNUMBER(SEARCH(" "&Search!$P$9,N55))),OR(Search!$P$10="",ISNUMBER(SEARCH(" "&Search!$P$10,N55)))),ROW(),"")) -> 55 | N55: =IF(D55="",""," "&SUBSTITUTE(SUBSTITUTE(SUBSTITUTE(SUBSTITUTE(SUBSTITUTE(SUBSTITUTE(SUBSTITUTE(B55&" "&C55&" "&D55&" "&E55&" "&F55&" "&G55&" "&H55&" "&'01 Aluminium'!R57,"("," "),")"," "),"/"," "),"-"," "),","," "),";"," "),":"," ")&" ") -> AL 053 Sheet & Panel Aluminium chequered plate 3.0 mm tread Mill finish Local Imported m2 3.0mm aluminum alu checker anti slip
A56: =IF('01 Aluminium'!$C$58="","","Aluminium Profiles & Systems") | B56: =IF('01 Aluminium'!$C$58="","",'01 Aluminium'!A58) | C56: =IF('01 Aluminium'!$C$58="","",'01 Aluminium'!B58) | D56: =IF('01 Aluminium'!$C$58="","",'01 Aluminium'!C58) | E56: =IF('01 Aluminium'!$C$58="","",'01 Aluminium'!D58) | F56: =IF('01 Aluminium'!$C$58="","",'01 Aluminium'!E58) | G56: =IF('01 Aluminium'!$C$58="","",'01 Aluminium'!F58) | H56: =IF('01 Aluminium'!$C$58="","",'01 Aluminium'!G58) | I56: =IF('01 Aluminium'!$C$58="","",'01 Aluminium'!J58) | J56: =IF('01 Aluminium'!$C$58="","",'01 Aluminium'!K58) | K56: =IF('01 Aluminium'!$C$58="","",'01 Aluminium'!L58) | L56: =IF('01 Aluminium'!$C$58="","",'01 Aluminium'!M58) | M56: =IF(D56="","",IF(AND(OR(Search!$C$6="All Categories",A56=Search!$C$6),OR(Search!$P$5="",ISNUMBER(SEARCH(" "&Search!$P$5,N56))),OR(Search!$P$6="",ISNUMBER(SEARCH(" "&Search!$P$6,N56))),OR(Search!$P$7="",ISNUMBER(SEARCH(" "&Search!$P$7,N56))),OR(Search!$P$8="",ISNUMBER(SEARCH(" "&Search!$P$8,N56))),OR(Search!$P$9="",ISNUMBER(SEARCH(" "&Search!$P$9,N56))),OR(Search!$P$10="",ISNUMBER(SEARCH(" "&Search!$P$10,N56)))),ROW(),"")) | N56: =IF(D56="",""," "&SUBSTITUTE(SUBSTITUTE(SUBSTITUTE(SUBSTITUTE(SUBSTITUTE(SUBSTITUTE(SUBSTITUTE(B56&" "&C56&" "&D56&" "&E56&" "&F56&" "&G56&" "&H56&" "&'01 Aluminium'!R58,"("," "),")"," "),"/"," "),"-"," "),","," "),";"," "),":"," ")&" ")
A57: =IF('01 Aluminium'!$C$59="","","Aluminium Profiles & Systems") | B57: =IF('01 Aluminium'!$C$59="","",'01 Aluminium'!A59) | C57: =IF('01 Aluminium'!$C$59="","",'01 Aluminium'!B59) | D57: =IF('01 Aluminium'!$C$59="","",'01 Aluminium'!C59) | E57: =IF('01 Aluminium'!$C$59="","",'01 Aluminium'!D59) | F57: =IF('01 Aluminium'!$C$59="","",'01 Aluminium'!E59) | G57: =IF('01 Aluminium'!$C$59="","",'01 Aluminium'!F59) | H57: =IF('01 Aluminium'!$C$59="","",'01 Aluminium'!G59) | I57: =IF('01 Aluminium'!$C$59="","",'01 Aluminium'!J59) | J57: =IF('01 Aluminium'!$C$59="","",'01 Aluminium'!K59) | K57: =IF('01 Aluminium'!$C$59="","",'01 Aluminium'!L59) | L57: =IF('01 Aluminium'!$C$59="","",'01 Aluminium'!M59) | M57: =IF(D57="","",IF(AND(OR(Search!$C$6="All Categories",A57=Search!$C$6),OR(Search!$P$5="",ISNUMBER(SEARCH(" "&Search!$P$5,N57))),OR(Search!$P$6="",ISNUMBER(SEARCH(" "&Search!$P$6,N57))),OR(Search!$P$7="",ISNUMBER(SEARCH(" "&Search!$P$7,N57))),OR(Search!$P$8="",ISNUMBER(SEARCH(" "&Search!$P$8,N57))),OR(Search!$P$9="",ISNUMBER(SEARCH(" "&Search!$P$9,N57))),OR(Search!$P$10="",ISNUMBER(SEARCH(" "&Search!$P$10,N57)))),ROW(),"")) | N57: =IF(D57="",""," "&SUBSTITUTE(SUBSTITUTE(SUBSTITUTE(SUBSTITUTE(SUBSTITUTE(SUBSTITUTE(SUBSTITUTE(B57&" "&C57&" "&D57&" "&E57&" "&F57&" "&G57&" "&H57&" "&'01 Aluminium'!R59,"("," "),")"," "),"/"," "),"-"," "),","," "),";"," "),":"," ")&" ")
A58: =IF('01 Aluminium'!$C$60="","","Aluminium Profiles & Systems") | B58: =IF('01 Aluminium'!$C$60="","",'01 Aluminium'!A60) | C58: =IF('01 Aluminium'!$C$60="","",'01 Aluminium'!B60) | D58: =IF('01 Aluminium'!$C$60="","",'01 Aluminium'!C60) | E58: =IF('01 Aluminium'!$C$60="","",'01 Aluminium'!D60) | F58: =IF('01 Aluminium'!$C$60="","",'01 Aluminium'!E60) | G58: =IF('01 Aluminium'!$C$60="","",'01 Aluminium'!F60) | H58: =IF('01 Aluminium'!$C$60="","",'01 Aluminium'!G60) | I58: =IF('01 Aluminium'!$C$60="","",'01 Aluminium'!J60) | J58: =IF('01 Aluminium'!$C$60="","",'01 Aluminium'!K60) | K58: =IF('01 Aluminium'!$C$60="","",'01 Aluminium'!L60) | L58: =IF('01 Aluminium'!$C$60="","",'01 Aluminium'!M60) | M58: =IF(D58="","",IF(AND(OR(Search!$C$6="All Categories",A58=Search!$C$6),OR(Search!$P$5="",ISNUMBER(SEARCH(" "&Search!$P$5,N58))),OR(Search!$P$6="",ISNUMBER(SEARCH(" "&Search!$P$6,N58))),OR(Search!$P$7="",ISNUMBER(SEARCH(" "&Search!$P$7,N58))),OR(Search!$P$8="",ISNUMBER(SEARCH(" "&Search!$P$8,N58))),OR(Search!$P$9="",ISNUMBER(SEARCH(" "&Search!$P$9,N58))),OR(Search!$P$10="",ISNUMBER(SEARCH(" "&Search!$P$10,N58)))),ROW(),"")) | N58: =IF(D58="",""," "&SUBSTITUTE(SUBSTITUTE(SUBSTITUTE(SUBSTITUTE(SUBSTITUTE(SUBSTITUTE(SUBSTITUTE(B58&" "&C58&" "&D58&" "&E58&" "&F58&" "&G58&" "&H58&" "&'01 Aluminium'!R60,"("," "),")"," "),"/"," "),"-"," "),","," "),";"," "),":"," ")&" ")
A59: =IF('01 Aluminium'!$C$61="","","Aluminium Profiles & Systems") | B59: =IF('01 Aluminium'!$C$61="","",'01 Aluminium'!A61) | C59: =IF('01 Aluminium'!$C$61="","",'01 Aluminium'!B61) | D59: =IF('01 Aluminium'!$C$61="","",'01 Aluminium'!C61) | E59: =IF('01 Aluminium'!$C$61="","",'01 Aluminium'!D61) | F59: =IF('01 Aluminium'!$C$61="","",'01 Aluminium'!E61) | G59: =IF('01 Aluminium'!$C$61="","",'01 Aluminium'!F61) | H59: =IF('01 Aluminium'!$C$61="","",'01 Aluminium'!G61) | I59: =IF('01 Aluminium'!$C$61="","",'01 Aluminium'!J61) | J59: =IF('01 Aluminium'!$C$61="","",'01 Aluminium'!K61) | K59: =IF('01 Aluminium'!$C$61="","",'01 Aluminium'!L61) | L59: =IF('01 Aluminium'!$C$61="","",'01 Aluminium'!M61) | M59: =IF(D59="","",IF(AND(OR(Search!$C$6="All Categories",A59=Search!$C$6),OR(Search!$P$5="",ISNUMBER(SEARCH(" "&Search!$P$5,N59))),OR(Search!$P$6="",ISNUMBER(SEARCH(" "&Search!$P$6,N59))),OR(Search!$P$7="",ISNUMBER(SEARCH(" "&Search!$P$7,N59))),OR(Search!$P$8="",ISNUMBER(SEARCH(" "&Search!$P$8,N59))),OR(Search!$P$9="",ISNUMBER(SEARCH(" "&Search!$P$9,N59))),OR(Search!$P$10="",ISNUMBER(SEARCH(" "&Search!$P$10,N59)))),ROW(),"")) | N59: =IF(D59="",""," "&SUBSTITUTE(SUBSTITUTE(SUBSTITUTE(SUBSTITUTE(SUBSTITUTE(SUBSTITUTE(SUBSTITUTE(B59&" "&C59&" "&D59&" "&E59&" "&F59&" "&G59&" "&H59&" "&'01 Aluminium'!R61,"("," "),")"," "),"/"," "),"-"," "),","," "),";"," "),":"," ")&" ")
A60: =IF('01 Aluminium'!$C$62="","","Aluminium Profiles & Systems") | B60: =IF('01 Aluminium'!$C$62="","",'01 Aluminium'!A62) | C60: =IF('01 Aluminium'!$C$62="","",'01 Aluminium'!B62) | D60: =IF('01 Aluminium'!$C$62="","",'01 Aluminium'!C62) | E60: =IF('01 Aluminium'!$C$62="","",'01 Aluminium'!D62) | F60: =IF('01 Aluminium'!$C$62="","",'01 Aluminium'!E62) | G60: =IF('01 Aluminium'!$C$62="","",'01 Aluminium'!F62) | H60: =IF('01 Aluminium'!$C$62="","",'01 Aluminium'!G62) | I60: =IF('01 Aluminium'!$C$62="","",'01 Aluminium'!J62) | J60: =IF('01 Aluminium'!$C$62="","",'01 Aluminium'!K62) | K60: =IF('01 Aluminium'!$C$62="","",'01 Aluminium'!L62) | L60: =IF('01 Aluminium'!$C$62="","",'01 Aluminium'!M62) | M60: =IF(D60="","",IF(AND(OR(Search!$C$6="All Categories",A60=Search!$C$6),OR(Search!$P$5="",ISNUMBER(SEARCH(" "&Search!$P$5,N60))),OR(Search!$P$6="",ISNUMBER(SEARCH(" "&Search!$P$6,N60))),OR(Search!$P$7="",ISNUMBER(SEARCH(" "&Search!$P$7,N60))),OR(Search!$P$8="",ISNUMBER(SEARCH(" "&Search!$P$8,N60))),OR(Search!$P$9="",ISNUMBER(SEARCH(" "&Search!$P$9,N60))),OR(Search!$P$10="",ISNUMBER(SEARCH(" "&Search!$P$10,N60)))),ROW(),"")) | N60: =IF(D60="",""," "&SUBSTITUTE(SUBSTITUTE(SUBSTITUTE(SUBSTITUTE(SUBSTITUTE(SUBSTITUTE(SUBSTITUTE(B60&" "&C60&" "&D60&" "&E60&" "&F60&" "&G60&" "&H60&" "&'01 Aluminium'!R62,"("," "),")"," "),"/"," "),"-"," "),","," "),";"," "),":"," ")&" ")
A61: =IF('01 Aluminium'!$C$63="","","Aluminium Profiles & Systems") | B61: =IF('01 Aluminium'!$C$63="","",'01 Aluminium'!A63) | C61: =IF('01 Aluminium'!$C$63="","",'01 Aluminium'!B63) | D61: =IF('01 Aluminium'!$C$63="","",'01 Aluminium'!C63) | E61: =IF('01 Aluminium'!$C$63="","",'01 Aluminium'!D63) | F61: =IF('01 Aluminium'!$C$63="","",'01 Aluminium'!E63) | G61: =IF('01 Aluminium'!$C$63="","",'01 Aluminium'!F63) | H61: =IF('01 Aluminium'!$C$63="","",'01 Aluminium'!G63) | I61: =IF('01 Aluminium'!$C$63="","",'01 Aluminium'!J63) | J61: =IF('01 Aluminium'!$C$63="","",'01 Aluminium'!K63) | K61: =IF('01 Aluminium'!$C$63="","",'01 Aluminium'!L63) | L61: =IF('01 Aluminium'!$C$63="","",'01 Aluminium'!M63) | M61: =IF(D61="","",IF(AND(OR(Search!$C$6="All Categories",A61=Search!$C$6),OR(Search!$P$5="",ISNUMBER(SEARCH(" "&Search!$P$5,N61))),OR(Search!$P$6="",ISNUMBER(SEARCH(" "&Search!$P$6,N61))),OR(Search!$P$7="",ISNUMBER(SEARCH(" "&Search!$P$7,N61))),OR(Search!$P$8="",ISNUMBER(SEARCH(" "&Search!$P$8,N61))),OR(Search!$P$9="",ISNUMBER(SEARCH(" "&Search!$P$9,N61))),OR(Search!$P$10="",ISNUMBER(SEARCH(" "&Search!$P$10,N61)))),ROW(),"")) | N61: =IF(D61="",""," "&SUBSTITUTE(SUBSTITUTE(SUBSTITUTE(SUBSTITUTE(SUBSTITUTE(SUBSTITUTE(SUBSTITUTE(B61&" "&C61&" "&D61&" "&E61&" "&F61&" "&G61&" "&H61&" "&'01 Aluminium'!R63,"("," "),")"," "),"/"," "),"-"," "),","," "),";"," "),":"," ")&" ")
A62: =IF('01 Aluminium'!$C$64="","","Aluminium Profiles & Systems") | B62: =IF('01 Aluminium'!$C$64="","",'01 Aluminium'!A64) | C62: =IF('01 Aluminium'!$C$64="","",'01 Aluminium'!B64) | D62: =IF('01 Aluminium'!$C$64="","",'01 Aluminium'!C64) | E62: =IF('01 Aluminium'!$C$64="","",'01 Aluminium'!D64) | F62: =IF('01 Aluminium'!$C$64="","",'01 Aluminium'!E64) | G62: =IF('01 Aluminium'!$C$64="","",'01 Aluminium'!F64) | H62: =IF('01 Aluminium'!$C$64="","",'01 Aluminium'!G64) | I62: =IF('01 Aluminium'!$C$64="","",'01 Aluminium'!J64) | J62: =IF('01 Aluminium'!$C$64="","",'01 Aluminium'!K64) | K62: =IF('01 Aluminium'!$C$64="","",'01 Aluminium'!L64) | L62: =IF('01 Aluminium'!$C$64="","",'01 Aluminium'!M64) | M62: =IF(D62="","",IF(AND(OR(Search!$C$6="All Categories",A62=Search!$C$6),OR(Search!$P$5="",ISNUMBER(SEARCH(" "&Search!$P$5,N62))),OR(Search!$P$6="",ISNUMBER(SEARCH(" "&Search!$P$6,N62))),OR(Search!$P$7="",ISNUMBER(SEARCH(" "&Search!$P$7,N62))),OR(Search!$P$8="",ISNUMBER(SEARCH(" "&Search!$P$8,N62))),OR(Search!$P$9="",ISNUMBER(SEARCH(" "&Search!$P$9,N62))),OR(Search!$P$10="",ISNUMBER(SEARCH(" "&Search!$P$10,N62)))),ROW(),"")) | N62: =IF(D62="",""," "&SUBSTITUTE(SUBSTITUTE(SUBSTITUTE(SUBSTITUTE(SUBSTITUTE(SUBSTITUTE(SUBSTITUTE(B62&" "&C62&" "&D62&" "&E62&" "&F62&" "&G62&" "&H62&" "&'01 Aluminium'!R64,"("," "),")"," "),"/"," "),"-"," "),","," "),";"," "),":"," ")&" ")
A63: =IF('01 Aluminium'!$C$65="","","Aluminium Profiles & Systems") | B63: =IF('01 Aluminium'!$C$65="","",'01 Aluminium'!A65) | C63: =IF('01 Aluminium'!$C$65="","",'01 Aluminium'!B65) | D63: =IF('01 Aluminium'!$C$65="","",'01 Aluminium'!C65) | E63: =IF('01 Aluminium'!$C$65="","",'01 Aluminium'!D65) | F63: =IF('01 Aluminium'!$C$65="","",'01 Aluminium'!E65) | G63: =IF('01 Aluminium'!$C$65="","",'01 Aluminium'!F65) | H63: =IF('01 Aluminium'!$C$65="","",'01 Aluminium'!G65) | I63: =IF('01 Aluminium'!$C$65="","",'01 Aluminium'!J65) | J63: =IF('01 Aluminium'!$C$65="","",'01 Aluminium'!K65) | K63: =IF('01 Aluminium'!$C$65="","",'01 Aluminium'!L65) | L63: =IF('01 Aluminium'!$C$65="","",'01 Aluminium'!M65) | M63: =IF(D63="","",IF(AND(OR(Search!$C$6="All Categories",A63=Search!$C$6),OR(Search!$P$5="",ISNUMBER(SEARCH(" "&Search!$P$5,N63))),OR(Search!$P$6="",ISNUMBER(SEARCH(" "&Search!$P$6,N63))),OR(Search!$P$7="",ISNUMBER(SEARCH(" "&Search!$P$7,N63))),OR(Search!$P$8="",ISNUMBER(SEARCH(" "&Search!$P$8,N63))),OR(Search!$P$9="",ISNUMBER(SEARCH(" "&Search!$P$9,N63))),OR(Search!$P$10="",ISNUMBER(SEARCH(" "&Search!$P$10,N63)))),ROW(),"")) | N63: =IF(D63="",""," "&SUBSTITUTE(SUBSTITUTE(SUBSTITUTE(SUBSTITUTE(SUBSTITUTE(SUBSTITUTE(SUBSTITUTE(B63&" "&C63&" "&D63&" "&E63&" "&F63&" "&G63&" "&H63&" "&'01 Aluminium'!R65,"("," "),")"," "),"/"," "),"-"," "),","," "),";"," "),":"," ")&" ")
A64: =IF('01 Aluminium'!$C$66="","","Aluminium Profiles & Systems") | B64: =IF('01 Aluminium'!$C$66="","",'01 Aluminium'!A66) | C64: =IF('01 Aluminium'!$C$66="","",'01 Aluminium'!B66) | D64: =IF('01 Aluminium'!$C$66="","",'01 Aluminium'!C66) | E64: =IF('01 Aluminium'!$C$66="","",'01 Aluminium'!D66) | F64: =IF('01 Aluminium'!$C$66="","",'01 Aluminium'!E66) | G64: =IF('01 Aluminium'!$C$66="","",'01 Aluminium'!F66) | H64: =IF('01 Aluminium'!$C$66="","",'01 Aluminium'!G66) | I64: =IF('01 Aluminium'!$C$66="","",'01 Aluminium'!J66) | J64: =IF('01 Aluminium'!$C$66="","",'01 Aluminium'!K66) | K64: =IF('01 Aluminium'!$C$66="","",'01 Aluminium'!L66) | L64: =IF('01 Aluminium'!$C$66="","",'01 Aluminium'!M66) | M64: =IF(D64="","",IF(AND(OR(Search!$C$6="All Categories",A64=Search!$C$6),OR(Search!$P$5="",ISNUMBER(SEARCH(" "&Search!$P$5,N64))),OR(Search!$P$6="",ISNUMBER(SEARCH(" "&Search!$P$6,N64))),OR(Search!$P$7="",ISNUMBER(SEARCH(" "&Search!$P$7,N64))),OR(Search!$P$8="",ISNUMBER(SEARCH(" "&Search!$P$8,N64))),OR(Search!$P$9="",ISNUMBER(SEARCH(" "&Search!$P$9,N64))),OR(Search!$P$10="",ISNUMBER(SEARCH(" "&Search!$P$10,N64)))),ROW(),"")) | N64: =IF(D64="",""," "&SUBSTITUTE(SUBSTITUTE(SUBSTITUTE(SUBSTITUTE(SUBSTITUTE(SUBSTITUTE(SUBSTITUTE(B64&" "&C64&" "&D64&" "&E64&" "&F64&" "&G64&" "&H64&" "&'01 Aluminium'!R66,"("," "),")"," "),"/"," "),"-"," "),","," "),";"," "),":"," ")&" ")
A65: =IF('01 Aluminium'!$C$67="","","Aluminium Profiles & Systems") | B65: =IF('01 Aluminium'!$C$67="","",'01 Aluminium'!A67) | C65: =IF('01 Aluminium'!$C$67="","",'01 Aluminium'!B67) | D65: =IF('01 Aluminium'!$C$67="","",'01 Aluminium'!C67) | E65: =IF('01 Aluminium'!$C$67="","",'01 Aluminium'!D67) | F65: =IF('01 Aluminium'!$C$67="","",'01 Aluminium'!E67) | G65: =IF('01 Aluminium'!$C$67="","",'01 Aluminium'!F67) | H65: =IF('01 Aluminium'!$C$67="","",'01 Aluminium'!G67) | I65: =IF('01 Aluminium'!$C$67="","",'01 Aluminium'!J67) | J65: =IF('01 Aluminium'!$C$67="","",'01 Aluminium'!K67) | K65: =IF('01 Aluminium'!$C$67="","",'01 Aluminium'!L67) | L65: =IF('01 Aluminium'!$C$67="","",'01 Aluminium'!M67) | M65: =IF(D65="","",IF(AND(OR(Search!$C$6="All Categories",A65=Search!$C$6),OR(Search!$P$5="",ISNUMBER(SEARCH(" "&Search!$P$5,N65))),OR(Search!$P$6="",ISNUMBER(SEARCH(" "&Search!$P$6,N65))),OR(Search!$P$7="",ISNUMBER(SEARCH(" "&Search!$P$7,N65))),OR(Search!$P$8="",ISNUMBER(SEARCH(" "&Search!$P$8,N65))),OR(Search!$P$9="",ISNUMBER(SEARCH(" "&Search!$P$9,N65))),OR(Search!$P$10="",ISNUMBER(SEARCH(" "&Search!$P$10,N65)))),ROW(),"")) | N65: =IF(D65="",""," "&SUBSTITUTE(SUBSTITUTE(SUBSTITUTE(SUBSTITUTE(SUBSTITUTE(SUBSTITUTE(SUBSTITUTE(B65&" "&C65&" "&D65&" "&E65&" "&F65&" "&G65&" "&H65&" "&'01 Aluminium'!R67,"("," "),")"," "),"/"," "),"-"," "),","," "),";"," "),":"," ")&" ")
A66: =IF('01 Aluminium'!$C$68="","","Aluminium Profiles & Systems") | B66: =IF('01 Aluminium'!$C$68="","",'01 Aluminium'!A68) | C66: =IF('01 Aluminium'!$C$68="","",'01 Aluminium'!B68) | D66: =IF('01 Aluminium'!$C$68="","",'01 Aluminium'!C68) | E66: =IF('01 Aluminium'!$C$68="","",'01 Aluminium'!D68) | F66: =IF('01 Aluminium'!$C$68="","",'01 Aluminium'!E68) | G66: =IF('01 Aluminium'!$C$68="","",'01 Aluminium'!F68) | H66: =IF('01 Aluminium'!$C$68="","",'01 Aluminium'!G68) | I66: =IF('01 Aluminium'!$C$68="","",'01 Aluminium'!J68) | J66: =IF('01 Aluminium'!$C$68="","",'01 Aluminium'!K68) | K66: =IF('01 Aluminium'!$C$68="","",'01 Aluminium'!L68) | L66: =IF('01 Aluminium'!$C$68="","",'01 Aluminium'!M68) | M66: =IF(D66="","",IF(AND(OR(Search!$C$6="All Categories",A66=Search!$C$6),OR(Search!$P$5="",ISNUMBER(SEARCH(" "&Search!$P$5,N66))),OR(Search!$P$6="",ISNUMBER(SEARCH(" "&Search!$P$6,N66))),OR(Search!$P$7="",ISNUMBER(SEARCH(" "&Search!$P$7,N66))),OR(Search!$P$8="",ISNUMBER(SEARCH(" "&Search!$P$8,N66))),OR(Search!$P$9="",ISNUMBER(SEARCH(" "&Search!$P$9,N66))),OR(Search!$P$10="",ISNUMBER(SEARCH(" "&Search!$P$10,N66)))),ROW(),"")) | N66: =IF(D66="",""," "&SUBSTITUTE(SUBSTITUTE(SUBSTITUTE(SUBSTITUTE(SUBSTITUTE(SUBSTITUTE(SUBSTITUTE(B66&" "&C66&" "&D66&" "&E66&" "&F66&" "&G66&" "&H66&" "&'01 Aluminium'!R68,"("," "),")"," "),"/"," "),"-"," "),","," "),";"," "),":"," ")&" ")
A67: =IF('01 Aluminium'!$C$69="","","Aluminium Profiles & Systems") | B67: =IF('01 Aluminium'!$C$69="","",'01 Aluminium'!A69) | C67: =IF('01 Aluminium'!$C$69="","",'01 Aluminium'!B69) | D67: =IF('01 Aluminium'!$C$69="","",'01 Aluminium'!C69) | E67: =IF('01 Aluminium'!$C$69="","",'01 Aluminium'!D69) | F67: =IF('01 Aluminium'!$C$69="","",'01 Aluminium'!E69) | G67: =IF('01 Aluminium'!$C$69="","",'01 Aluminium'!F69) | H67: =IF('01 Aluminium'!$C$69="","",'01 Aluminium'!G69) | I67: =IF('01 Aluminium'!$C$69="","",'01 Aluminium'!J69) | J67: =IF('01 Aluminium'!$C$69="","",'01 Aluminium'!K69) | K67: =IF('01 Aluminium'!$C$69="","",'01 Aluminium'!L69) | L67: =IF('01 Aluminium'!$C$69="","",'01 Aluminium'!M69) | M67: =IF(D67="","",IF(AND(OR(Search!$C$6="All Categories",A67=Search!$C$6),OR(Search!$P$5="",ISNUMBER(SEARCH(" "&Search!$P$5,N67))),OR(Search!$P$6="",ISNUMBER(SEARCH(" "&Search!$P$6,N67))),OR(Search!$P$7="",ISNUMBER(SEARCH(" "&Search!$P$7,N67))),OR(Search!$P$8="",ISNUMBER(SEARCH(" "&Search!$P$8,N67))),OR(Search!$P$9="",ISNUMBER(SEARCH(" "&Search!$P$9,N67))),OR(Search!$P$10="",ISNUMBER(SEARCH(" "&Search!$P$10,N67)))),ROW(),"")) | N67: =IF(D67="",""," "&SUBSTITUTE(SUBSTITUTE(SUBSTITUTE(SUBSTITUTE(SUBSTITUTE(SUBSTITUTE(SUBSTITUTE(B67&" "&C67&" "&D67&" "&E67&" "&F67&" "&G67&" "&H67&" "&'01 Aluminium'!R69,"("," "),")"," "),"/"," "),"-"," "),","," "),";"," "),":"," ")&" ")
A68: =IF('01 Aluminium'!$C$70="","","Aluminium Profiles & Systems") | B68: =IF('01 Aluminium'!$C$70="","",'01 Aluminium'!A70) | C68: =IF('01 Aluminium'!$C$70="","",'01 Aluminium'!B70) | D68: =IF('01 Aluminium'!$C$70="","",'01 Aluminium'!C70) | E68: =IF('01 Aluminium'!$C$70="","",'01 Aluminium'!D70) | F68: =IF('01 Aluminium'!$C$70="","",'01 Aluminium'!E70) | G68: =IF('01 Aluminium'!$C$70="","",'01 Aluminium'!F70) | H68: =IF('01 Aluminium'!$C$70="","",'01 Aluminium'!G70) | I68: =IF('01 Aluminium'!$C$70="","",'01 Aluminium'!J70) | J68: =IF('01 Aluminium'!$C$70="","",'01 Aluminium'!K70) | K68: =IF('01 Aluminium'!$C$70="","",'01 Aluminium'!L70) | L68: =IF('01 Aluminium'!$C$70="","",'01 Aluminium'!M70) | M68: =IF(D68="","",IF(AND(OR(Search!$C$6="All Categories",A68=Search!$C$6),OR(Search!$P$5="",ISNUMBER(SEARCH(" "&Search!$P$5,N68))),OR(Search!$P$6="",ISNUMBER(SEARCH(" "&Search!$P$6,N68))),OR(Search!$P$7="",ISNUMBER(SEARCH(" "&Search!$P$7,N68))),OR(Search!$P$8="",ISNUMBER(SEARCH(" "&Search!$P$8,N68))),OR(Search!$P$9="",ISNUMBER(SEARCH(" "&Search!$P$9,N68))),OR(Search!$P$10="",ISNUMBER(SEARCH(" "&Search!$P$10,N68)))),ROW(),"")) | N68: =IF(D68="",""," "&SUBSTITUTE(SUBSTITUTE(SUBSTITUTE(SUBSTITUTE(SUBSTITUTE(SUBSTITUTE(SUBSTITUTE(B68&" "&C68&" "&D68&" "&E68&" "&F68&" "&G68&" "&H68&" "&'01 Aluminium'!R70,"("," "),")"," "),"/"," "),"-"," "),","," "),";"," "),":"," ")&" ")
A69: =IF('01 Aluminium'!$C$71="","","Aluminium Profiles & Systems") | B69: =IF('01 Aluminium'!$C$71="","",'01 Aluminium'!A71) | C69: =IF('01 Aluminium'!$C$71="","",'01 Aluminium'!B71) | D69: =IF('01 Aluminium'!$C$71="","",'01 Aluminium'!C71) | E69: =IF('01 Aluminium'!$C$71="","",'01 Aluminium'!D71) | F69: =IF('01 Aluminium'!$C$71="","",'01 Aluminium'!E71) | G69: =IF('01 Aluminium'!$C$71="","",'01 Aluminium'!F71) | H69: =IF('01 Aluminium'!$C$71="","",'01 Aluminium'!G71) | I69: =IF('01 Aluminium'!$C$71="","",'01 Aluminium'!J71) | J69: =IF('01 Aluminium'!$C$71="","",'01 Aluminium'!K71) | K69: =IF('01 Aluminium'!$C$71="","",'01 Aluminium'!L71) | L69: =IF('01 Aluminium'!$C$71="","",'01 Aluminium'!M71) | M69: =IF(D69="","",IF(AND(OR(Search!$C$6="All Categories",A69=Search!$C$6),OR(Search!$P$5="",ISNUMBER(SEARCH(" "&Search!$P$5,N69))),OR(Search!$P$6="",ISNUMBER(SEARCH(" "&Search!$P$6,N69))),OR(Search!$P$7="",ISNUMBER(SEARCH(" "&Search!$P$7,N69))),OR(Search!$P$8="",ISNUMBER(SEARCH(" "&Search!$P$8,N69))),OR(Search!$P$9="",ISNUMBER(SEARCH(" "&Search!$P$9,N69))),OR(Search!$P$10="",ISNUMBER(SEARCH(" "&Search!$P$10,N69)))),ROW(),"")) | N69: =IF(D69="",""," "&SUBSTITUTE(SUBSTITUTE(SUBSTITUTE(SUBSTITUTE(SUBSTITUTE(SUBSTITUTE(SUBSTITUTE(B69&" "&C69&" "&D69&" "&E69&" "&F69&" "&G69&" "&H69&" "&'01 Aluminium'!R71,"("," "),")"," "),"/"," "),"-"," "),","," "),";"," "),":"," ")&" ")
A70: =IF('01 Aluminium'!$C$72="","","Aluminium Profiles & Systems") | B70: =IF('01 Aluminium'!$C$72="","",'01 Aluminium'!A72) | C70: =IF('01 Aluminium'!$C$72="","",'01 Aluminium'!B72) | D70: =IF('01 Aluminium'!$C$72="","",'01 Aluminium'!C72) | E70: =IF('01 Aluminium'!$C$72="","",'01 Aluminium'!D72) | F70: =IF('01 Aluminium'!$C$72="","",'01 Aluminium'!E72) | G70: =IF('01 Aluminium'!$C$72="","",'01 Aluminium'!F72) | H70: =IF('01 Aluminium'!$C$72="","",'01 Aluminium'!G72) | I70: =IF('01 Aluminium'!$C$72="","",'01 Aluminium'!J72) | J70: =IF('01 Aluminium'!$C$72="","",'01 Aluminium'!K72) | K70: =IF('01 Aluminium'!$C$72="","",'01 Aluminium'!L72) | L70: =IF('01 Aluminium'!$C$72="","",'01 Aluminium'!M72) | M70: =IF(D70="","",IF(AND(OR(Search!$C$6="All Categories",A70=Search!$C$6),OR(Search!$P$5="",ISNUMBER(SEARCH(" "&Search!$P$5,N70))),OR(Search!$P$6="",ISNUMBER(SEARCH(" "&Search!$P$6,N70))),OR(Search!$P$7="",ISNUMBER(SEARCH(" "&Search!$P$7,N70))),OR(Search!$P$8="",ISNUMBER(SEARCH(" "&Search!$P$8,N70))),OR(Search!$P$9="",ISNUMBER(SEARCH(" "&Search!$P$9,N70))),OR(Search!$P$10="",ISNUMBER(SEARCH(" "&Search!$P$10,N70)))),ROW(),"")) | N70: =IF(D70="",""," "&SUBSTITUTE(SUBSTITUTE(SUBSTITUTE(SUBSTITUTE(SUBSTITUTE(SUBSTITUTE(SUBSTITUTE(B70&" "&C70&" "&D70&" "&E70&" "&F70&" "&G70&" "&H70&" "&'01 Aluminium'!R72,"("," "),")"," "),"/"," "),"-"," "),","," "),";"," "),":"," ")&" ")
A71: =IF('02 Glass'!$C$5="","","Glass - Float, Tempered, Laminated & DGU") -> Glass - Float, Tempered, Laminated & DGU | B71: =IF('02 Glass'!$C$5="","",'02 Glass'!A5) -> GL-001 | C71: =IF('02 Glass'!$C$5="","",'02 Glass'!B5) -> Annealed Float | D71: =IF('02 Glass'!$C$5="","",'02 Glass'!C5) -> Clear float glass | E71: =IF('02 Glass'!$C$5="","",'02 Glass'!D5) -> 4 mm | F71: =IF('02 Glass'!$C$5="","",'02 Glass'!E5) -> Clear | G71: =IF('02 Glass'!$C$5="","",'02 Glass'!F5) -> Emirates Float / Guardian | H71: =IF('02 Glass'!$C$5="","",'02 Glass'!G5) -> m2 | I71: =IF('02 Glass'!$C$5="","",'02 Glass'!J5) -> 31.5 | J71: =IF('02 Glass'!$C$5="","",'02 Glass'!K5) -> 37.8 | K71: =IF('02 Glass'!$C$5="","",'02 Glass'!L5) -> 39.69 | L71: =IF('02 Glass'!$C$5="","",'02 Glass'!M5) -> Indicative | M71: =IF(D71="","",IF(AND(OR(Search!$C$6="All Categories",A71=Search!$C$6),OR(Search!$P$5="",ISNUMBER(SEARCH(" "&Search!$P$5,N71))),OR(Search!$P$6="",ISNUMBER(SEARCH(" "&Search!$P$6,N71))),OR(Search!$P$7="",ISNUMBER(SEARCH(" "&Search!$P$7,N71))),OR(Search!$P$8="",ISNUMBER(SEARCH(" "&Search!$P$8,N71))),OR(Search!$P$9="",ISNUMBER(SEARCH(" "&Search!$P$9,N71))),OR(Search!$P$10="",ISNUMBER(SEARCH(" "&Search!$P$10,N71)))),ROW(),"")) | N71: =IF(D71="",""," "&SUBSTITUTE(SUBSTITUTE(SUBSTITUTE(SUBSTITUTE(SUBSTITUTE(SUBSTITUTE(SUBSTITUTE(B71&" "&C71&" "&D71&" "&E71&" "&F71&" "&G71&" "&H71&" "&'02 Glass'!R5,"("," "),")"," "),"/"," "),"-"," "),","," "),";"," "),":"," ")&" ") -> GL 001 Annealed Float Clear float glass 4 mm Clear Emirates Float Guardian m2 4mm stainless steel
A72: =IF('02 Glass'!$C$6="","","Glass - Float, Tempered, Laminated & DGU") -> Glass - Float, Tempered, Laminated & DGU | B72: =IF('02 Glass'!$C$6="","",'02 Glass'!A6) -> GL-002 | C72: =IF('02 Glass'!$C$6="","",'02 Glass'!B6) -> Annealed Float | D72: =IF('02 Glass'!$C$6="","",'02 Glass'!C6) -> Clear float glass | E72: =IF('02 Glass'!$C$6="","",'02 Glass'!D6) -> 6 mm | F72: =IF('02 Glass'!$C$6="","",'02 Glass'!E6) -> Clear | G72: =IF('02 Glass'!$C$6="","",'02 Glass'!F6) -> Emirates Float / Guardian | H72: =IF('02 Glass'!$C$6="","",'02 Glass'!G6) -> m2 | I72: =IF('02 Glass'!$C$6="","",'02 Glass'!J6) -> 42 | J72: =IF('02 Glass'!$C$6="","",'02 Glass'!K6) -> 50.4 | K72: =IF('02 Glass'!$C$6="","",'02 Glass'!L6) -> 52.92 | L72: =IF('02 Glass'!$C$6="","",'02 Glass'!M6) -> Indicative | M72: =IF(D72="","",IF(AND(OR(Search!$C$6="All Categories",A72=Search!$C$6),OR(Search!$P$5="",ISNUMBER(SEARCH(" "&Search!$P$5,N72))),OR(Search!$P$6="",ISNUMBER(SEARCH(" "&Search!$P$6,N72))),OR(Search!$P$7="",ISNUMBER(SEARCH(" "&Search!$P$7,N72))),OR(Search!$P$8="",ISNUMBER(SEARCH(" "&Search!$P$8,N72))),OR(Search!$P$9="",ISNUMBER(SEARCH(" "&Search!$P$9,N72))),OR(Search!$P$10="",ISNUMBER(SEARCH(" "&Search!$P$10,N72)))),ROW(),"")) | N72: =IF(D72="",""," "&SUBSTITUTE(SUBSTITUTE(SUBSTITUTE(SUBSTITUTE(SUBSTITUTE(SUBSTITUTE(SUBSTITUTE(B72&" "&C72&" "&D72&" "&E72&" "&F72&" "&G72&" "&H72&" "&'02 Glass'!R6,"("," "),")"," "),"/"," "),"-"," "),","," "),";"," "),":"," ")&" ") -> GL 002 Annealed Float Clear float glass 6 mm Clear Emirates Float Guardian m2 6mm stainless steel
A73: =IF('02 Glass'!$C$7="","","Glass - Float, Tempered, Laminated & DGU") -> Glass - Float, Tempered, Laminated & DGU | B73: =IF('02 Glass'!$C$7="","",'02 Glass'!A7) -> GL-003 | C73: =IF('02 Glass'!$C$7="","",'02 Glass'!B7) -> Annealed Float | D73: =IF('02 Glass'!$C$7="","",'02 Glass'!C7) -> Clear float glass | E73: =IF('02 Glass'!$C$7="","",'02 Glass'!D7) -> 8 mm | F73: =IF('02 Glass'!$C$7="","",'02 Glass'!E7) -> Clear | G73: =IF('02 Glass'!$C$7="","",'02 Glass'!F7) -> Emirates Float / Guardian | H73: =IF('02 Glass'!$C$7="","",'02 Glass'!G7) -> m2 | I73: =IF('02 Glass'!$C$7="","",'02 Glass'!J7) -> 57.75 | J73: =IF('02 Glass'!$C$7="","",'02 Glass'!K7) -> 69.3 | K73: =IF('02 Glass'!$C$7="","",'02 Glass'!L7) -> 72.77 | L73: =IF('02 Glass'!$C$7="","",'02 Glass'!M7) -> Indicative | M73: =IF(D73="","",IF(AND(OR(Search!$C$6="All Categories",A73=Search!$C$6),OR(Search!$P$5="",ISNUMBER(SEARCH(" "&Search!$P$5,N73))),OR(Search!$P$6="",ISNUMBER(SEARCH(" "&Search!$P$6,N73))),OR(Search!$P$7="",ISNUMBER(SEARCH(" "&Search!$P$7,N73))),OR(Search!$P$8="",ISNUMBER(SEARCH(" "&Search!$P$8,N73))),OR(Search!$P$9="",ISNUMBER(SEARCH(" "&Search!$P$9,N73))),OR(Search!$P$10="",ISNUMBER(SEARCH(" "&Search!$P$10,N73)))),ROW(),"")) | N73: =IF(D73="",""," "&SUBSTITUTE(SUBSTITUTE(SUBSTITUTE(SUBSTITUTE(SUBSTITUTE(SUBSTITUTE(SUBSTITUTE(B73&" "&C73&" "&D73&" "&E73&" "&F73&" "&G73&" "&H73&" "&'02 Glass'!R7,"("," "),")"," "),"/"," "),"-"," "),","," "),";"," "),":"," ")&" ") -> GL 003 Annealed Float Clear float glass 8 mm Clear Emirates Float Guardian m2 8mm stainless steel
A74: =IF('02 Glass'!$C$8="","","Glass - Float, Tempered, Laminated & DGU") -> Glass - Float, Tempered, Laminated & DGU | B74: =IF('02 Glass'!$C$8="","",'02 Glass'!A8) -> GL-004 | C74: =IF('02 Glass'!$C$8="","",'02 Glass'!B8) -> Annealed Float | D74: =IF('02 Glass'!$C$8="","",'02 Glass'!C8) -> Clear float glass | E74: =IF('02 Glass'!$C$8="","",'02 Glass'!D8) -> 10 mm | F74: =IF('02 Glass'!$C$8="","",'02 Glass'!E8) -> Clear | G74: =IF('02 Glass'!$C$8="","",'02 Glass'!F8) -> Emirates Float / Guardian | H74: =IF('02 Glass'!$C$8="","",'02 Glass'!G8) -> m2 | I74: =IF('02 Glass'!$C$8="","",'02 Glass'!J8) -> 73.5 | J74: =IF('02 Glass'!$C$8="","",'02 Glass'!K8) -> 88.2 | K74: =IF('02 Glass'!$C$8="","",'02 Glass'!L8) -> 92.61 | L74: =IF('02 Glass'!$C$8="","",'02 Glass'!M8) -> Indicative | M74: =IF(D74="","",IF(AND(OR(Search!$C$6="All Categories",A74=Search!$C$6),OR(Search!$P$5="",ISNUMBER(SEARCH(" "&Search!$P$5,N74))),OR(Search!$P$6="",ISNUMBER(SEARCH(" "&Search!$P$6,N74))),OR(Search!$P$7="",ISNUMBER(SEARCH(" "&Search!$P$7,N74))),OR(Search!$P$8="",ISNUMBER(SEARCH(" "&Search!$P$8,N74))),OR(Search!$P$9="",ISNUMBER(SEARCH(" "&Search!$P$9,N74))),OR(Search!$P$10="",ISNUMBER(SEARCH(" "&Search!$P$10,N74)))),ROW(),"")) | N74: =IF(D74="",""," "&SUBSTITUTE(SUBSTITUTE(SUBSTITUTE(SUBSTITUTE(SUBSTITUTE(SUBSTITUTE(SUBSTITUTE(B74&" "&C74&" "&D74&" "&E74&" "&F74&" "&G74&" "&H74&" "&'02 Glass'!R8,"("," "),")"," "),"/"," "),"-"," "),","," "),";"," "),":"," ")&" ") -> GL 004 Annealed Float Clear float glass 10 mm Clear Emirates Float Guardian m2 10mm stainless steel
A75: =IF('02 Glass'!$C$9="","","Glass - Float, Tempered, Laminated & DGU") -> Glass - Float, Tempered, Laminated & DGU | B75: =IF('02 Glass'!$C$9="","",'02 Glass'!A9) -> GL-005 | C75: =IF('02 Glass'!$C$9="","",'02 Glass'!B9) -> Annealed Float | D75: =IF('02 Glass'!$C$9="","",'02 Glass'!C9) -> Clear float glass | E75: =IF('02 Glass'!$C$9="","",'02 Glass'!D9) -> 12 mm | F75: =IF('02 Glass'!$C$9="","",'02 Glass'!E9) -> Clear | G75: =IF('02 Glass'!$C$9="","",'02 Glass'!F9) -> Emirates Float / Guardian | H75: =IF('02 Glass'!$C$9="","",'02 Glass'!G9) -> m2 | I75: =IF('02 Glass'!$C$9="","",'02 Glass'!J9) -> 92.4 | J75: =IF('02 Glass'!$C$9="","",'02 Glass'!K9) -> 110.88 | K75: =IF('02 Glass'!$C$9="","",'02 Glass'!L9) -> 116.42 | L75: =IF('02 Glass'!$C$9="","",'02 Glass'!M9) -> Indicative | M75: =IF(D75="","",IF(AND(OR(Search!$C$6="All Categories",A75=Search!$C$6),OR(Search!$P$5="",ISNUMBER(SEARCH(" "&Search!$P$5,N75))),OR(Search!$P$6="",ISNUMBER(SEARCH(" "&Search!$P$6,N75))),OR(Search!$P$7="",ISNUMBER(SEARCH(" "&Search!$P$7,N75))),OR(Search!$P$8="",ISNUMBER(SEARCH(" "&Search!$P$8,N75))),OR(Search!$P$9="",ISNUMBER(SEARCH(" "&Search!$P$9,N75))),OR(Search!$P$10="",ISNUMBER(SEARCH(" "&Search!$P$10,N75)))),ROW(),"")) | N75: =IF(D75="",""," "&SUBSTITUTE(SUBSTITUTE(SUBSTITUTE(SUBSTITUTE(SUBSTITUTE(SUBSTITUTE(SUBSTITUTE(B75&" "&C75&" "&D75&" "&E75&" "&F75&" "&G75&" "&H75&" "&'02 Glass'!R9,"("," "),")"," "),"/"," "),"-"," "),","," "),";"," "),":"," ")&" ") -> GL 005 Annealed Float Clear float glass 12 mm Clear Emirates Float Guardian m2 12mm stainless steel
A76: =IF('02 Glass'!$C$10="","","Glass - Float, Tempered, Laminated & DGU") -> Glass - Float, Tempered, Laminated & DGU | B76: =IF('02 Glass'!$C$10="","",'02 Glass'!A10) -> GL-006 | C76: =IF('02 Glass'!$C$10="","",'02 Glass'!B10) -> Annealed Float | D76: =IF('02 Glass'!$C$10="","",'02 Glass'!C10) -> Tinted float glass | E76: =IF('02 Glass'!$C$10="","",'02 Glass'!D10) -> 6 mm | F76: =IF('02 Glass'!$C$10="","",'02 Glass'!E10) -> Grey / Bronze / Green | G76: =IF('02 Glass'!$C$10="","",'02 Glass'!F10) -> Emirates Float / Guardian | H76: =IF('02 Glass'!$C$10="","",'02 Glass'!G10) -> m2 | I76: =IF('02 Glass'!$C$10="","",'02 Glass'!J10) -> 57.75 | J76: =IF('02 Glass'!$C$10="","",'02 Glass'!K10) -> 69.3 | K76: =IF('02 Glass'!$C$10="","",'02 Glass'!L10) -> 72.77 | L76: =IF('02 Glass'!$C$10="","",'02 Glass'!M10) -> Indicative | M76: =IF(D76="","",IF(AND(OR(Search!$C$6="All Categories",A76=Search!$C$6),OR(Search!$P$5="",ISNUMBER(SEARCH(" "&Search!$P$5,N76))),OR(Search!$P$6="",ISNUMBER(SEARCH(" "&Search!$P$6,N76))),OR(Search!$P$7="",ISNUMBER(SEARCH(" "&Search!$P$7,N76))),OR(Search!$P$8="",ISNUMBER(SEARCH(" "&Search!$P$8,N76))),OR(Search!$P$9="",ISNUMBER(SEARCH(" "&Search!$P$9,N76))),OR(Search!$P$10="",ISNUMBER(SEARCH(" "&Search!$P$10,N76)))),ROW(),"")) | N76: =IF(D76="",""," "&SUBSTITUTE(SUBSTITUTE(SUBSTITUTE(SUBSTITUTE(SUBSTITUTE(SUBSTITUTE(SUBSTITUTE(B76&" "&C76&" "&D76&" "&E76&" "&F76&" "&G76&" "&H76&" "&'02 Glass'!R10,"("," "),")"," "),"/"," "),"-"," "),","," "),";"," "),":"," ")&" ") -> GL 006 Annealed Float Tinted float glass 6 mm Grey Bronze Green Emirates Float Guardian m2 6mm stainless steel
A77: =IF('02 Glass'!$C$11="","","Glass - Float, Tempered, Laminated & DGU") -> Glass - Float, Tempered, Laminated & DGU | B77: =IF('02 Glass'!$C$11="","",'02 Glass'!A11) -> GL-007 | C77: =IF('02 Glass'!$C$11="","",'02 Glass'!B11) -> Annealed Float | D77: =IF('02 Glass'!$C$11="","",'02 Glass'!C11) -> Reflective glass (hard coat) | E77: =IF('02 Glass'!$C$11="","",'02 Glass'!D11) -> 6 mm | F77: =IF('02 Glass'!$C$11="","",'02 Glass'!E11) -> Blue / Grey / Silver | G77: =IF('02 Glass'!$C$11="","",'02 Glass'!F11) -> Emirates Float / Guardian | H77: =IF('02 Glass'!$C$11="","",'02 Glass'!G11) -> m2 | I77: =IF('02 Glass'!$C$11="","",'02 Glass'!J11) -> 78.75 | J77: =IF('02 Glass'!$C$11="","",'02 Glass'!K11) -> 94.5 | K77: =IF('02 Glass'!$C$11="","",'02 Glass'!L11) -> 99.23 | L77: =IF('02 Glass'!$C$11="","",'02 Glass'!M11) -> Indicative | M77: =IF(D77="","",IF(AND(OR(Search!$C$6="All Categories",A77=Search!$C$6),OR(Search!$P$5="",ISNUMBER(SEARCH(" "&Search!$P$5,N77))),OR(Search!$P$6="",ISNUMBER(SEARCH(" "&Search!$P$6,N77))),OR(Search!$P$7="",ISNUMBER(SEARCH(" "&Search!$P$7,N77))),OR(Search!$P$8="",ISNUMBER(SEARCH(" "&Search!$P$8,N77))),OR(Search!$P$9="",ISNUMBER(SEARCH(" "&Search!$P$9,N77))),OR(Search!$P$10="",ISNUMBER(SEARCH(" "&Search!$P$10,N77)))),ROW(),"")) | N77: =IF(D77="",""," "&SUBSTITUTE(SUBSTITUTE(SUBSTITUTE(SUBSTITUTE(SUBSTITUTE(SUBSTITUTE(SUBSTITUTE(B77&" "&C77&" "&D77&" "&E77&" "&F77&" "&G77&" "&H77&" "&'02 Glass'!R11,"("," "),")"," "),"/"," "),"-"," "),","," "),";"," "),":"," ")&" ") -> GL 007 Annealed Float Reflective glass hard coat 6 mm Blue Grey Silver Emirates Float Guardian m2 6mm stainless steel
A78: =IF('02 Glass'!$C$12="","","Glass - Float, Tempered, Laminated & DGU") -> Glass - Float, Tempered, Laminated & DGU | B78: =IF('02 Glass'!$C$12="","",'02 Glass'!A12) -> GL-008 | C78: =IF('02 Glass'!$C$12="","",'02 Glass'!B12) -> Tempered | D78: =IF('02 Glass'!$C$12="","",'02 Glass'!C12) -> Clear tempered glass | E78: =IF('02 Glass'!$C$12="","",'02 Glass'!D12) -> 6 mm, edges polished | F78: =IF('02 Glass'!$C$12="","",'02 Glass'!E12) -> Clear | G78: =IF('02 Glass'!$C$12="","",'02 Glass'!F12) -> Local processor | H78: =IF('02 Glass'!$C$12="","",'02 Glass'!G12) -> m2 | I78: =IF('02 Glass'!$C$12="","",'02 Glass'!J12) -> 78.75 | J78: =IF('02 Glass'!$C$12="","",'02 Glass'!K12) -> 94.5 | K78: =IF('02 Glass'!$C$12="","",'02 Glass'!L12) -> 99.23 | L78: =IF('02 Glass'!$C$12="","",'02 Glass'!M12) -> Indicative | M78: =IF(D78="","",IF(AND(OR(Search!$C$6="All Categories",A78=Search!$C$6),OR(Search!$P$5="",ISNUMBER(SEARCH(" "&Search!$P$5,N78))),OR(Search!$P$6="",ISNUMBER(SEARCH(" "&Search!$P$6,N78))),OR(Search!$P$7="",ISNUMBER(SEARCH(" "&Search!$P$7,N78))),OR(Search!$P$8="",ISNUMBER(SEARCH(" "&Search!$P$8,N78))),OR(Search!$P$9="",ISNUMBER(SEARCH(" "&Search!$P$9,N78))),OR(Search!$P$10="",ISNUMBER(SEARCH(" "&Search!$P$10,N78)))),ROW(),"")) | N78: =IF(D78="",""," "&SUBSTITUTE(SUBSTITUTE(SUBSTITUTE(SUBSTITUTE(SUBSTITUTE(SUBSTITUTE(SUBSTITUTE(B78&" "&C78&" "&D78&" "&E78&" "&F78&" "&G78&" "&H78&" "&'02 Glass'!R12,"("," "),")"," "),"/"," "),"-"," "),","," "),";"," "),":"," ")&" ") -> GL 008 Tempered Clear tempered glass 6 mm edges polished Clear Local processor m2 6mm toughened stainless steel
A79: =IF('02 Glass'!$C$13="","","Glass - Float, Tempered, Laminated & DGU") -> Glass - Float, Tempered, Laminated & DGU | B79: =IF('02 Glass'!$C$13="","",'02 Glass'!A13) -> GL-009 | C79: =IF('02 Glass'!$C$13="","",'02 Glass'!B13) -> Tempered | D79: =IF('02 Glass'!$C$13="","",'02 Glass'!C13) -> Clear tempered glass | E79: =IF('02 Glass'!$C$13="","",'02 Glass'!D13) -> 8 mm, edges polished | F79: =IF('02 Glass'!$C$13="","",'02 Glass'!E13) -> Clear | G79: =IF('02 Glass'!$C$13="","",'02 Glass'!F13) -> Local processor | H79: =IF('02 Glass'!$C$13="","",'02 Glass'!G13) -> m2 | I79: =IF('02 Glass'!$C$13="","",'02 Glass'!J13) -> 99.75 | J79: =IF('02 Glass'!$C$13="","",'02 Glass'!K13) -> 119.7 | K79: =IF('02 Glass'!$C$13="","",'02 Glass'!L13) -> 125.69 | L79: =IF('02 Glass'!$C$13="","",'02 Glass'!M13) -> Indicative | M79: =IF(D79="","",IF(AND(OR(Search!$C$6="All Categories",A79=Search!$C$6),OR(Search!$P$5="",ISNUMBER(SEARCH(" "&Search!$P$5,N79))),OR(Search!$P$6="",ISNUMBER(SEARCH(" "&Search!$P$6,N79))),OR(Search!$P$7="",ISNUMBER(SEARCH(" "&Search!$P$7,N79))),OR(Search!$P$8="",ISNUMBER(SEARCH(" "&Search!$P$8,N79))),OR(Search!$P$9="",ISNUMBER(SEARCH(" "&Search!$P$9,N79))),OR(Search!$P$10="",ISNUMBER(SEARCH(" "&Search!$P$10,N79)))),ROW(),"")) | N79: =IF(D79="",""," "&SUBSTITUTE(SUBSTITUTE(SUBSTITUTE(SUBSTITUTE(SUBSTITUTE(SUBSTITUTE(SUBSTITUTE(B79&" "&C79&" "&D79&" "&E79&" "&F79&" "&G79&" "&H79&" "&'02 Glass'!R13,"("," "),")"," "),"/"," "),"-"," "),","," "),";"," "),":"," ")&" ") -> GL 009 Tempered Clear tempered glass 8 mm edges polished Clear Local processor m2 8mm toughened stainless steel
A80: =IF('02 Glass'!$C$14="","","Glass - Float, Tempered, Laminated & DGU") -> Glass - Float, Tempered, Laminated & DGU | B80: =IF('02 Glass'!$C$14="","",'02 Glass'!A14) -> GL-010 | C80: =IF('02 Glass'!$C$14="","",'02 Glass'!B14) -> Tempered | D80: =IF('02 Glass'!$C$14="","",'02 Glass'!C14) -> Clear tempered glass | E80: =IF('02 Glass'!$C$14="","",'02 Glass'!D14) -> 10 mm, edges polished | F80: =IF('02 Glass'!$C$14="","",'02 Glass'!E14) -> Clear | G80: =IF('02 Glass'!$C$14="","",'02 Glass'!F14) -> Local processor | H80: =IF('02 Glass'!$C$14="","",'02 Glass'!G14) -> m2 | I80: =IF('02 Glass'!$C$14="","",'02 Glass'!J14) -> 126 | J80: =IF('02 Glass'!$C$14="","",'02 Glass'!K14) -> 151.2 | K80: =IF('02 Glass'!$C$14="","",'02 Glass'!L14) -> 158.76 | L80: =IF('02 Glass'!$C$14="","",'02 Glass'!M14) -> Indicative | M80: =IF(D80="","",IF(AND(OR(Search!$C$6="All Categories",A80=Search!$C$6),OR(Search!$P$5="",ISNUMBER(SEARCH(" "&Search!$P$5,N80))),OR(Search!$P$6="",ISNUMBER(SEARCH(" "&Search!$P$6,N80))),OR(Search!$P$7="",ISNUMBER(SEARCH(" "&Search!$P$7,N80))),OR(Search!$P$8="",ISNUMBER(SEARCH(" "&Search!$P$8,N80))),OR(Search!$P$9="",ISNUMBER(SEARCH(" "&Search!$P$9,N80))),OR(Search!$P$10="",ISNUMBER(SEARCH(" "&Search!$P$10,N80)))),ROW(),"")) | N80: =IF(D80="",""," "&SUBSTITUTE(SUBSTITUTE(SUBSTITUTE(SUBSTITUTE(SUBSTITUTE(SUBSTITUTE(SUBSTITUTE(B80&" "&C80&" "&D80&" "&E80&" "&F80&" "&G80&" "&H80&" "&'02 Glass'!R14,"("," "),")"," "),"/"," "),"-"," "),","," "),";"," "),":"," ")&" ") -> GL 010 Tempered Clear tempered glass 10 mm edges polished Clear Local processor m2 10mm toughened stainless steel
A81: =IF('02 Glass'!$C$15="","","Glass - Float, Tempered, Laminated & DGU") -> Glass - Float, Tempered, Laminated & DGU | B81: =IF('02 Glass'!$C$15="","",'02 Glass'!A15) -> GL-011 | C81: =IF('02 Glass'!$C$15="","",'02 Glass'!B15) -> Tempered | D81: =IF('02 Glass'!$C$15="","",'02 Glass'!C15) -> Clear tempered glass | E81: =IF('02 Glass'!$C$15="","",'02 Glass'!D15) -> 12 mm, edges polished | F81: =IF('02 Glass'!$C$15="","",'02 Glass'!E15) -> Clear | G81: =IF('02 Glass'!$C$15="","",'02 Glass'!F15) -> Local processor | H81: =IF('02 Glass'!$C$15="","",'02 Glass'!G15) -> m2 | I81: =IF('02 Glass'!$C$15="","",'02 Glass'!J15) -> 157.5 | J81: =IF('02 Glass'!$C$15="","",'02 Glass'!K15) -> 189 | K81: =IF('02 Glass'!$C$15="","",'02 Glass'!L15) -> 198.45 | L81: =IF('02 Glass'!$C$15="","",'02 Glass'!M15) -> Indicative | M81: =IF(D81="","",IF(AND(OR(Search!$C$6="All Categories",A81=Search!$C$6),OR(Search!$P$5="",ISNUMBER(SEARCH(" "&Search!$P$5,N81))),OR(Search!$P$6="",ISNUMBER(SEARCH(" "&Search!$P$6,N81))),OR(Search!$P$7="",ISNUMBER(SEARCH(" "&Search!$P$7,N81))),OR(Search!$P$8="",ISNUMBER(SEARCH(" "&Search!$P$8,N81))),OR(Search!$P$9="",ISNUMBER(SEARCH(" "&Search!$P$9,N81))),OR(Search!$P$10="",ISNUMBER(SEARCH(" "&Search!$P$10,N81)))),ROW(),"")) | N81: =IF(D81="",""," "&SUBSTITUTE(SUBSTITUTE(SUBSTITUTE(SUBSTITUTE(SUBSTITUTE(SUBSTITUTE(SUBSTITUTE(B81&" "&C81&" "&D81&" "&E81&" "&F81&" "&G81&" "&H81&" "&'02 Glass'!R15,"("," "),")"," "),"/"," "),"-"," "),","," "),";"," "),":"," ")&" ") -> GL 011 Tempered Clear tempered glass 12 mm edges polished Clear Local processor m2 12mm toughened stainless steel
A82: =IF('02 Glass'!$C$16="","","Glass - Float, Tempered, Laminated & DGU") -> Glass - Float, Tempered, Laminated & DGU | B82: =IF('02 Glass'!$C$16="","",'02 Glass'!A16) -> GL-012 | C82: =IF('02 Glass'!$C$16="","",'02 Glass'!B16) -> Tempered | D82: =IF('02 Glass'!$C$16="","",'02 Glass'!C16) -> Clear tempered glass | E82: =IF('02 Glass'!$C$16="","",'02 Glass'!D16) -> 15 mm, edges polished | F82: =IF('02 Glass'!$C$16="","",'02 Glass'!E16) -> Clear | G82: =IF('02 Glass'!$C$16="","",'02 Glass'!F16) -> Local processor | H82: =IF('02 Glass'!$C$16="","",'02 Glass'!G16) -> m2 | I82: =IF('02 Glass'!$C$16="","",'02 Glass'!J16) -> 273 | J82: =IF('02 Glass'!$C$16="","",'02 Glass'!K16) -> 327.6 | K82: =IF('02 Glass'!$C$16="","",'02 Glass'!L16) -> 343.98 | L82: =IF('02 Glass'!$C$16="","",'02 Glass'!M16) -> Indicative | M82: =IF(D82="","",IF(AND(OR(Search!$C$6="All Categories",A82=Search!$C$6),OR(Search!$P$5="",ISNUMBER(SEARCH(" "&Search!$P$5,N82))),OR(Search!$P$6="",ISNUMBER(SEARCH(" "&Search!$P$6,N82))),OR(Search!$P$7="",ISNUMBER(SEARCH(" "&Search!$P$7,N82))),OR(Search!$P$8="",ISNUMBER(SEARCH(" "&Search!$P$8,N82))),OR(Search!$P$9="",ISNUMBER(SEARCH(" "&Search!$P$9,N82))),OR(Search!$P$10="",ISNUMBER(SEARCH(" "&Search!$P$10,N82)))),ROW(),"")) | N82: =IF(D82="",""," "&SUBSTITUTE(SUBSTITUTE(SUBSTITUTE(SUBSTITUTE(SUBSTITUTE(SUBSTITUTE(SUBSTITUTE(B82&" "&C82&" "&D82&" "&E82&" "&F82&" "&G82&" "&H82&" "&'02 Glass'!R16,"("," "),")"," "),"/"," "),"-"," "),","," "),";"," "),":"," ")&" ") -> GL 012 Tempered Clear tempered glass 15 mm edges polished Clear Local processor m2 15mm toughened stainless steel
A83: =IF('02 Glass'!$C$17="","","Glass - Float, Tempered, Laminated & DGU") -> Glass - Float, Tempered, Laminated & DGU | B83: =IF('02 Glass'!$C$17="","",'02 Glass'!A17) -> GL-013 | C83: =IF('02 Glass'!$C$17="","",'02 Glass'!B17) -> Tempered | D83: =IF('02 Glass'!$C$17="","",'02 Glass'!C17) -> Clear tempered glass | E83: =IF('02 Glass'!$C$17="","",'02 Glass'!D17) -> 19 mm, edges polished | F83: =IF('02 Glass'!$C$17="","",'02 Glass'!E17) -> Clear | G83: =IF('02 Glass'!$C$17="","",'02 Glass'!F17) -> Local processor | H83: =IF('02 Glass'!$C$17="","",'02 Glass'!G17) -> m2 | I83: =IF('02 Glass'!$C$17="","",'02 Glass'!J17) -> 441 | J83: =IF('02 Glass'!$C$17="","",'02 Glass'!K17) -> 529.2 | K83: =IF('02 Glass'!$C$17="","",'02 Glass'!L17) -> 555.66 | L83: =IF('02 Glass'!$C$17="","",'02 Glass'!M17) -> Indicative | M83: =IF(D83="","",IF(AND(OR(Search!$C$6="All Categories",A83=Search!$C$6),OR(Search!$P$5="",ISNUMBER(SEARCH(" "&Search!$P$5,N83))),OR(Search!$P$6="",ISNUMBER(SEARCH(" "&Search!$P$6,N83))),OR(Search!$P$7="",ISNUMBER(SEARCH(" "&Search!$P$7,N83))),OR(Search!$P$8="",ISNUMBER(SEARCH(" "&Search!$P$8,N83))),OR(Search!$P$9="",ISNUMBER(SEARCH(" "&Search!$P$9,N83))),OR(Search!$P$10="",ISNUMBER(SEARCH(" "&Search!$P$10,N83)))),ROW(),"")) | N83: =IF(D83="",""," "&SUBSTITUTE(SUBSTITUTE(SUBSTITUTE(SUBSTITUTE(SUBSTITUTE(SUBSTITUTE(SUBSTITUTE(B83&" "&C83&" "&D83&" "&E83&" "&F83&" "&G83&" "&H83&" "&'02 Glass'!R17,"("," "),")"," "),"/"," "),"-"," "),","," "),";"," "),":"," ")&" ") -> GL 013 Tempered Clear tempered glass 19 mm edges polished Clear Local processor m2 19mm toughened stainless steel
A84: =IF('02 Glass'!$C$18="","","Glass - Float, Tempered, Laminated & DGU") -> Glass - Float, Tempered, Laminated & DGU | B84: =IF('02 Glass'!$C$18="","",'02 Glass'!A18) -> GL-014 | C84: =IF('02 Glass'!$C$18="","",'02 Glass'!B18) -> Tempered | D84: =IF('02 Glass'!$C$18="","",'02 Glass'!C18) -> Tinted tempered glass | E84: =IF('02 Glass'!$C$18="","",'02 Glass'!D18) -> 10 mm | F84: =IF('02 Glass'!$C$18="","",'02 Glass'!E18) -> Grey / Bronze | G84: =IF('02 Glass'!$C$18="","",'02 Glass'!F18) -> Local processor | H84: =IF('02 Glass'!$C$18="","",'02 Glass'!G18) -> m2 | I84: =IF('02 Glass'!$C$18="","",'02 Glass'!J18) -> 152.25 | J84: =IF('02 Glass'!$C$18="","",'02 Glass'!K18) -> 182.7 | K84: =IF('02 Glass'!$C$18="","",'02 Glass'!L18) -> 191.84 | L84: =IF('02 Glass'!$C$18="","",'02 Glass'!M18) -> Indicative | M84: =IF(D84="","",IF(AND(OR(Search!$C$6="All Categories",A84=Search!$C$6),OR(Search!$P$5="",ISNUMBER(SEARCH(" "&Search!$P$5,N84))),OR(Search!$P$6="",ISNUMBER(SEARCH(" "&Search!$P$6,N84))),OR(Search!$P$7="",ISNUMBER(SEARCH(" "&Search!$P$7,N84))),OR(Search!$P$8="",ISNUMBER(SEARCH(" "&Search!$P$8,N84))),OR(Search!$P$9="",ISNUMBER(SEARCH(" "&Search!$P$9,N84))),OR(Search!$P$10="",ISNUMBER(SEARCH(" "&Search!$P$10,N84)))),ROW(),"")) | N84: =IF(D84="",""," "&SUBSTITUTE(SUBSTITUTE(SUBSTITUTE(SUBSTITUTE(SUBSTITUTE(SUBSTITUTE(SUBSTITUTE(B84&" "&C84&" "&D84&" "&E84&" "&F84&" "&G84&" "&H84&" "&'02 Glass'!R18,"("," "),")"," "),"/"," "),"-"," "),","," "),";"," "),":"," ")&" ") -> GL 014 Tempered Tinted tempered glass 10 mm Grey Bronze Local processor m2 10mm toughened stainless steel
A85: =IF('02 Glass'!$C$19="","","Glass - Float, Tempered, Laminated & DGU") -> Glass - Float, Tempered, Laminated & DGU | B85: =IF('02 Glass'!$C$19="","",'02 Glass'!A19) -> GL-015 | C85: =IF('02 Glass'!$C$19="","",'02 Glass'!B19) -> Tempered | D85: =IF('02 Glass'!$C$19="","",'02 Glass'!C19) -> Low-iron (extra clear) tempered glass | E85: =IF('02 Glass'!$C$19="","",'02 Glass'!D19) -> 10 mm | F85: =IF('02 Glass'!$C$19="","",'02 Glass'!E19) -> Ultra clear | G85: =IF('02 Glass'!$C$19="","",'02 Glass'!F19) -> Local processor | H85: =IF('02 Glass'!$C$19="","",'02 Glass'!G19) -> m2 | I85: =IF('02 Glass'!$C$19="","",'02 Glass'!J19) -> 220.5 | J85: =IF('02 Glass'!$C$19="","",'02 Glass'!K19) -> 264.6 | K85: =IF('02 Glass'!$C$19="","",'02 Glass'!L19) -> 277.83 | L85: =IF('02 Glass'!$C$19="","",'02 Glass'!M19) -> Indicative | M85: =IF(D85="","",IF(AND(OR(Search!$C$6="All Categories",A85=Search!$C$6),OR(Search!$P$5="",ISNUMBER(SEARCH(" "&Search!$P$5,N85))),OR(Search!$P$6="",ISNUMBER(SEARCH(" "&Search!$P$6,N85))),OR(Search!$P$7="",ISNUMBER(SEARCH(" "&Search!$P$7,N85))),OR(Search!$P$8="",ISNUMBER(SEARCH(" "&Search!$P$8,N85))),OR(Search!$P$9="",ISNUMBER(SEARCH(" "&Search!$P$9,N85))),OR(Search!$P$10="",ISNUMBER(SEARCH(" "&Search!$P$10,N85)))),ROW(),"")) | N85: =IF(D85="",""," "&SUBSTITUTE(SUBSTITUTE(SUBSTITUTE(SUBSTITUTE(SUBSTITUTE(SUBSTITUTE(SUBSTITUTE(B85&" "&C85&" "&D85&" "&E85&" "&F85&" "&G85&" "&H85&" "&'02 Glass'!R19,"("," "),")"," "),"/"," "),"-"," "),","," "),";"," "),":"," ")&" ") -> GL 015 Tempered Low iron extra clear tempered glass 10 mm Ultra clear Local processor m2 10mm toughened extra clear ultra stainless steel
A86: =IF('02 Glass'!$C$20="","","Glass - Float, Tempered, Laminated & DGU") -> Glass - Float, Tempered, Laminated & DGU | B86: =IF('02 Glass'!$C$20="","",'02 Glass'!A20) -> GL-016 | C86: =IF('02 Glass'!$C$20="","",'02 Glass'!B20) -> Tempered | D86: =IF('02 Glass'!$C$20="","",'02 Glass'!C20) -> Low-iron (extra clear) tempered glass | E86: =IF('02 Glass'!$C$20="","",'02 Glass'!D20) -> 12 mm | F86: =IF('02 Glass'!$C$20="","",'02 Glass'!E20) -> Ultra clear | G86: =IF('02 Glass'!$C$20="","",'02 Glass'!F20) -> Local processor | H86: =IF('02 Glass'!$C$20="","",'02 Glass'!G20) -> m2 | I86: =IF('02 Glass'!$C$20="","",'02 Glass'!J20) -> 273 | J86: =IF('02 Glass'!$C$20="","",'02 Glass'!K20) -> 327.6 | K86: =IF('02 Glass'!$C$20="","",'02 Glass'!L20) -> 343.98 | L86: =IF('02 Glass'!$C$20="","",'02 Glass'!M20) -> Indicative | M86: =IF(D86="","",IF(AND(OR(Search!$C$6="All Categories",A86=Search!$C$6),OR(Search!$P$5="",ISNUMBER(SEARCH(" "&Search!$P$5,N86))),OR(Search!$P$6="",ISNUMBER(SEARCH(" "&Search!$P$6,N86))),OR(Search!$P$7="",ISNUMBER(SEARCH(" "&Search!$P$7,N86))),OR(Search!$P$8="",ISNUMBER(SEARCH(" "&Search!$P$8,N86))),OR(Search!$P$9="",ISNUMBER(SEARCH(" "&Search!$P$9,N86))),OR(Search!$P$10="",ISNUMBER(SEARCH(" "&Search!$P$10,N86)))),ROW(),"")) | N86: =IF(D86="",""," "&SUBSTITUTE(SUBSTITUTE(SUBSTITUTE(SUBSTITUTE(SUBSTITUTE(SUBSTITUTE(SUBSTITUTE(B86&" "&C86&" "&D86&" "&E86&" "&F86&" "&G86&" "&H86&" "&'02 Glass'!R20,"("," "),")"," "),"/"," "),"-"," "),","," "),";"," "),":"," ")&" ") -> GL 016 Tempered Low iron extra clear tempered glass 12 mm Ultra clear Local processor m2 12mm toughened extra clear ultra stainless steel
A87: =IF('02 Glass'!$C$21="","","Glass - Float, Tempered, Laminated & DGU") -> Glass - Float, Tempered, Laminated & DGU | B87: =IF('02 Glass'!$C$21="","",'02 Glass'!A21) -> GL-017 | C87: =IF('02 Glass'!$C$21="","",'02 Glass'!B21) -> Tempered | D87: =IF('02 Glass'!$C$21="","",'02 Glass'!C21) -> Frosted / acid-etched tempered glass | E87: =IF('02 Glass'!$C$21="","",'02 Glass'!D21) -> 10 mm | F87: =IF('02 Glass'!$C$21="","",'02 Glass'!E21) -> Satin | G87: =IF('02 Glass'!$C$21="","",'02 Glass'!F21) -> Local processor | H87: =IF('02 Glass'!$C$21="","",'02 Glass'!G21) -> m2 | I87: =IF('02 Glass'!$C$21="","",'02 Glass'!J21) -> 178.5 | J87: =IF('02 Glass'!$C$21="","",'02 Glass'!K21) -> 214.2 | K87: =IF('02 Glass'!$C$21="","",'02 Glass'!L21) -> 224.91 | L87: =IF('02 Glass'!$C$21="","",'02 Glass'!M21) -> Indicative | M87: =IF(D87="","",IF(AND(OR(Search!$C$6="All Categories",A87=Search!$C$6),OR(Search!$P$5="",ISNUMBER(SEARCH(" "&Search!$P$5,N87))),OR(Search!$P$6="",ISNUMBER(SEARCH(" "&Search!$P$6,N87))),OR(Search!$P$7="",ISNUMBER(SEARCH(" "&Search!$P$7,N87))),OR(Search!$P$8="",ISNUMBER(SEARCH(" "&Search!$P$8,N87))),OR(Search!$P$9="",ISNUMBER(SEARCH(" "&Search!$P$9,N87))),OR(Search!$P$10="",ISNUMBER(SEARCH(" "&Search!$P$10,N87)))),ROW(),"")) | N87: =IF(D87="",""," "&SUBSTITUTE(SUBSTITUTE(SUBSTITUTE(SUBSTITUTE(SUBSTITUTE(SUBSTITUTE(SUBSTITUTE(B87&" "&C87&" "&D87&" "&E87&" "&F87&" "&G87&" "&H87&" "&'02 Glass'!R21,"("," "),")"," "),"/"," "),"-"," "),","," "),";"," "),":"," ")&" ") -> GL 017 Tempered Frosted acid etched tempered glass 10 mm Satin Local processor m2 10mm toughened sandblast frosted stainless steel
A88: =IF('02 Glass'!$C$22="","","Glass - Float, Tempered, Laminated & DGU") -> Glass - Float, Tempered, Laminated & DGU | B88: =IF('02 Glass'!$C$22="","",'02 Glass'!A22) -> GL-018 | C88: =IF('02 Glass'!$C$22="","",'02 Glass'!B22) -> Tempered | D88: =IF('02 Glass'!$C$22="","",'02 Glass'!C22) -> Frosted / acid-etched tempered glass | E88: =IF('02 Glass'!$C$22="","",'02 Glass'!D22) -> 12 mm | F88: =IF('02 Glass'!$C$22="","",'02 Glass'!E22) -> Satin | G88: =IF('02 Glass'!$C$22="","",'02 Glass'!F22) -> Local processor | H88: =IF('02 Glass'!$C$22="","",'02 Glass'!G22) -> m2 | I88: =IF('02 Glass'!$C$22="","",'02 Glass'!J22) -> 215.25 | J88: =IF('02 Glass'!$C$22="","",'02 Glass'!K22) -> 258.3 | K88: =IF('02 Glass'!$C$22="","",'02 Glass'!L22) -> 271.22 | L88: =IF('02 Glass'!$C$22="","",'02 Glass'!M22) -> Indicative | M88: =IF(D88="","",IF(AND(OR(Search!$C$6="All Categories",A88=Search!$C$6),OR(Search!$P$5="",ISNUMBER(SEARCH(" "&Search!$P$5,N88))),OR(Search!$P$6="",ISNUMBER(SEARCH(" "&Search!$P$6,N88))),OR(Search!$P$7="",ISNUMBER(SEARCH(" "&Search!$P$7,N88))),OR(Search!$P$8="",ISNUMBER(SEARCH(" "&Search!$P$8,N88))),OR(Search!$P$9="",ISNUMBER(SEARCH(" "&Search!$P$9,N88))),OR(Search!$P$10="",ISNUMBER(SEARCH(" "&Search!$P$10,N88)))),ROW(),"")) | N88: =IF(D88="",""," "&SUBSTITUTE(SUBSTITUTE(SUBSTITUTE(SUBSTITUTE(SUBSTITUTE(SUBSTITUTE(SUBSTITUTE(B88&" "&C88&" "&D88&" "&E88&" "&F88&" "&G88&" "&H88&" "&'02 Glass'!R22,"("," "),")"," "),"/"," "),"-"," "),","," "),";"," "),":"," ")&" ") -> GL 018 Tempered Frosted acid etched tempered glass 12 mm Satin Local processor m2 12mm toughened sandblast frosted stainless steel
A89: =IF('02 Glass'!$C$23="","","Glass - Float, Tempered, Laminated & DGU") -> Glass - Float, Tempered, Laminated & DGU | B89: =IF('02 Glass'!$C$23="","",'02 Glass'!A23) -> GL-019 | C89: =IF('02 Glass'!$C$23="","",'02 Glass'!B23) -> Tempered | D89: =IF('02 Glass'!$C$23="","",'02 Glass'!C23) -> Fluted / reeded tempered glass | E89: =IF('02 Glass'!$C$23="","",'02 Glass'!D23) -> 8 mm | F89: =IF('02 Glass'!$C$23="","",'02 Glass'!E23) -> Fluted | G89: =IF('02 Glass'!$C$23="","",'02 Glass'!F23) -> Imported | H89: =IF('02 Glass'!$C$23="","",'02 Glass'!G23) -> m2 | I89: =IF('02 Glass'!$C$23="","",'02 Glass'!J23) -> 241.5 | J89: =IF('02 Glass'!$C$23="","",'02 Glass'!K23) -> 289.8 | K89: =IF('02 Glass'!$C$23="","",'02 Glass'!L23) -> 304.29 | L89: =IF('02 Glass'!$C$23="","",'02 Glass'!M23) -> Indicative | M89: =IF(D89="","",IF(AND(OR(Search!$C$6="All Categories",A89=Search!$C$6),OR(Search!$P$5="",ISNUMBER(SEARCH(" "&Search!$P$5,N89))),OR(Search!$P$6="",ISNUMBER(SEARCH(" "&Search!$P$6,N89))),OR(Search!$P$7="",ISNUMBER(SEARCH(" "&Search!$P$7,N89))),OR(Search!$P$8="",ISNUMBER(SEARCH(" "&Search!$P$8,N89))),OR(Search!$P$9="",ISNUMBER(SEARCH(" "&Search!$P$9,N89))),OR(Search!$P$10="",ISNUMBER(SEARCH(" "&Search!$P$10,N89)))),ROW(),"")) | N89: =IF(D89="",""," "&SUBSTITUTE(SUBSTITUTE(SUBSTITUTE(SUBSTITUTE(SUBSTITUTE(SUBSTITUTE(SUBSTITUTE(B89&" "&C89&" "&D89&" "&E89&" "&F89&" "&G89&" "&H89&" "&'02 Glass'!R23,"("," "),")"," "),"/"," "),"-"," "),","," "),";"," "),":"," ")&" ") -> GL 019 Tempered Fluted reeded tempered glass 8 mm Fluted Imported m2 8mm toughened stainless steel
A90: =IF('02 Glass'!$C$24="","","Glass - Float, Tempered, Laminated & DGU") -> Glass - Float, Tempered, Laminated & DGU | B90: =IF('02 Glass'!$C$24="","",'02 Glass'!A24) -> GL-020 | C90: =IF('02 Glass'!$C$24="","",'02 Glass'!B24) -> Tempered | D90: =IF('02 Glass'!$C$24="","",'02 Glass'!C24) -> Heat-soak test (HST) - extra | E90: =IF('02 Glass'!$C$24="","",'02 Glass'!D24) -> Any thickness | F90: =IF('02 Glass'!$C$24="","",'02 Glass'!E24) -> - | G90: =IF('02 Glass'!$C$24="","",'02 Glass'!F24) -> Local processor | H90: =IF('02 Glass'!$C$24="","",'02 Glass'!G24) -> m2 | I90: =IF('02 Glass'!$C$24="","",'02 Glass'!J24) -> 26.25 | J90: =IF('02 Glass'!$C$24="","",'02 Glass'!K24) -> 31.5 | K90: =IF('02 Glass'!$C$24="","",'02 Glass'!L24) -> 33.08 | L90: =IF('02 Glass'!$C$24="","",'02 Glass'!M24) -> Indicative | M90: =IF(D90="","",IF(AND(OR(Search!$C$6="All Categories",A90=Search!$C$6),OR(Search!$P$5="",ISNUMBER(SEARCH(" "&Search!$P$5,N90))),OR(Search!$P$6="",ISNUMBER(SEARCH(" "&Search!$P$6,N90))),OR(Search!$P$7="",ISNUMBER(SEARCH(" "&Search!$P$7,N90))),OR(Search!$P$8="",ISNUMBER(SEARCH(" "&Search!$P$8,N90))),OR(Search!$P$9="",ISNUMBER(SEARCH(" "&Search!$P$9,N90))),OR(Search!$P$10="",ISNUMBER(SEARCH(" "&Search!$P$10,N90)))),ROW(),"")) | N90: =IF(D90="",""," "&SUBSTITUTE(SUBSTITUTE(SUBSTITUTE(SUBSTITUTE(SUBSTITUTE(SUBSTITUTE(SUBSTITUTE(B90&" "&C90&" "&D90&" "&E90&" "&F90&" "&G90&" "&H90&" "&'02 Glass'!R24,"("," "),")"," "),"/"," "),"-"," "),","," "),";"," "),":"," ")&" ") -> GL 020 Tempered Heat soak test HST extra Any thickness Local processor m2 toughened stainless steel
A91: =IF('02 Glass'!$C$25="","","Glass - Float, Tempered, Laminated & DGU") -> Glass - Float, Tempered, Laminated & DGU | B91: =IF('02 Glass'!$C$25="","",'02 Glass'!A25) -> GL-021 | C91: =IF('02 Glass'!$C$25="","",'02 Glass'!B25) -> Tempered | D91: =IF('02 Glass'!$C$25="","",'02 Glass'!C25) -> Heat-strengthened glass - extra over tempered | E91: =IF('02 Glass'!$C$25="","",'02 Glass'!D25) -> Any thickness | F91: =IF('02 Glass'!$C$25="","",'02 Glass'!E25) -> - | G91: =IF('02 Glass'!$C$25="","",'02 Glass'!F25) -> Local processor | H91: =IF('02 Glass'!$C$25="","",'02 Glass'!G25) -> m2 | I91: =IF('02 Glass'!$C$25="","",'02 Glass'!J25) -> 15.75 | J91: =IF('02 Glass'!$C$25="","",'02 Glass'!K25) -> 18.9 | K91: =IF('02 Glass'!$C$25="","",'02 Glass'!L25) -> 19.85 | L91: =IF('02 Glass'!$C$25="","",'02 Glass'!M25) -> Indicative | M91: =IF(D91="","",IF(AND(OR(Search!$C$6="All Categories",A91=Search!$C$6),OR(Search!$P$5="",ISNUMBER(SEARCH(" "&Search!$P$5,N91))),OR(Search!$P$6="",ISNUMBER(SEARCH(" "&Search!$P$6,N91))),OR(Search!$P$7="",ISNUMBER(SEARCH(" "&Search!$P$7,N91))),OR(Search!$P$8="",ISNUMBER(SEARCH(" "&Search!$P$8,N91))),OR(Search!$P$9="",ISNUMBER(SEARCH(" "&Search!$P$9,N91))),OR(Search!$P$10="",ISNUMBER(SEARCH(" "&Search!$P$10,N91)))),ROW(),"")) | N91: =IF(D91="",""," "&SUBSTITUTE(SUBSTITUTE(SUBSTITUTE(SUBSTITUTE(SUBSTITUTE(SUBSTITUTE(SUBSTITUTE(B91&" "&C91&" "&D91&" "&E91&" "&F91&" "&G91&" "&H91&" "&'02 Glass'!R25,"("," "),")"," "),"/"," "),"-"," "),","," "),";"," "),":"," ")&" ") -> GL 021 Tempered Heat strengthened glass extra over tempered Any thickness Local processor m2 toughened stainless steel
A92: =IF('02 Glass'!$C$26="","","Glass - Float, Tempered, Laminated & DGU") -> Glass - Float, Tempered, Laminated & DGU | B92: =IF('02 Glass'!$C$26="","",'02 Glass'!A26) -> GL-022 | C92: =IF('02 Glass'!$C$26="","",'02 Glass'!B26) -> Laminated | D92: =IF('02 Glass'!$C$26="","",'02 Glass'!C26) -> Clear laminated glass | E92: =IF('02 Glass'!$C$26="","",'02 Glass'!D26) -> 6.38 mm (3+0.38 PVB+3) | F92: =IF('02 Glass'!$C$26="","",'02 Glass'!E26) -> Clear | G92: =IF('02 Glass'!$C$26="","",'02 Glass'!F26) -> Local processor | H92: =IF('02 Glass'!$C$26="","",'02 Glass'!G26) -> m2 | I92: =IF('02 Glass'!$C$26="","",'02 Glass'!J26) -> 99.75 | J92: =IF('02 Glass'!$C$26="","",'02 Glass'!K26) -> 119.7 | K92: =IF('02 Glass'!$C$26="","",'02 Glass'!L26) -> 125.69 | L92: =IF('02 Glass'!$C$26="","",'02 Glass'!M26) -> Indicative | M92: =IF(D92="","",IF(AND(OR(Search!$C$6="All Categories",A92=Search!$C$6),OR(Search!$P$5="",ISNUMBER(SEARCH(" "&Search!$P$5,N92))),OR(Search!$P$6="",ISNUMBER(SEARCH(" "&Search!$P$6,N92))),OR(Search!$P$7="",ISNUMBER(SEARCH(" "&Search!$P$7,N92))),OR(Search!$P$8="",ISNUMBER(SEARCH(" "&Search!$P$8,N92))),OR(Search!$P$9="",ISNUMBER(SEARCH(" "&Search!$P$9,N92))),OR(Search!$P$10="",ISNUMBER(SEARCH(" "&Search!$P$10,N92)))),ROW(),"")) | N92: =IF(D92="",""," "&SUBSTITUTE(SUBSTITUTE(SUBSTITUTE(SUBSTITUTE(SUBSTITUTE(SUBSTITUTE(SUBSTITUTE(B92&" "&C92&" "&D92&" "&E92&" "&F92&" "&G92&" "&H92&" "&'02 Glass'!R26,"("," "),")"," "),"/"," "),"-"," "),","," "),";"," "),":"," ")&" ") -> GL 022 Laminated Clear laminated glass 6.38 mm 3+0.38 PVB+3 Clear Local processor m2 6.38mm 3+0.38 lami stainless steel
A93: =IF('02 Glass'!$C$27="","","Glass - Float, Tempered, Laminated & DGU") -> Glass - Float, Tempered, Laminated & DGU | B93: =IF('02 Glass'!$C$27="","",'02 Glass'!A27) -> GL-023 | C93: =IF('02 Glass'!$C$27="","",'02 Glass'!B27) -> Laminated | D93: =IF('02 Glass'!$C$27="","",'02 Glass'!C27) -> Clear laminated glass | E93: =IF('02 Glass'!$C$27="","",'02 Glass'!D27) -> 8.76 mm (4+0.76+4) | F93: =IF('02 Glass'!$C$27="","",'02 Glass'!E27) -> Clear | G93: =IF('02 Glass'!$C$27="","",'02 Glass'!F27) -> Local processor | H93: =IF('02 Glass'!$C$27="","",'02 Glass'!G27) -> m2 | I93: =IF('02 Glass'!$C$27="","",'02 Glass'!J27) -> 131.25 | J93: =IF('02 Glass'!$C$27="","",'02 Glass'!K27) -> 157.5 | K93: =IF('02 Glass'!$C$27="","",'02 Glass'!L27) -> 165.38 | L93: =IF('02 Glass'!$C$27="","",'02 Glass'!M27) -> Indicative | M93: =IF(D93="","",IF(AND(OR(Search!$C$6="All Categories",A93=Search!$C$6),OR(Search!$P$5="",ISNUMBER(SEARCH(" "&Search!$P$5,N93))),OR(Search!$P$6="",ISNUMBER(SEARCH(" "&Search!$P$6,N93))),OR(Search!$P$7="",ISNUMBER(SEARCH(" "&Search!$P$7,N93))),OR(Search!$P$8="",ISNUMBER(SEARCH(" "&Search!$P$8,N93))),OR(Search!$P$9="",ISNUMBER(SEARCH(" "&Search!$P$9,N93))),OR(Search!$P$10="",ISNUMBER(SEARCH(" "&Search!$P$10,N93)))),ROW(),"")) | N93: =IF(D93="",""," "&SUBSTITUTE(SUBSTITUTE(SUBSTITUTE(SUBSTITUTE(SUBSTITUTE(SUBSTITUTE(SUBSTITUTE(B93&" "&C93&" "&D93&" "&E93&" "&F93&" "&G93&" "&H93&" "&'02 Glass'!R27,"("," "),")"," "),"/"," "),"-"," "),","," "),";"," "),":"," ")&" ") -> GL 023 Laminated Clear laminated glass 8.76 mm 4+0.76+4 Clear Local processor m2 8.76mm 4+0.76+4 lami stainless steel
A94: =IF('02 Glass'!$C$28="","","Glass - Float, Tempered, Laminated & DGU") -> Glass - Float, Tempered, Laminated & DGU | B94: =IF('02 Glass'!$C$28="","",'02 Glass'!A28) -> GL-024 | C94: =IF('02 Glass'!$C$28="","",'02 Glass'!B28) -> Laminated | D94: =IF('02 Glass'!$C$28="","",'02 Glass'!C28) -> Clear laminated glass | E94: =IF('02 Glass'!$C$28="","",'02 Glass'!D28) -> 10.76 mm (5+0.76+5) | F94: =IF('02 Glass'!$C$28="","",'02 Glass'!E28) -> Clear | G94: =IF('02 Glass'!$C$28="","",'02 Glass'!F28) -> Local processor | H94: =IF('02 Glass'!$C$28="","",'02 Glass'!G28) -> m2 | I94: =IF('02 Glass'!$C$28="","",'02 Glass'!J28) -> 157.5 | J94: =IF('02 Glass'!$C$28="","",'02 Glass'!K28) -> 189 | K94: =IF('02 Glass'!$C$28="","",'02 Glass'!L28) -> 198.45 | L94: =IF('02 Glass'!$C$28="","",'02 Glass'!M28) -> Indicative | M94: =IF(D94="","",IF(AND(OR(Search!$C$6="All Categories",A94=Search!$C$6),OR(Search!$P$5="",ISNUMBER(SEARCH(" "&Search!$P$5,N94))),OR(Search!$P$6="",ISNUMBER(SEARCH(" "&Search!$P$6,N94))),OR(Search!$P$7="",ISNUMBER(SEARCH(" "&Search!$P$7,N94))),OR(Search!$P$8="",ISNUMBER(SEARCH(" "&Search!$P$8,N94))),OR(Search!$P$9="",ISNUMBER(SEARCH(" "&Search!$P$9,N94))),OR(Search!$P$10="",ISNUMBER(SEARCH(" "&Search!$P$10,N94)))),ROW(),"")) | N94: =IF(D94="",""," "&SUBSTITUTE(SUBSTITUTE(SUBSTITUTE(SUBSTITUTE(SUBSTITUTE(SUBSTITUTE(SUBSTITUTE(B94&" "&C94&" "&D94&" "&E94&" "&F94&" "&G94&" "&H94&" "&'02 Glass'!R28,"("," "),")"," "),"/"," "),"-"," "),","," "),";"," "),":"," ")&" ") -> GL 024 Laminated Clear laminated glass 10.76 mm 5+0.76+5 Clear Local processor m2 10.76mm 5+0.76+5 lami stainless steel
A95: =IF('02 Glass'!$C$29="","","Glass - Float, Tempered, Laminated & DGU") -> Glass - Float, Tempered, Laminated & DGU | B95: =IF('02 Glass'!$C$29="","",'02 Glass'!A29) -> GL-025 | C95: =IF('02 Glass'!$C$29="","",'02 Glass'!B29) -> Laminated | D95: =IF('02 Glass'!$C$29="","",'02 Glass'!C29) -> Clear laminated glass | E95: =IF('02 Glass'!$C$29="","",'02 Glass'!D29) -> 12.76 mm (6+0.76+6) | F95: =IF('02 Glass'!$C$29="","",'02 Glass'!E29) -> Clear | G95: =IF('02 Glass'!$C$29="","",'02 Glass'!F29) -> Local processor | H95: =IF('02 Glass'!$C$29="","",'02 Glass'!G29) -> m2 | I95: =IF('02 Glass'!$C$29="","",'02 Glass'!J29) -> 183.75 | J95: =IF('02 Glass'!$C$29="","",'02 Glass'!K29) -> 220.5 | K95: =IF('02 Glass'!$C$29="","",'02 Glass'!L29) -> 231.53 | L95: =IF('02 Glass'!$C$29="","",'02 Glass'!M29) -> Indicative | M95: =IF(D95="","",IF(AND(OR(Search!$C$6="All Categories",A95=Search!$C$6),OR(Search!$P$5="",ISNUMBER(SEARCH(" "&Search!$P$5,N95))),OR(Search!$P$6="",ISNUMBER(SEARCH(" "&Search!$P$6,N95))),OR(Search!$P$7="",ISNUMBER(SEARCH(" "&Search!$P$7,N95))),OR(Search!$P$8="",ISNUMBER(SEARCH(" "&Search!$P$8,N95))),OR(Search!$P$9="",ISNUMBER(SEARCH(" "&Search!$P$9,N95))),OR(Search!$P$10="",ISNUMBER(SEARCH(" "&Search!$P$10,N95)))),ROW(),"")) | N95: =IF(D95="",""," "&SUBSTITUTE(SUBSTITUTE(SUBSTITUTE(SUBSTITUTE(SUBSTITUTE(SUBSTITUTE(SUBSTITUTE(B95&" "&C95&" "&D95&" "&E95&" "&F95&" "&G95&" "&H95&" "&'02 Glass'!R29,"("," "),")"," "),"/"," "),"-"," "),","," "),";"," "),":"," ")&" ") -> GL 025 Laminated Clear laminated glass 12.76 mm 6+0.76+6 Clear Local processor m2 12.76mm 6+0.76+6 lami stainless steel
A96: =IF('02 Glass'!$C$30="","","Glass - Float, Tempered, Laminated & DGU") -> Glass - Float, Tempered, Laminated & DGU | B96: =IF('02 Glass'!$C$30="","",'02 Glass'!A30) -> GL-026 | C96: =IF('02 Glass'!$C$30="","",'02 Glass'!B30) -> Laminated | D96: =IF('02 Glass'!$C$30="","",'02 Glass'!C30) -> Tempered laminated glass | E96: =IF('02 Glass'!$C$30="","",'02 Glass'!D30) -> 12.76 mm (6T+0.76 PVB+6T) | F96: =IF('02 Glass'!$C$30="","",'02 Glass'!E30) -> Clear | G96: =IF('02 Glass'!$C$30="","",'02 Glass'!F30) -> Local processor | H96: =IF('02 Glass'!$C$30="","",'02 Glass'!G30) -> m2 | I96: =IF('02 Glass'!$C$30="","",'02 Glass'!J30) -> 273 | J96: =IF('02 Glass'!$C$30="","",'02 Glass'!K30) -> 327.6 | K96: =IF('02 Glass'!$C$30="","",'02 Glass'!L30) -> 343.98 | L96: =IF('02 Glass'!$C$30="","",'02 Glass'!M30) -> Indicative | M96: =IF(D96="","",IF(AND(OR(Search!$C$6="All Categories",A96=Search!$C$6),OR(Search!$P$5="",ISNUMBER(SEARCH(" "&Search!$P$5,N96))),OR(Search!$P$6="",ISNUMBER(SEARCH(" "&Search!$P$6,N96))),OR(Search!$P$7="",ISNUMBER(SEARCH(" "&Search!$P$7,N96))),OR(Search!$P$8="",ISNUMBER(SEARCH(" "&Search!$P$8,N96))),OR(Search!$P$9="",ISNUMBER(SEARCH(" "&Search!$P$9,N96))),OR(Search!$P$10="",ISNUMBER(SEARCH(" "&Search!$P$10,N96)))),ROW(),"")) | N96: =IF(D96="",""," "&SUBSTITUTE(SUBSTITUTE(SUBSTITUTE(SUBSTITUTE(SUBSTITUTE(SUBSTITUTE(SUBSTITUTE(B96&" "&C96&" "&D96&" "&E96&" "&F96&" "&G96&" "&H96&" "&'02 Glass'!R30,"("," "),")"," "),"/"," "),"-"," "),","," "),";"," "),":"," ")&" ") -> GL 026 Laminated Tempered laminated glass 12.76 mm 6T+0.76 PVB+6T Clear Local processor m2 12.76mm toughened lami stainless steel
A97: =IF('02 Glass'!$C$31="","","Glass - Float, Tempered, Laminated & DGU") -> Glass - Float, Tempered, Laminated & DGU | B97: =IF('02 Glass'!$C$31="","",'02 Glass'!A31) -> GL-027 | C97: =IF('02 Glass'!$C$31="","",'02 Glass'!B31) -> Laminated | D97: =IF('02 Glass'!$C$31="","",'02 Glass'!C31) -> Tempered laminated glass | E97: =IF('02 Glass'!$C$31="","",'02 Glass'!D31) -> 17.52 mm (8T+1.52 PVB+8T) | F97: =IF('02 Glass'!$C$31="","",'02 Glass'!E31) -> Clear | G97: =IF('02 Glass'!$C$31="","",'02 Glass'!F31) -> Local processor | H97: =IF('02 Glass'!$C$31="","",'02 Glass'!G31) -> m2 | I97: =IF('02 Glass'!$C$31="","",'02 Glass'!J31) -> 378 | J97: =IF('02 Glass'!$C$31="","",'02 Glass'!K31) -> 453.6 | K97: =IF('02 Glass'!$C$31="","",'02 Glass'!L31) -> 476.28 | L97: =IF('02 Glass'!$C$31="","",'02 Glass'!M31) -> Indicative | M97: =IF(D97="","",IF(AND(OR(Search!$C$6="All Categories",A97=Search!$C$6),OR(Search!$P$5="",ISNUMBER(SEARCH(" "&Search!$P$5,N97))),OR(Search!$P$6="",ISNUMBER(SEARCH(" "&Search!$P$6,N97))),OR(Search!$P$7="",ISNUMBER(SEARCH(" "&Search!$P$7,N97))),OR(Search!$P$8="",ISNUMBER(SEARCH(" "&Search!$P$8,N97))),OR(Search!$P$9="",ISNUMBER(SEARCH(" "&Search!$P$9,N97))),OR(Search!$P$10="",ISNUMBER(SEARCH(" "&Search!$P$10,N97)))),ROW(),"")) | N97: =IF(D97="",""," "&SUBSTITUTE(SUBSTITUTE(SUBSTITUTE(SUBSTITUTE(SUBSTITUTE(SUBSTITUTE(SUBSTITUTE(B97&" "&C97&" "&D97&" "&E97&" "&F97&" "&G97&" "&H97&" "&'02 Glass'!R31,"("," "),")"," "),"/"," "),"-"," "),","," "),";"," "),":"," ")&" ") -> GL 027 Laminated Tempered laminated glass 17.52 mm 8T+1.52 PVB+8T Clear Local processor m2 17.52mm toughened lami stainless steel
A98: =IF('02 Glass'!$C$32="","","Glass - Float, Tempered, Laminated & DGU") -> Glass - Float, Tempered, Laminated & DGU | B98: =IF('02 Glass'!$C$32="","",'02 Glass'!A32) -> GL-028 | C98: =IF('02 Glass'!$C$32="","",'02 Glass'!B32) -> Laminated | D98: =IF('02 Glass'!$C$32="","",'02 Glass'!C32) -> Tempered laminated glass | E98: =IF('02 Glass'!$C$32="","",'02 Glass'!D32) -> 21.52 mm (10T+1.52 PVB+10T) | F98: =IF('02 Glass'!$C$32="","",'02 Glass'!E32) -> Clear | G98: =IF('02 Glass'!$C$32="","",'02 Glass'!F32) -> Local processor | H98: =IF('02 Glass'!$C$32="","",'02 Glass'!G32) -> m2 | I98: =IF('02 Glass'!$C$32="","",'02 Glass'!J32) -> 472.5 | J98: =IF('02 Glass'!$C$32="","",'02 Glass'!K32) -> 567 | K98: =IF('02 Glass'!$C$32="","",'02 Glass'!L32) -> 595.35 | L98: =IF('02 Glass'!$C$32="","",'02 Glass'!M32) -> Indicative | M98: =IF(D98="","",IF(AND(OR(Search!$C$6="All Categories",A98=Search!$C$6),OR(Search!$P$5="",ISNUMBER(SEARCH(" "&Search!$P$5,N98))),OR(Search!$P$6="",ISNUMBER(SEARCH(" "&Search!$P$6,N98))),OR(Search!$P$7="",ISNUMBER(SEARCH(" "&Search!$P$7,N98))),OR(Search!$P$8="",ISNUMBER(SEARCH(" "&Search!$P$8,N98))),OR(Search!$P$9="",ISNUMBER(SEARCH(" "&Search!$P$9,N98))),OR(Search!$P$10="",ISNUMBER(SEARCH(" "&Search!$P$10,N98)))),ROW(),"")) | N98: =IF(D98="",""," "&SUBSTITUTE(SUBSTITUTE(SUBSTITUTE(SUBSTITUTE(SUBSTITUTE(SUBSTITUTE(SUBSTITUTE(B98&" "&C98&" "&D98&" "&E98&" "&F98&" "&G98&" "&H98&" "&'02 Glass'!R32,"("," "),")"," "),"/"," "),"-"," "),","," "),";"," "),":"," ")&" ") -> GL 028 Laminated Tempered laminated glass 21.52 mm 10T+1.52 PVB+10T Clear Local processor m2 21.52mm toughened lami stainless steel
A99: =IF('02 Glass'!$C$33="","","Glass - Float, Tempered, Laminated & DGU") -> Glass - Float, Tempered, Laminated & DGU | B99: =IF('02 Glass'!$C$33="","",'02 Glass'!A33) -> GL-029 | C99: =IF('02 Glass'!$C$33="","",'02 Glass'!B33) -> Laminated | D99: =IF('02 Glass'!$C$33="","",'02 Glass'!C33) -> Tempered laminated glass - SGP interlayer | E99: =IF('02 Glass'!$C$33="","",'02 Glass'!D33) -> 21.52 mm (10T+1.52 SGP+10T) | F99: =IF('02 Glass'!$C$33="","",'02 Glass'!E33) -> Clear | G99: =IF('02 Glass'!$C$33="","",'02 Glass'!F33) -> Local processor | H99: =IF('02 Glass'!$C$33="","",'02 Glass'!G33) -> m2 | I99: =IF('02 Glass'!$C$33="","",'02 Glass'!J33) -> 682.5 | J99: =IF('02 Glass'!$C$33="","",'02 Glass'!K33) -> 819 | K99: =IF('02 Glass'!$C$33="","",'02 Glass'!L33) -> 859.95 | L99: =IF('02 Glass'!$C$33="","",'02 Glass'!M33) -> Indicative | M99: =IF(D99="","",IF(AND(OR(Search!$C$6="All Categories",A99=Search!$C$6),OR(Search!$P$5="",ISNUMBER(SEARCH(" "&Search!$P$5,N99))),OR(Search!$P$6="",ISNUMBER(SEARCH(" "&Search!$P$6,N99))),OR(Search!$P$7="",ISNUMBER(SEARCH(" "&Search!$P$7,N99))),OR(Search!$P$8="",ISNUMBER(SEARCH(" "&Search!$P$8,N99))),OR(Search!$P$9="",ISNUMBER(SEARCH(" "&Search!$P$9,N99))),OR(Search!$P$10="",ISNUMBER(SEARCH(" "&Search!$P$10,N99)))),ROW(),"")) | N99: =IF(D99="",""," "&SUBSTITUTE(SUBSTITUTE(SUBSTITUTE(SUBSTITUTE(SUBSTITUTE(SUBSTITUTE(SUBSTITUTE(B99&" "&C99&" "&D99&" "&E99&" "&F99&" "&G99&" "&H99&" "&'02 Glass'!R33,"("," "),")"," "),"/"," "),"-"," "),","," "),";"," "),":"," ")&" ") -> GL 029 Laminated Tempered laminated glass SGP interlayer 21.52 mm 10T+1.52 SGP+10T Clear Local processor m2 21.52mm toughened lami stainless steel
A100: =IF('02 Glass'!$C$34="","","Glass - Float, Tempered, Laminated & DGU") -> Glass - Float, Tempered, Laminated & DGU | B100: =IF('02 Glass'!$C$34="","",'02 Glass'!A34) -> GL-030 | C100: =IF('02 Glass'!$C$34="","",'02 Glass'!B34) -> Laminated | D100: =IF('02 Glass'!$C$34="","",'02 Glass'!C34) -> Laminated glass - frosted / milky PVB | E100: =IF('02 Glass'!$C$34="","",'02 Glass'!D34) -> 10.76 mm | F100: =IF('02 Glass'!$C$34="","",'02 Glass'!E34) -> Milky white | G100: =IF('02 Glass'!$C$34="","",'02 Glass'!F34) -> Local processor | H100: =IF('02 Glass'!$C$34="","",'02 Glass'!G34) -> m2 | I100: =IF('02 Glass'!$C$34="","",'02 Glass'!J34) -> 183.75 | J100: =IF('02 Glass'!$C$34="","",'02 Glass'!K34) -> 220.5 | K100: =IF('02 Glass'!$C$34="","",'02 Glass'!L34) -> 231.53 | L100: =IF('02 Glass'!$C$34="","",'02 Glass'!M34) -> Indicative | M100: =IF(D100="","",IF(AND(OR(Search!$C$6="All Categories",A100=Search!$C$6),OR(Search!$P$5="",ISNUMBER(SEARCH(" "&Search!$P$5,N100))),OR(Search!$P$6="",ISNUMBER(SEARCH(" "&Search!$P$6,N100))),OR(Search!$P$7="",ISNUMBER(SEARCH(" "&Search!$P$7,N100))),OR(Search!$P$8="",ISNUMBER(SEARCH(" "&Search!$P$8,N100))),OR(Search!$P$9="",ISNUMBER(SEARCH(" "&Search!$P$9,N100))),OR(Search!$P$10="",ISNUMBER(SEARCH(" "&Search!$P$10,N100)))),ROW(),"")) | N100: =IF(D100="",""," "&SUBSTITUTE(SUBSTITUTE(SUBSTITUTE(SUBSTITUTE(SUBSTITUTE(SUBSTITUTE(SUBSTITUTE(B100&" "&C100&" "&D100&" "&E100&" "&F100&" "&G100&" "&H100&" "&'02 Glass'!R34,"("," "),")"," "),"/"," "),"-"," "),","," "),";"," "),":"," ")&" ") -> GL 030 Laminated Laminated glass frosted milky PVB 10.76 mm Milky white Local processor m2 10.76mm lami sandblast stainless steel
...

Sheet Settings
B2: SETTINGS & BASE RATES
B3: Change the yellow cells - every linked rate in the workbook updates automatically.
B5: Parameter | C5: Value | D5: Unit | E5: Name (used in formulas) | F5: Note
B6: VAT (UAE) | C6: 0.05 | D6: % | E6: VAT | F6: Federal VAT rate
B7: Overhead & Profit (default) | C7: 0.2 | D7: % | E7: OHP | F7: Applied to Net Cost to get Selling Rate
B8: Aluminium extrusion - mill finish | C8: 15.5 | D8: AED/kg | E8: AL_MILL | F8: 6063-T5/T6, local extruder
B9: Add for powder coating | C9: 3 | D9: AED/kg | E9: AL_PC | F9: Qualicoat approved, standard RAL
B10: Add for anodizing | C10: 5 | D10: AED/kg | E10: AL_ANOD | F10: 15-20 micron
B11: Add for PVDF coating | C11: 8.5 | D11: AED/kg | E11: AL_PVDF | F11: 2/3-coat Kynar 500
B12: Add for wood-grain finish | C12: 6.5 | D12: AED/kg | E12: AL_WOOD | F12: Sublimation over powder coat
B13: Add for thermal-break (polyamide) | C13: 6 | D13: AED/kg | E13: AL_TB | F13: Crimped polyamide strips
B14: MS structural sections | C14: 3.6 | D14: AED/kg | E14: MS_KG | F14: SHS/RHS/angle/channel/beam, black
B15: MS plates & sheets | C15: 3.4 | D15: AED/kg | E15: MS_PLATE | F15: S275/S355, cut-to-size extra
B16: GI sheets / pre-galvanized | C16: 4.2 | D16: AED/kg | E16: GI_KG | F16: Z275
B17: SS 304 tubes / sheets (hairline) | C17: 17 | D17: AED/kg | E17: SS304 | F17: Grade 304, #4 hairline
... B19: Add for SS mirror finish (#8) | C19: 3 | D19: AED/kg | E19: SS_MIRROR | F19: Over hairline rate
B21: Rate validity / last reviewed | C21: 09-Oct-2026
B22: Currency | C22: AED
B24: Note: all base rates are INDICATIVE UAE market budget rates (Oct-2026) for estimation reference only. Confirm with current supplier quotations before final pricing.

Sheet 01 Aluminium
A1: 01. ALUMINIUM PROFILES & SYSTEMS
A2: Scope: Extrusions by kg, standard sections, window/door/curtain wall/pergola profiles
A3: =HYPERLINK("#Index!A1","<< Back to Index") -> << Back to Index | D3: Items: | E3: =COUNTA(C5:C72) -> 53 | H3: Blue = input | Black = formula | Yellow rows at bottom = spare for new items
A4: Item Code | B4: Sub-Category | C4: Item Description | D4: Specification / Size | E4: Finish / Colour | F4: Brand / Origin | G4: Unit | H4: Basic Rate (AED) | I4: Wastage % | J4: Net Cost Rate (AED) | K4: Selling Rate (AED, +O&P) | L4: Selling Rate incl. VAT (AED) | M4: Rate Status | N4: Supplier | O4: Quote Ref. | P4: Rate Date | Q4: Remarks | R4: Search Tags (extra keywords)
A5: AL-001 | B5: Extrusions (per kg) | C5: Aluminium extrusion | D5: Alloy 6063-T5/T6 | E5: Mill finish | F5: Gulf Extrusions / Equiv. | G5: kg | H5: =AL_MILL -> 15.5 | I5: 0.05 | J5: =IF(H5="","",ROUND(H5*(1+I5),2)) -> 16.28 | K5: =IF(J5="","",ROUND(J5*(1+OHP),2)) -> 19.54 | L5: =IF(K5="","",ROUND(K5*(1+VAT),2)) -> 20.52 | M5: Indicative | R5: aluminum alu
A6: AL-002 | B6: Extrusions (per kg) | C6: Aluminium extrusion | D6: Alloy 6063-T5/T6 | E6: Powder coated (RAL) | F6: Gulf Extrusions / Equiv. | G6: kg | H6: =AL_MILL+AL_PC -> 18.5 | I6: 0.05 | J6: =IF(H6="","",ROUND(H6*(1+I6),2)) -> 19.43 | K6: =IF(J6="","",ROUND(J6*(1+OHP),2)) -> 23.32 | L6: =IF(K6="","",ROUND(K6*(1+VAT),2)) -> 24.49 | M6: Indicative | R6: aluminum alu pc
A7: AL-003 | B7: Extrusions (per kg) | C7: Aluminium extrusion | D7: Alloy 6063-T5/T6 | E7: Anodized 15-20 micron | F7: Gulf Extrusions / Equiv. | G7: kg | H7: =AL_MILL+AL_ANOD -> 20.5 | I7: 0.05 | J7: =IF(H7="","",ROUND(H7*(1+I7),2)) -> 21.53 | K7: =IF(J7="","",ROUND(J7*(1+OHP),2)) -> 25.84 | L7: =IF(K7="","",ROUND(K7*(1+VAT),2)) -> 27.13 | M7: Indicative | R7: aluminum alu
A8: AL-004 | B8: Extrusions (per kg) | C8: Aluminium extrusion | D8: Alloy 6063-T5/T6 | E8: PVDF 2/3-coat | F8: Gulf Extrusions / Equiv. | G8: kg | H8: =AL_MILL+AL_PVDF -> 24 | I8: 0.05 | J8: =IF(H8="","",ROUND(H8*(1+I8),2)) -> 25.2 | K8: =IF(J8="","",ROUND(J8*(1+OHP),2)) -> 30.24 | L8: =IF(K8="","",ROUND(K8*(1+VAT),2)) -> 31.75 | M8: Indicative | R8: aluminum alu
A9: AL-005 | B9: Extrusions (per kg) | C9: Aluminium extrusion | D9: Alloy 6063-T5/T6 | E9: Wood-grain finish | F9: Gulf Extrusions / Equiv. | G9: kg | H9: =AL_MILL+AL_PC+AL_WOOD -> 25 | I9: 0.05 | J9: =IF(H9="","",ROUND(H9*(1+I9),2)) -> 26.25 | K9: =IF(J9="","",ROUND(J9*(1+OHP),2)) -> 31.5 | L9: =IF(K9="","",ROUND(K9*(1+VAT),2)) -> 33.08 | M9: Indicative | R9: aluminum alu
A10: AL-006 | B10: Extrusions (per kg) | C10: Thermal-break aluminium extrusion | D10: With polyamide strips | E10: Powder coated | F10: Gulf Extrusions / Equiv. | G10: kg | H10: =AL_MILL+AL_PC+AL_TB -> 24.5 | I10: 0.05 | J10: =IF(H10="","",ROUND(H10*(1+I10),2)) -> 25.73 | K10: =IF(J10="","",ROUND(J10*(1+OHP),2)) -> 30.88 | L10: =IF(K10="","",ROUND(K10*(1+VAT),2)) -> 32.42 | M10: Indicative | R10: aluminum alu pc
A11: AL-007 | B11: Standard Sections | C11: Aluminium square tube | D11: 25 x 25 x 1.5 mm (0.38 kg/m) | E11: Powder coated | F11: Local | G11: lm | H11: =ROUND(0.38*(AL_MILL+AL_PC),2) -> 7.03 | I11: 0.05 | J11: =IF(H11="","",ROUND(H11*(1+I11),2)) -> 7.38 | K11: =IF(J11="","",ROUND(J11*(1+OHP),2)) -> 8.86 | L11: =IF(K11="","",ROUND(K11*(1+VAT),2)) -> 9.3 | M11: Indicative | R11: 25x25 25x25x1.5 1.5mm pipe box aluminum alu pc
A12: AL-008 | B12: Standard Sections | C12: Aluminium square tube | D12: 40 x 40 x 2.0 mm (0.82 kg/m) | E12: Powder coated | F12: Local | G12: lm | H12: =ROUND(0.82*(AL_MILL+AL_PC),2) -> 15.17 | I12: 0.05 | J12: =IF(H12="","",ROUND(H12*(1+I12),2)) -> 15.93 | K12: =IF(J12="","",ROUND(J12*(1+OHP),2)) -> 19.12 | L12: =IF(K12="","",ROUND(K12*(1+VAT),2)) -> 20.08 | M12: Indicative | R12: 40x40 40x40x2.0 40x40x2 2.0mm pipe box aluminum alu pc
A13: AL-009 | B13: Standard Sections | C13: Aluminium square tube | D13: 50 x 50 x 2.0 mm (1.04 kg/m) | E13: Powder coated | F13: Local | G13: lm | H13: =ROUND(1.04*(AL_MILL+AL_PC),2) -> 19.24 | I13: 0.05 | J13: =IF(H13="","",ROUND(H13*(1+I13),2)) -> 20.2 | K13: =IF(J13="","",ROUND(J13*(1+OHP),2)) -> 24.24 | L13: =IF(K13="","",ROUND(K13*(1+VAT),2)) -> 25.45 | M13: Indicative | R13: 50x50 50x50x2.0 50x50x2 2.0mm pipe box aluminum alu pc
A14: AL-010 | B14: Standard Sections | C14: Aluminium rectangular tube | D14: 100 x 50 x 2.5 mm (1.96 kg/m) | E14: Powder coated | F14: Local | G14: lm | H14: =ROUND(1.96*(AL_MILL+AL_PC),2) -> 36.26 | I14: 0.05 | J14: =IF(H14="","",ROUND(H14*(1+I14),2)) -> 38.07 | K14: =IF(J14="","",ROUND(J14*(1+OHP),2)) -> 45.68 | L14: =IF(K14="","",ROUND(K14*(1+VAT),2)) -> 47.96 | M14: Indicative | R14: 100x50 100x50x2.5 2.5mm pipe box aluminum alu pc
A15: AL-011 | B15: Standard Sections | C15: Aluminium rectangular tube | D15: 100 x 50 x 3.0 mm (2.33 kg/m) | E15: Powder coated | F15: Local | G15: lm | H15: =ROUND(2.33*(AL_MILL+AL_PC),2) -> 43.11 | I15: 0.05 | J15: =IF(H15="","",ROUND(H15*(1+I15),2)) -> 45.27 | K15: =IF(J15="","",ROUND(J15*(1+OHP),2)) -> 54.32 | L15: =IF(K15="","",ROUND(K15*(1+VAT),2)) -> 57.04 | M15: Indicative | R15: 100x50 100x50x3.0 100x50x3 3.0mm pipe box aluminum alu pc
A16: AL-012 | B16: Standard Sections | C16: Aluminium rectangular tube | D16: 150 x 50 x 3.0 mm (3.14 kg/m) | E16: Powder coated | F16: Local | G16: lm | H16: =ROUND(3.14*(AL_MILL+AL_PC),2) -> 58.09 | I16: 0.05 | J16: =IF(H16="","",ROUND(H16*(1+I16),2)) -> 60.99 | K16: =IF(J16="","",ROUND(J16*(1+OHP),2)) -> 73.19 | L16: =IF(K16="","",ROUND(K16*(1+VAT),2)) -> 76.85 | M16: Indicative | R16: 150x50 150x50x3.0 150x50x3 3.0mm pipe box aluminum alu pc
A17: AL-013 | B17: Standard Sections | C17: Aluminium rectangular tube | D17: 200 x 50 x 3.0 mm (3.95 kg/m) | E17: Powder coated | F17: Local | G17: lm | H17: =ROUND(3.95*(AL_MILL+AL_PC),2) -> 73.08 | I17: 0.05 | J17: =IF(H17="","",ROUND(H17*(1+I17),2)) -> 76.73 | K17: =IF(J17="","",ROUND(J17*(1+OHP),2)) -> 92.08 | L17: =IF(K17="","",ROUND(K17*(1+VAT),2)) -> 96.68 | M17: Indicative | R17: 200x50 200x50x3.0 200x50x3 3.0mm pipe box aluminum alu pc
A18: AL-014 | B18: Standard Sections | C18: Aluminium equal angle | D18: 25 x 25 x 2.0 mm (0.26 kg/m) | E18: Powder coated | F18: Local | G18: lm | H18: =ROUND(0.26*(AL_MILL+AL_PC),2) -> 4.81 | I18: 0.05 | J18: =IF(H18="","",ROUND(H18*(1+I18),2)) -> 5.05 | K18: =IF(J18="","",ROUND(J18*(1+OHP),2)) -> 6.06 | L18: =IF(K18="","",ROUND(K18*(1+VAT),2)) -> 6.36 | M18: Indicative | R18: 25x25 25x25x2.0 25x25x2 2.0mm aluminum alu pc angle l
A19: AL-015 | B19: Standard Sections | C19: Aluminium equal angle | D19: 50 x 50 x 3.0 mm (0.79 kg/m) | E19: Powder coated | F19: Local | G19: lm | H19: =ROUND(0.79*(AL_MILL+AL_PC),2) -> 14.62 | I19: 0.05 | J19: =IF(H19="","",ROUND(H19*(1+I19),2)) -> 15.35 | K19: =IF(J19="","",ROUND(J19*(1+OHP),2)) -> 18.42 | L19: =IF(K19="","",ROUND(K19*(1+VAT),2)) -> 19.34 | M19: Indicative | R19: 50x50 50x50x3.0 50x50x3 3.0mm aluminum alu pc angle l
A20: AL-016 | B20: Standard Sections | C20: Aluminium flat bar | D20: 50 x 5 mm (0.68 kg/m) | E20: Powder coated | F20: Local | G20: lm | H20: =ROUND(0.68*(AL_MILL+AL_PC),2) -> 12.58 | I20: 0.05 | J20: =IF(H20="","",ROUND(H20*(1+I20),2)) -> 13.21 | K20: =IF(J20="","",ROUND(J20*(1+OHP),2)) -> 15.85 | L20: =IF(K20="","",ROUND(K20*(1+VAT),2)) -> 16.64 | M20: Indicative | R20: 50x5 5mm aluminum alu pc patti strip
A21: AL-017 | B21: Standard Sections | C21: Aluminium flat bar | D21: 100 x 6 mm (1.62 kg/m) | E21: Powder coated | F21: Local | G21: lm | H21: =ROUND(1.62*(AL_MILL+AL_PC),2) -> 29.97 | I21: 0.05 | J21: =IF(H21="","",ROUND(H21*(1+I21),2)) -> 31.47 | K21: =IF(J21="","",ROUND(J21*(1+OHP),2)) -> 37.76 | L21: =IF(K21="","",ROUND(K21*(1+VAT),2)) -> 39.65 | M21: Indicative | R21: 100x6 6mm aluminum alu pc patti strip
A22: AL-018 | B22: Standard Sections | C22: Aluminium U-channel for glass | D22: For 10-12 mm glass (0.45 kg/m) | E22: Powder coated / anodized | F22: Local | G22: lm | H22: =ROUND(0.45*(AL_MILL+AL_PC),2) -> 8.33 | I22: 0.05 | J22: =IF(H22="","",ROUND(H22*(1+I22),2)) -> 8.75 | K22: =IF(J22="","",ROUND(J22*(1+OHP),2)) -> 10.5 | L22: =IF(K22="","",ROUND(K22*(1+VAT),2)) -> 11.03 | M22: Indicative | R22: 12mm aluminum alu pc stainless steel
A23: AL-019 | B23: Standard Sections | C23: Aluminium heavy U-channel (frameless partition) | D23: 40 x 40 mm (0.90 kg/m) | E23: Anodized / PC | F23: Local | G23: lm | H23: =ROUND(0.9*(AL_MILL+AL_PC),2) -> 16.65 | I23: 0.05 | J23: =IF(H23="","",ROUND(H23*(1+I23),2)) -> 17.48 | K23: =IF(J23="","",ROUND(J23*(1+OHP),2)) -> 20.98 | L23: =IF(K23="","",ROUND(K23*(1+VAT),2)) -> 22.03 | M23: Indicative | R23: 40x40 40mm aluminum alu stainless steel
A24: AL-020 | B24: Sliding Window System | C24: Sliding window outer frame - 2 track | D24: Non-thermal (approx. 1.25 kg/m) | E24: Powder coated | F24: Gulf Extrusions / Equiv. | G24: lm | H24: =ROUND(1.25*(AL_MILL+AL_PC),2) -> 23.13 | I24: 0.05 | J24: =IF(H24="","",ROUND(H24*(1+I24),2)) -> 24.29 | K24: =IF(J24="","",ROUND(J24*(1+OHP),2)) -> 29.15 | L24: =IF(K24="","",ROUND(K24*(1+VAT),2)) -> 30.61 | M24: Indicative | R24: pc
A25: AL-021 | B25: Sliding Window System | C25: Sliding window outer frame - 3 track | D25: Non-thermal (approx. 1.75 kg/m) | E25: Powder coated | F25: Gulf Extrusions / Equiv. | G25: lm | H25: =ROUND(1.75*(AL_MILL+AL_PC),2) -> 32.38 | I25: 0.05 | J25: =IF(H25="","",ROUND(H25*(1+I25),2)) -> 34 | K25: =IF(J25="","",ROUND(J25*(1+OHP),2)) -> 40.8 | L25: =IF(K25="","",ROUND(K25*(1+VAT),2)) -> 42.84 | M25: Indicative | R25: pc
A26: AL-022 | B26: Sliding Window System | C26: Sliding sash profile | D26: Approx. 0.95 kg/m | E26: Powder coated | F26: Gulf Extrusions / Equiv. | G26: lm | H26: =ROUND(0.95*(AL_MILL+AL_PC),2) -> 17.58 | I26: 0.05 | J26: =IF(H26="","",ROUND(H26*(1+I26),2)) -> 18.46 | K26: =IF(J26="","",ROUND(J26*(1+OHP),2)) -> 22.15 | L26: =IF(K26="","",ROUND(K26*(1+VAT),2)) -> 23.26 | M26: Indicative | R26: pc
A27: AL-023 | B27: Sliding Window System | C27: Sliding interlock profile | D27: Approx. 0.75 kg/m | E27: Powder coated | F27: Gulf Extrusions / Equiv. | G27: lm | H27: =ROUND(0.75*(AL_MILL+AL_PC),2) -> 13.88 | I27: 0.05 | J27: =IF(H27="","",ROUND(H27*(1+I27),2)) -> 14.57 | K27: =IF(J27="","",ROUND(J27*(1+OHP),2)) -> 17.48 | L27: =IF(K27="","",ROUND(K27*(1+VAT),2)) -> 18.35 | M27: Indicative | R27: pc
A28: AL-024 | B28: Sliding Window System | C28: Thermal-break sliding frame | D28: Approx. 2.40 kg/m | E28: Powder coated | F28: Gulf Extrusions / Equiv. | G28: lm | H28: =ROUND(2.4*(AL_MILL+AL_PC+AL_TB),2) -> 58.8 | I28: 0.05 | J28: =IF(H28="","",ROUND(H28*(1+I28),2)) -> 61.74 | K28: =IF(J28="","",ROUND(J28*(1+OHP),2)) -> 74.09 | L28: =IF(K28="","",ROUND(K28*(1+VAT),2)) -> 77.79 | M28: Indicative | R28: pc
A29: AL-025 | B29: Sliding Window System | C29: Lift & slide door frame (TB) | D29: Approx. 3.80 kg/m | E29: Powder coated | F29: Gulf Extrusions / Equiv. | G29: lm | H29: =ROUND(3.8*(AL_MILL+AL_PC+AL_TB),2) -> 93.1 | I29: 0.05 | J29: =IF(H29="","",ROUND(H29*(1+I29),2)) -> 97.76 | K29: =IF(J29="","",ROUND(J29*(1+OHP),2)) -> 117.31 | L29: =IF(K29="","",ROUND(K29*(1+VAT),2)) -> 123.18 | M29: Indicative | R29: pc
A30: AL-026 | B30: Casement / Hinged System | C30: Casement window frame | D30: Approx. 0.95 kg/m | E30: Powder coated | F30: Gulf Extrusions / Equiv. | G30: lm | H30: =ROUND(0.95*(AL_MILL+AL_PC),2) -> 17.58 | I30: 0.05 | J30: =IF(H30="","",ROUND(H30*(1+I30),2)) -> 18.46 | K30: =IF(J30="","",ROUND(J30*(1+OHP),2)) -> 22.15 | L30: =IF(K30="","",ROUND(K30*(1+VAT),2)) -> 23.26 | M30: Indicative | R30: pc
A31: AL-027 | B31: Casement / Hinged System | C31: Casement window sash | D31: Approx. 1.05 kg/m | E31: Powder coated | F31: Gulf Extrusions / Equiv. | G31: lm | H31: =ROUND(1.05*(AL_MILL+AL_PC),2) -> 19.43 | I31: 0.05 | J31: =IF(H31="","",ROUND(H31*(1+I31),2)) -> 20.4 | K31: =IF(J31="","",ROUND(J31*(1+OHP),2)) -> 24.48 | L31: =IF(K31="","",ROUND(K31*(1+VAT),2)) -> 25.7 | M31: Indicative | R31: pc
A32: AL-028 | B32: Casement / Hinged System | C32: Window mullion / transom | D32: Approx. 1.30 kg/m | E32: Powder coated | F32: Gulf Extrusions / Equiv. | G32: lm | H32: =ROUND(1.3*(AL_MILL+AL_PC),2) -> 24.05 | I32: 0.05 | J32: =IF(H32="","",ROUND(H32*(1+I32),2)) -> 25.25 | K32: =IF(J32="","",ROUND(J32*(1+OHP),2)) -> 30.3 | L32: =IF(K32="","",ROUND(K32*(1+VAT),2)) -> 31.82 | M32: Indicative | R32: pc
A33: AL-029 | B33: Casement / Hinged System | C33: Thermal-break casement frame | D33: Approx. 1.50 kg/m | E33: Powder coated | F33: Gulf Extrusions / Equiv. | G33: lm | H33: =ROUND(1.5*(AL_MILL+AL_PC+AL_TB),2) -> 36.75 | I33: 0.05 | J33: =IF(H33="","",ROUND(H33*(1+I33),2)) -> 38.59 | K33: =IF(J33="","",ROUND(J33*(1+OHP),2)) -> 46.31 | L33: =IF(K33="","",ROUND(K33*(1+VAT),2)) -> 48.63 | M33: Indicative | R33: pc
A34: AL-030 | B34: Casement / Hinged System | C34: Hinged door frame | D34: Approx. 1.60 kg/m | E34: Powder coated | F34: Gulf Extrusions / Equiv. | G34: lm | H34: =ROUND(1.6*(AL_MILL+AL_PC),2) -> 29.6 | I34: 0.05 | J34: =IF(H34="","",ROUND(H34*(1+I34),2)) -> 31.08 | K34: =IF(J34="","",ROUND(J34*(1+OHP),2)) -> 37.3 | L34: =IF(K34="","",ROUND(K34*(1+VAT),2)) -> 39.17 | M34: Indicative | R34: pc
A35: AL-031 | B35: Casement / Hinged System | C35: Hinged door leaf (stile) | D35: Approx. 2.10 kg/m | E35: Powder coated | F35: Gulf Extrusions / Equiv. | G35: lm | H35: =ROUND(2.1*(AL_MILL+AL_PC),2) -> 38.85 | I35: 0.05 | J35: =IF(H35="","",ROUND(H35*(1+I35),2)) -> 40.79 | K35: =IF(J35="","",ROUND(J35*(1+OHP),2)) -> 48.95 | L35: =IF(K35="","",ROUND(K35*(1+VAT),2)) -> 51.4 | M35: Indicative | R35: pc
A36: AL-032 | B36: Casement / Hinged System | C36: Door bottom rail (deep) | D36: Approx. 2.80 kg/m | E36: Powder coated | F36: Gulf Extrusions / Equiv. | G36: lm | H36: =ROUND(2.8*(AL_MILL+AL_PC),2) -> 51.8 | I36: 0.05 | J36: =IF(H36="","",ROUND(H36*(1+I36),2)) -> 54.39 | K36: =IF(J36="","",ROUND(J36*(1+OHP),2)) -> 65.27 | L36: =IF(K36="","",ROUND(K36*(1+VAT),2)) -> 68.53 | M36: Indicative | R36: pc
A37: AL-033 | B37: Casement / Hinged System | C37: Glazing bead | D37: Approx. 0.25 kg/m | E37: Powder coated | F37: Gulf Extrusions / Equiv. | G37: lm | H37: =ROUND(0.25*(AL_MILL+AL_PC),2) -> 4.63 | I37: 0.05 | J37: =IF(H37="","",ROUND(H37*(1+I37),2)) -> 4.86 | K37: =IF(J37="","",ROUND(J37*(1+OHP),2)) -> 5.83 | L37: =IF(K37="","",ROUND(K37*(1+VAT),2)) -> 6.12 | M37: Indicative | R37: pc
A38: AL-034 | B38: Curtain Wall System | C38: Curtain wall mullion - 150 mm deep | D38: Stick system (approx. 3.80 kg/m) | E38: Powder coated | F38: Gulf Extrusions / Equiv. | G38: lm | H38: =ROUND(3.8*(AL_MILL+AL_PC),2) -> 70.3 | I38: 0.05 | J38: =IF(H38="","",ROUND(H38*(1+I38),2)) -> 73.82 | K38: =IF(J38="","",ROUND(J38*(1+OHP),2)) -> 88.58 | L38: =IF(K38="","",ROUND(K38*(1+VAT),2)) -> 93.01 | M38: Indicative | R38: 150mm pc
A39: AL-035 | B39: Curtain Wall System | C39: Curtain wall mullion - 180 mm deep | D39: Stick system (approx. 4.60 kg/m) | E39: Powder coated | F39: Gulf Extrusions / Equiv. | G39: lm | H39: =ROUND(4.6*(AL_MILL+AL_PC),2) -> 85.1 | I39: 0.05 | J39: =IF(H39="","",ROUND(H39*(1+I39),2)) -> 89.36 | K39: =IF(J39="","",ROUND(J39*(1+OHP),2)) -> 107.23 | L39: =IF(K39="","",ROUND(K39*(1+VAT),2)) -> 112.59 | M39: Indicative | R39: 180mm pc
A40: AL-036 | B40: Curtain Wall System | C40: Curtain wall mullion - 200 mm deep | D40: Stick system (approx. 5.40 kg/m) | E40: Powder coated | F40: Gulf Extrusions / Equiv. | G40: lm | H40: =ROUND(5.4*(AL_MILL+AL_PC),2) -> 99.9 | I40: 0.05 | J40: =IF(H40="","",ROUND(H40*(1+I40),2)) -> 104.9 | K40: =IF(J40="","",ROUND(J40*(1+OHP),2)) -> 125.88 | L40: =IF(K40="","",ROUND(K40*(1+VAT),2)) -> 132.17 | M40: Indicative | R40: 200mm pc
A41: AL-037 | B41: Curtain Wall System | C41: Curtain wall transom - 120 mm | D41: Approx. 2.40 kg/m | E41: Powder coated | F41: Gulf Extrusions / Equiv. | G41: lm | H41: =ROUND(2.4*(AL_MILL+AL_PC),2) -> 44.4 | I41: 0.05 | J41: =IF(H41="","",ROUND(H41*(1+I41),2)) -> 46.62 | K41: =IF(J41="","",ROUND(J41*(1+OHP),2)) -> 55.94 | L41: =IF(K41="","",ROUND(K41*(1+VAT),2)) -> 58.74 | M41: Indicative | R41: 120mm pc
A42: AL-038 | B42: Curtain Wall System | C42: Pressure plate | D42: Approx. 0.55 kg/m | E42: Mill finish | F42: Gulf Extrusions / Equiv. | G42: lm | H42: =ROUND(0.55*AL_MILL,2) -> 8.53 | I42: 0.05 | J42: =IF(H42="","",ROUND(H42*(1+I42),2)) -> 8.96 | K42: =IF(J42="","",ROUND(J42*(1+OHP),2)) -> 10.75 | L42: =IF(K42="","",ROUND(K42*(1+VAT),2)) -> 11.29 | M42: Indicative
